Workbook

Sheet Pivots
A1: GA 55 | F1: Last Update on this sheet | G1: 46110
A3: FY | B3: Pay | C3: DA | D3: HRA | E3: ROP | F3: Bonus | G3: PL Arrer | H3: Sum of CCA | I3: SI Loan | J3: Gross Amount | K3: SI | L3: NPS | M3: GIS | N3: GIS Tax | O3: H.F.R.F. | P3: C M FUND | Q3: GPF 2004 | R3: RGHS | S3: Itax | T3: SI Loan EMI | U3: Total Deduction | V3: Net. Payable Amount | AI3: SI SSO id (new) | AM3: negative value shows extra entries | AZ3: NPS SSOid
A4: 2013-2014 | B4: 46838 | J4: 46838 | U4: 0 | V4: 46838 | X4: SI SSO id (old)
A5: 2014-2015 | B5: 114560 | J5: 114560 | M5: 220 | N5: 27.19 | O5: 538 | U5: 785.19 | V5: 113774.81 | AI5: Sum of Total Premium | AZ5: FY | BA5: Employee Contribution | BB5: Employer Contribution | BC5: Sum of Total
A6: 2015-2016 | B6: 139150 | C6: 69561 | D6: 5846 | E6: -1452 | J6: 213105 | L6: 12801 | M6: 220 | N6: 27.19 | U6: 13048.19 | V6: 200056.81 | X6: Row Labels | Y6: Sum of Trans | Z6: Sum of Premium | AA6: Sum of Incremental Premium | AB6: Sum of Arrers | AC6: Sum of Loan Installment | AD6: Sum of Loan Interest | AE6: Sum of Misc Arrear | AF6: Sum of Service Tax | AG6: Sum of Total Premium | AI6: Row Labels | AJ6: Jan | AK6: Feb | AL6: Mar | AM6: Apr | AN6: May | AO6: Jun | AP6: Jul | AQ6: Aug | AR6: Sep | AS6: Oct | AT6: Nov | AU6: Dec | AW6: Grand Total | AZ6: 2015-2016 | BA6: 12801 | BB6: 12801 | BC6: 25602
A7: 2016-2017 | B7: 142515 | C7: 186335 | D7: 13676 | F7: 3387 | J7: 345913 | K7: 13200 | L7: 31550 | M7: 220 | N7: 31.9 | U7: 45001.9 | V7: 300911.1 | X7: 2016-2017 | Y7: 0 | Z7: 13200 | AA7: 0 | AB7: 0 | AC7: 0 | AD7: 0 | AE7: 0 | AF7: 0 | AG7: 13200 | AI7: 2016-2017 | AJ7: 1100 | AK7: 1100 | AL7: 1100 | AM7: 1100 | AN7: 1100 | AO7: 1100 | AP7: 1100 | AQ7: 1100 | AR7: 1100 | AS7: 2200 | AU7: 1100 | AV7: 0 | AW7: 13200 | AZ7: 2016-2017 | BA7: 31550 | BB7: 31550 | BC7: 63100
A8: 2017-2018 | B8: 238420 | C8: 119658 | D8: 19537 | F8: 6774 | J8: 384389 | K8: 31800 | L8: 34279 | M8: 220 | N8: 33 | U8: 66332 | V8: 318057 | X8: 2017-2018 | Y8: 0 | Z8: 31800 | AA8: 0 | AB8: 0 | AC8: 0 | AD8: 0 | AE8: 0 | AF8: 0 | AG8: 31800 | AI8: 2017-2018 | AJ8: 2650 | AK8: 2650 | AL8: 2650 | AM8: 2650 | AN8: 2650 | AO8: 2650 | AP8: 2650 | AQ8: 2650 | AR8: 2650 | AS8: 2650 | AT8: 2650 | AU8: 2650 | AW8: 31800 | AZ8: 2017-2018 | BA8: 34279 | BB8: 34279 | BC8: 68558
A9: 2018-2019 | B9: 524505 | C9: -106361 | D9: 28128 | F9: 6774 | G9: 287 | J9: 453333 | K9: 36000 | L9: 40111 | M9: 220 | U9: 76331 | V9: 377002 | X9: 2018-2019 | Y9: 0 | Z9: 36000 | AA9: 0 | AB9: 0 | AC9: 0 | AD9: 0 | AE9: 0 | AF9: 0 | AG9: 36000 | AI9: 2018-2019 | AJ9: 3000 | AK9: 6000 | AL9: 3000 | AM9: 3000 | AN9: 3000 | AO9: 3000 | AP9: 3000 | AQ9: 3000 | AR9: 3000 | AS9: 3000 | AT9: 3000 | AV9: 0 | AW9: 36000 | AZ9: 2018-2019 | BA9: 40111 | BB9: 40111 | BC9: 80222
A10: 2019-2020 | B10: 377650 | C10: 47094 | D10: 28992 | F10: 6774 | J10: 460510 | K10: 36000 | L10: 40766 | M10: 220 | U10: 76986 | V10: 383524 | X10: 2019-2020 | Y10: 0 | Z10: 36000 | AA10: 0 | AB10: 0 | AC10: 0 | AD10: 0 | AE10: 0 | AF10: 0 | AG10: 36000 | AI10: 2019-2020 | AJ10: 3000 | AK10: 3000 | AL10: 3000 | AM10: 3000 | AN10: 3000 | AO10: 3000 | AP10: 3000 | AQ10: 3000 | AR10: 3000 | AS10: 3000 | AT10: 3000 | AU10: 3000 | AW10: 36000 | AZ10: 2019-2020 | BA10: 40766 | BB10: 40766 | BC10: 81532
A11: 2020-2021 | B11: 388900 | C11: 78313 | D11: 29857 | F11: 6774 | J11: 503844 | K11: 60000 | L11: 44891 | M11: 220 | P11: 4542 | Q11: 5081 | U11: 114734 | V11: 389110 | X11: 2020-2021 | Y11: 0 | Z11: 55000 | AA11: 0 | AB11: 0 | AC11: 0 | AD11: 0 | AE11: 5000 | AF11: 0 | AG11: 55000 | AI11: 2020-2021 | AJ11: 5000 | AK11: 5000 | AL11: 5000 | AM11: 0 | AN11: 5000 | AO11: 10000 | AP11: 5000 | AQ11: 5000 | AR11: 5000 | AS11: 5000 | AT11: 5000 | AU11: 5000 | AW11: 60000 | AZ11: 2020-2021 | BA11: 44891 | BB11: 44891 | BC11: 89782
A12: 2021-2022 | B12: 399700 | C12: 104125 | D12: 33304 | F12: 6774 | J12: 543903 | K12: 60000 | L12: 48544 | M12: 2100 | Q12: 6003 | R12: 1760 | U12: 118407 | V12: 425496 | X12: 2021-2022 | Y12: 0 | Z12: 60000 | AA12: 0 | AB12: 0 | AC12: 0 | AD12: 0 | AE12: 0 | AF12: 0 | AG12: 60000 | AI12: 2021-2022 | AJ12: 5000 | AK12: 5000 | AL12: 5000 | AM12: 5000 | AN12: 5000 | AO12: 5000 | AP12: 5000 | AQ12: 5000 | AR12: 5000 | AS12: 5000 | AT12: 5000 | AU12: 5000 | AW12: 60000 | AZ12: 2021-2022 | BA12: 44313 | BB12: 44313 | BC12: 88626
A13: 2022-2023 | B13: 419600 | C13: 155572 | D13: 36311 | F13: 6774 | J13: 618257 | K13: 60000 | M13: 1750 | Q13: 31711 | R13: 5496 | U13: 98957 | V13: 519300 | X13: 2022-2023 | Z13: 60000 | AG13: 60000 | AI13: 2022-2023 | AJ13: 5000 | AK13: 5000 | AL13: 5000 | AM13: 5000 | AN13: 5000 | AO13: 5000 | AP13: 5000 | AQ13: 5000 | AR13: 5000 | AS13: 5000 | AT13: 5000 | AU13: 5000 | AW13: 60000 | AZ13: 2022-2023
A14: 2023-2024 | B14: 425600 | C14: 192992 | D14: 38304 | F14: 6774 | J14: 663670 | K14: 60000 | M14: 2100 | Q14: 36798 | R14: 7896 | S14: 10000 | U14: 116794 | V14: 546876 | X14: 2023-2024 | Z14: 60000 | AG14: 60000 | AI14: 2023-2024 | AJ14: 5000 | AK14: 5000 | AL14: 5000 | AM14: 5000 | AN14: 5000 | AO14: 5000 | AP14: 5000 | AQ14: 5000 | AR14: 5000 | AS14: 5000 | AT14: 5000 | AU14: 5000 | AW14: 60000 | AZ14: Grand Total | BA14: 248711 | BB14: 248711 | BC14: 497422
A15: 2024-2025 | B15: 438400 | C15: 230920 | D15: 40932 | F15: 6774 | J15: 717026 | K15: 60000 | M15: 2100 | Q15: 34186 | R15: 7896 | S15: 27500 | U15: 131682 | V15: 585344 | X15: 2024-2025 | Z15: 60000 | AG15: 60000 | AI15: 2024-2025 | AJ15: 5000 | AK15: 5000 | AL15: 5000 | AM15: 5000 | AN15: 5000 | AO15: 5000 | AP15: 5000 | AQ15: 5000 | AR15: 5000 | AS15: 10000 | AU15: 5000 | AV15: 0 | AW15: 60000
A16: 2025-2026 | B16: 470050 | C16: 269124 | D16: 71147 | F16: 6774 | H16: 6839 | I16: 434500 | J16: 1258434 | K16: 60000 | M16: 2100 | Q16: 32528 | R16: 7896 | T16: 65178 | U16: 167702 | V16: 1090732 | X16: 2026-2026 | Z16: 60000 | AC16: 65178 | AG16: 125178 | AI16: 2025-2026 | AJ16: 12242 | AK16: 12242 | AL16: 12242 | AM16: 5000 | AN16: 5000 | AO16: 5000 | AP16: 12242 | AQ16: 12242 | AR16: 12242 | AS16: 12242 | AT16: 12242 | AU16: 12242 | AW16: 125178
A17: Grand Total | B17: 4125888 | C17: 1347333 | D17: 346034 | E17: -1452 | F17: 64353 | G17: 287 | H17: 6839 | I17: 434500 | J17: 6323782 | K17: 477000 | L17: 252942 | M17: 11690 | N17: 119.28 | O17: 538 | P17: 4542 | Q17: 146307 | R17: 30944 | S17: 37500 | T17: 65178 | U17: 1026760.3 | V17: 5297021.7 | X17: Grand Total | Y17: 0 | Z17: 472000 | AA17: 0 | AB17: 0 | AC17: 65178 | AD17: 0 | AE17: 5000 | AF17: 0 | AG17: 537178 | AI17: Grand Total | AJ17: 46992 | AK17: 49992 | AL17: 46992 | AM17: 34750 | AN17: 39750 | AO17: 44750 | AP17: 46992 | AQ17: 46992 | AR17: 46992 | AS17: 53092 | AT17: 40892 | AU17: 43992 | AV17: 0 | AW17: 542178
A31: Pivot On GA-55 Sheet | E31: Pivot On SBBJ Sheet
A33: Row Labels | B33: Sum of Net. Payable Amount | E33: Row Labels | F33: Sum of Credit
A34: Diwali Bonus | B34: 49109 | E34: Diwali Bonus | F34: 49109
A35: 42668 | B35: 3387 | E35: 42668 | F35: 3387
A36: 43021 | B36: 6774 | E36: 43021 | F36: 6774
A37: 43407 | B37: 6774 | E37: 43407 | F37: 6774
A38: 43766 | B38: 6774 | E38: 43766 | F38: 6774
A39: 44153 | B39: 1693 | E39: 44153 | F39: 1693
A40: 44501 | B40: 3387 | E40: 44501 | F40: 3387
A41: 44854 | B41: 5080 | E41: 44854 | F41: 5080
A42: 45239 | B42: 5080 | E42: 45239 | F42: 5080
A43: 45589 | B43: 5080 | E43: 45589 | F43: 5080
A44: 45947 | B44: 5080 | E44: 45947 | F44: 5080
A45: Grand Total | B45: 49109 | E45: Grand Total | F45: 49109

Sheet SI Passbook
K1: Last Update on this sheet | L1: 46110 | N1: correction needed | O1: =IF(L5=0,0,1) -> 0
G3: automatic from GA 55 sheet
K4: sum of si of this sheet | L4: =SUM(H:H) -> 477000
K5: diff (SI of this sheet)-(pivot si) | L5: =L4-GETPIVOTDATA(" SI",Pivots!$A$3) -> 0
A6: S. No. | B6: Bill No | C6: Bill Date | D6: TV No | E6: TV Date | F6: FY | G6: Name of month | H6: SI
A7: ='GA55'!A3 -> 1 | B7: ='GA55'!B3 -> 91 | C7: ='GA55'!C3 -> 41711 | D7: ='GA55'!D3 -> 48188 | E7: ='GA55'!E3 -> 41713 | F7: ='GA55'!F3 -> 2013-2014 | G7: ='GA55'!G3 -> 41518 | H7: ='GA55'!Q3 -> 0
A8: ='GA55'!A4 -> 2 | B8: ='GA55'!B4 -> 92 | C8: ='GA55'!C4 -> 41711 | D8: ='GA55'!D4 -> 48189 | E8: ='GA55'!E4 -> 41713 | F8: ='GA55'!F4 -> 2013-2014 | G8: ='GA55'!G4 -> 41548 | H8: ='GA55'!Q4 -> 0
A9: ='GA55'!A5 -> 3 | B9: ='GA55'!B5 -> 93 | C9: ='GA55'!C5 -> 41711 | D9: ='GA55'!D5 -> 48190 | E9: ='GA55'!E5 -> 41713 | F9: ='GA55'!F5 -> 2013-2014 | G9: ='GA55'!G5 -> 41579 | H9: ='GA55'!Q5 -> 0
A10: ='GA55'!A6 -> 4 | B10: ='GA55'!B6 -> 94 | C10: ='GA55'!C6 -> 41711 | D10: ='GA55'!D6 -> 48191 | E10: ='GA55'!E6 -> 41713 | F10: ='GA55'!F6 -> 2013-2014 | G10: ='GA55'!G6 -> 41609 | H10: ='GA55'!Q6 -> 0
A11: ='GA55'!A7 -> 5 | B11: ='GA55'!B7 -> 95 | C11: ='GA55'!C7 -> 41711 | D11: ='GA55'!D7 -> 48174 | E11: ='GA55'!E7 -> 41713 | F11: ='GA55'!F7 -> 2013-2014 | G11: ='GA55'!G7 -> 41640 | H11: ='GA55'!Q7 -> 0
A12: ='GA55'!A8 -> 6 | B12: ='GA55'!B8 -> 96 | C12: ='GA55'!C8 -> 41711 | D12: ='GA55'!D8 -> 48175 | E12: ='GA55'!E8 -> 41713 | F12: ='GA55'!F8 -> 2013-2014 | G12: ='GA55'!G8 -> 41671 | H12: ='GA55'!Q8 -> 0
A13: ='GA55'!A9 -> 7 | B13: ='GA55'!B9 -> 2 | C13: ='GA55'!C9 -> 41732 | D13: ='GA55'!D9 -> 268 | E13: ='GA55'!E9 -> 41736 | F13: ='GA55'!F9 -> 2014-2015 | G13: ='GA55'!G9 -> 41699 | H13: ='GA55'!Q9 -> 0
A14: ='GA55'!A10 -> 8 | B14: ='GA55'!B10 -> 5 | C14: ='GA55'!C10 -> 41757 | D14: ='GA55'!D10 -> 3591 | E14: ='GA55'!E10 -> 41761 | F14: ='GA55'!F10 -> 2014-2015 | G14: ='GA55'!G10 -> 41730 | H14: ='GA55'!Q10 -> 0
A15: ='GA55'!A11 -> 9 | B15: ='GA55'!B11 -> 11 | C15: ='GA55'!C11 -> 41767 | D15: ='GA55'!D11 -> 11212 | E15: ='GA55'!E11 -> 41822 | F15: ='GA55'!F11 -> 2014-2015 | G15: ='GA55'!G11 -> 41760 | H15: ='GA55'!Q11 -> 0
A16: ='GA55'!A12 -> 10 | B16: ='GA55'!B12 -> 13 | C16: ='GA55'!C12 -> 41820 | D16: ='GA55'!D12 -> 17812 | E16: ='GA55'!E12 -> 41872 | F16: ='GA55'!F12 -> 2014-2015 | G16: ='GA55'!G12 -> 41791 | H16: ='GA55'!Q12 -> 0
A17: ='GA55'!A13 -> 11 | B17: ='GA55'!B13 -> 16 | C17: ='GA55'!C13 -> 41848 | D17: ='GA55'!D13 -> 14902 | E17: ='GA55'!E13 -> 41852 | F17: ='GA55'!F13 -> 2014-2015 | G17: ='GA55'!G13 -> 41821 | H17: ='GA55'!Q13 -> 0
A18: ='GA55'!A14 -> 12 | B18: ='GA55'!B14 -> 19 | C18: ='GA55'!C14 -> 41877 | D18: ='GA55'!D14 -> 19307 | E18: ='GA55'!E14 -> 41883 | F18: ='GA55'!F14 -> 2014-2015 | G18: ='GA55'!G14 -> 41852 | H18: ='GA55'!Q14 -> 0
... A729: ='GA55'!A725 -> 0 | B729: ='GA55'!B725 -> 0 | C729: ='GA55'!C725 -> 0 | D729: ='GA55'!D725 -> 0 | E729: ='GA55'!E725 -> 0 | F729: ='GA55'!F725 -> 0 | G729: ='GA55'!G725 -> 0 | H729: ='GA55'!Q725 -> 0

Sheet GA55
G1: Last Update on this sheet | H1: 46110 | X1: =COUNTA(Table1[GPF 2004]) -> 62 | AC1: =COUNTA(Table1[remark]) -> 8
A2: S. No. | B2: Bill No | C2: Bill Date | D2: TV No | E2: TV Date | F2: FY | G2: Name of month | H2: Pay | I2: DA | J2: HRA | K2: ROP | L2: Bonus | M2: PL Arrer | N2: SI Loan | O2: CCA | P2: Gross Amount | Q2: SI | R2: SI Loan EMI | S2: NPS | T2: GIS | U2: GIS Tax | V2: H.F.R.F. | W2: C M FUND | X2: GPF 2004 | Y2: RGHS | Z2: Itax | AA2: Total Deduction | AB2: Net. Payable Amount | AC2: remark
A3: =IFERROR(VALUE(A2),0)+1 -> 1 | B3: 91 | C3: 41711 | D3: 48188 | E3: 41713 | F3: 2013-2014 | G3: 41518 | H3: 2088 | P3: =SUM(H3:O3) -> 2088 | AA3: =SUM(Q3:Z3) -> 0 | AB3: =P3-AA3 -> 2088
A4: =IFERROR(VALUE(A3),0)+1 -> 2 | B4: 92 | C4: 41711 | D4: 48189 | E4: 41713 | F4: 2013-2014 | G4: 41548 | H4: 8950 | P4: =SUM(H4:O4) -> 8950 | AA4: =SUM(Q4:Z4) -> 0 | AB4: =P4-AA4 -> 8950
A5: =IFERROR(VALUE(A4),0)+1 -> 3 | B5: 93 | C5: 41711 | D5: 48190 | E5: 41713 | F5: 2013-2014 | G5: 41579 | H5: 8950 | P5: =SUM(H5:O5) -> 8950 | AA5: =SUM(Q5:Z5) -> 0 | AB5: =P5-AA5 -> 8950
A6: =IFERROR(VALUE(A5),0)+1 -> 4 | B6: 94 | C6: 41711 | D6: 48191 | E6: 41713 | F6: 2013-2014 | G6: 41609 | H6: 8950 | P6: =SUM(H6:O6) -> 8950 | AA6: =SUM(Q6:Z6) -> 0 | AB6: =P6-AA6 -> 8950
A7: =IFERROR(VALUE(A6),0)+1 -> 5 | B7: 95 | C7: 41711 | D7: 48174 | E7: 41713 | F7: 2013-2014 | G7: 41640 | H7: 8950 | P7: =SUM(H7:O7) -> 8950 | AA7: =SUM(Q7:Z7) -> 0 | AB7: =P7-AA7 -> 8950
A8: =IFERROR(VALUE(A7),0)+1 -> 6 | B8: 96 | C8: 41711 | D8: 48175 | E8: 41713 | F8: 2013-2014 | G8: 41671 | H8: 8950 | P8: =SUM(H8:O8) -> 8950 | AA8: =SUM(Q8:Z8) -> 0 | AB8: =P8-AA8 -> 8950
A9: =IFERROR(VALUE(A8),0)+1 -> 7 | B9: 2 | C9: 41732 | D9: 268 | E9: 41736 | F9: 2014-2015 | G9: 41699 | H9: 8950 | P9: =SUM(H9:O9) -> 8950 | AA9: =SUM(Q9:Z9) -> 0 | AB9: =P9-AA9 -> 8950
A10: =IFERROR(VALUE(A9),0)+1 -> 8 | B10: 5 | C10: 41757 | D10: 3591 | E10: 41761 | F10: 2014-2015 | G10: 41730 | H10: 8950 | P10: =SUM(H10:O10) -> 8950 | T10: 220 | U10: 27.19 | AA10: =SUM(Q10:Z10) -> 247.19 | AB10: =P10-AA10 -> 8702.81
A11: =IFERROR(VALUE(A10),0)+1 -> 9 | B11: 11 | C11: 41767 | D11: 11212 | E11: 41822 | F11: 2014-2015 | G11: 41760 | H11: 8950 | P11: =SUM(H11:O11) -> 8950 | AA11: =SUM(Q11:Z11) -> 0 | AB11: =P11-AA11 -> 8950
A12: =IFERROR(VALUE(A11),0)+1 -> 10 | B12: 13 | C12: 41820 | D12: 17812 | E12: 41872 | F12: 2014-2015 | G12: 41791 | H12: 8950 | P12: =SUM(H12:O12) -> 8950 | AA12: =SUM(Q12:Z12) -> 0 | AB12: =P12-AA12 -> 8950
A13: =IFERROR(VALUE(A12),0)+1 -> 11 | B13: 16 | C13: 41848 | D13: 14902 | E13: 41852 | F13: 2014-2015 | G13: 41821 | H13: 8950 | P13: =SUM(H13:O13) -> 8950 | AA13: =SUM(Q13:Z13) -> 0 | AB13: =P13-AA13 -> 8950
A14: =IFERROR(VALUE(A13),0)+1 -> 12 | B14: 19 | C14: 41877 | D14: 19307 | E14: 41883 | F14: 2014-2015 | G14: 41852 | H14: 8950 | P14: =SUM(H14:O14) -> 8950 | AA14: =SUM(Q14:Z14) -> 0 | AB14: =P14-AA14 -> 8950
A15: =IFERROR(VALUE(A14),0)+1 -> 13 | B15: 25 | C15: 41912 | D15: 25673 | E15: 41920 | F15: 2014-2015 | G15: 41883 | H15: 8950 | P15: =SUM(H15:O15) -> 8950 | V15: 269 | AA15: =SUM(Q15:Z15) -> 269 | AB15: =P15-AA15 -> 8681
A16: =IFERROR(VALUE(A15),0)+1 -> 14 | B16: 34 | C16: 41941 | D16: 30648 | E16: 41944 | F16: 2014-2015 | G16: 41913 | H16: 8950 | P16: =SUM(H16:O16) -> 8950 | V16: 269 | AA16: =SUM(Q16:Z16) -> 269 | AB16: =P16-AA16 -> 8681
A17: =IFERROR(VALUE(A16),0)+1 -> 15 | B17: 71 | C17: 42062 | D17: 43520 | E17: 42073 | F17: 2014-2015 | G17: 41944 | H17: 10740 | P17: =SUM(H17:O17) -> 10740 | AA17: =SUM(Q17:Z17) -> 0 | AB17: =P17-AA17 -> 10740
A18: =IFERROR(VALUE(A17),0)+1 -> 16 | B18: 59 | C18: 41999 | D18: 36092 | E18: 42005 | F18: 2014-2015 | G18: 41974 | H18: 10740 | P18: =SUM(H18:O18) -> 10740 | AA18: =SUM(Q18:Z18) -> 0 | AB18: =P18-AA18 -> 10740
A19: =IFERROR(VALUE(A18),0)+1 -> 17 | B19: 60 | C19: 42032 | D19: 38855 | E19: 42037 | F19: 2014-2015 | G19: 42005 | H19: 10740 | P19: =SUM(H19:O19) -> 10740 | AA19: =SUM(Q19:Z19) -> 0 | AB19: =P19-AA19 -> 10740
A20: =IFERROR(VALUE(A19),0)+1 -> 18 | B20: 70 | C20: 42061 | D20: 42763 | E20: 42066 | F20: 2014-2015 | G20: 42036 | H20: 10740 | P20: =SUM(H20:O20) -> 10740 | AA20: =SUM(Q20:Z20) -> 0 | AB20: =P20-AA20 -> 10740
A21: =IFERROR(VALUE(A20),0)+1 -> 19 | B21: 2 | C21: 42107 | D21: 2031 | E21: 42115 | F21: 2015-2016 | G21: 42064 | H21: 10740 | P21: =SUM(H21:O21) -> 10740 | AA21: =SUM(Q21:Z21) -> 0 | AB21: =P21-AA21 -> 10740
A22: =IFERROR(VALUE(A21),0)+1 -> 20 | B22: 16 | C22: 42123 | D22: 4188 | E22: 42128 | F22: 2015-2016 | G22: 42095 | H22: 10740 | P22: =SUM(H22:O22) -> 10740 | T22: 220 | U22: 27.19 | AA22: =SUM(Q22:Z22) -> 247.19 | AB22: =P22-AA22 -> 10492.81
A23: =IFERROR(VALUE(A22),0)+1 -> 21 | B23: 57 | C23: 42276 | D23: 23777 | E23: 42278 | F23: 2015-2016 | G23: 42125 | H23: 10740 | P23: =SUM(H23:O23) -> 10740 | AA23: =SUM(Q23:Z23) -> 0 | AB23: =P23-AA23 -> 10740
A24: =IFERROR(VALUE(A23),0)+1 -> 22 | B24: 58 | C24: 42276 | D24: 23776 | E24: 42278 | F24: 2015-2016 | G24: 42156 | H24: 10740 | P24: =SUM(H24:O24) -> 10740 | AA24: =SUM(Q24:Z24) -> 0 | AB24: =P24-AA24 -> 10740
A25: =IFERROR(VALUE(A24),0)+1 -> 23 | B25: 38 | C25: 42215 | D25: 15532 | E25: 42217 | F25: 2015-2016 | G25: 42186 | H25: 11820 | P25: =SUM(H25:O25) -> 11820 | AA25: =SUM(Q25:Z25) -> 0 | AB25: =P25-AA25 -> 11820
A26: =IFERROR(VALUE(A25),0)+1 -> 24 | B26: 46 | C26: 42242 | D26: 21641 | E26: 43360 | F26: 2015-2016 | G26: 42217 | H26: 11820 | P26: =SUM(H26:O26) -> 11820 | AA26: =SUM(Q26:Z26) -> 0 | AB26: =P26-AA26 -> 11820
A27: =IFERROR(VALUE(A26),0)+1 -> 25 | B27: 56 | C27: 42276 | D27: 23778 | E27: 42278 | F27: 2015-2016 | G27: 42248 | H27: 11820 | P27: =SUM(H27:O27) -> 11820 | AA27: =SUM(Q27:Z27) -> 0 | AB27: =P27-AA27 -> 11820
A28: =IFERROR(VALUE(A27),0)+1 -> 26 | B28: 64 | C28: 42305 | D28: 42265 | E28: 42390 | F28: 2015-2016 | G28: 42278 | H28: 11820 | P28: =SUM(H28:O28) -> 11820 | AA28: =SUM(Q28:Z28) -> 0 | AB28: =P28-AA28 -> 11820 | AC28: SI, gpf etc sheet me entry check kren
A29: =IFERROR(VALUE(A28),0)+1 -> 27 | B29: 76 | C29: 42336 | D29: 36395 | E29: 42349 | F29: 2015-2016 | G29: 42309 | H29: 11820 | P29: =SUM(H29:O29) -> 11820 | AA29: =SUM(Q29:Z29) -> 0 | AB29: =P29-AA29 -> 11820
A30: =IFERROR(VALUE(A29),0)+1 -> 28 | B30: 96 | C30: 42009 | D30: 49219 | E30: 42432 | F30: 2015-2016 | G30: 42339 | H30: 11170 | I30: 13292 | J30: 1117 | P30: =SUM(H30:O30) -> 25579 | S30: 2446 | AA30: =SUM(Q30:Z30) -> 2446 | AB30: =P30-AA30 -> 23133
A31: =IFERROR(VALUE(A30),0)+1 -> 29 | B31: 115 | C31: 42394 | D31: 43674 | E31: 42401 | F31: 2015-2016 | G31: 42370 | H31: 11170 | I31: 13292 | J31: 1117 | P31: =SUM(H31:O31) -> 25579 | S31: 2446 | AA31: =SUM(Q31:Z31) -> 2446 | AB31: =P31-AA31 -> 23133
A32: =IFERROR(VALUE(A31),0)+1 -> 30 | B32: 131 | C32: 42401 | D32: 48941 | E32: 42431 | F32: 2015-2016 | G32: 42401 | H32: 11170 | I32: 13292 | J32: 1117 | P32: =SUM(H32:O32) -> 25579 | S32: 2446 | AA32: =SUM(Q32:Z32) -> 2446 | AB32: =P32-AA32 -> 23133
A33: =IFERROR(VALUE(A32),0)+1 -> 31 | B33: 61 | C33: 42291 | D33: 26313 | E33: 42294 | F33: 2015-2016 | G33: Oct-15 Salary Arrer | H33: 3580 | P33: =SUM(H33:O33) -> 3580 | AA33: =SUM(Q33:Z33) -> 0 | AB33: =P33-AA33 -> 3580
A34: =IFERROR(VALUE(A33),0)+1 -> 32 | B34: 137 | C34: 44270 | D34: 55291 | E34: 42460 | F34: 2015-2016 | G34: Mar-16 Salary Arrer | I34: 29685 | J34: 2495 | K34: -1452 | P34: =SUM(H34:O34) -> 30728 | S34: 5463 | AA34: =SUM(Q34:Z34) -> 5463 | AB34: =P34-AA34 -> 25265
A35: =IFERROR(VALUE(A34),0)+1 -> 33 | B35: 2 | C35: 42472 | D35: 2179 | E35: 42485 | F35: 2016-2017 | G35: 42430 | H35: 11170 | I35: 13292 | J35: 1117 | P35: =SUM(H35:O35) -> 25579 | Q35: 1100 | S35: 2446 | AA35: =SUM(Q35:Z35) -> 3546 | AB35: =P35-AA35 -> 22033
A36: =IFERROR(VALUE(A35),0)+1 -> 34 | B36: 12 | C36: 42487 | D36: 3158 | E36: 42492 | F36: 2016-2017 | G36: 42461 | H36: 11170 | I36: 13963 | J36: 1117 | P36: =SUM(H36:O36) -> 26250 | Q36: 1100 | S36: 2513 | T36: 220 | U36: 31.9 | AA36: =SUM(Q36:Z36) -> 3864.9 | AB36: =P36-AA36 -> 22385.1
A37: =IFERROR(VALUE(A36),0)+1 -> 35 | B37: 13 | C37: 42544 | D37: 13185 | E37: 42549 | F37: 2016-2017 | G37: 42491 | H37: 11170 | I37: 13963 | J37: 1117 | P37: =SUM(H37:O37) -> 26250 | Q37: 1100 | S37: 2513 | AA37: =SUM(Q37:Z37) -> 3613 | AB37: =P37-AA37 -> 22637
A38: =IFERROR(VALUE(A37),0)+1 -> 36 | B38: 14 | C38: 42548 | D38: 14705 | E38: 42553 | F38: 2016-2017 | G38: 42522 | H38: 11170 | I38: 13963 | J38: 1117 | P38: =SUM(H38:O38) -> 26250 | Q38: 1100 | S38: 2513 | AA38: =SUM(Q38:Z38) -> 3613 | AB38: =P38-AA38 -> 22637
A39: =IFERROR(VALUE(A38),0)+1 -> 37 | B39: 17 | C39: 42583 | D39: 19959 | E39: 42586 | F39: 2016-2017 | G39: 42552 | H39: 11170 | I39: 13963 | J39: 1117 | P39: =SUM(H39:O39) -> 26250 | Q39: 1100 | S39: 2513 | AA39: =SUM(Q39:Z39) -> 3613 | AB39: =P39-AA39 -> 22637
A40: =IFERROR(VALUE(A39),0)+1 -> 38 | B40: 28 | C40: 42605 | D40: 23893 | E40: 42614 | F40: 2016-2017 | G40: 42583 | H40: 11510 | I40: 14388 | J40: 1151 | P40: =SUM(H40:O40) -> 27049 | Q40: 1100 | S40: 2590 | AA40: =SUM(Q40:Z40) -> 3690 | AB40: =P40-AA40 -> 23359
A41: =IFERROR(VALUE(A40),0)+1 -> 39 | B41: 34 | C41: 42639 | D41: 28883 | E41: 42644 | F41: 2016-2017 | G41: 42614 | H41: 11510 | I41: 14388 | J41: 1151 | P41: =SUM(H41:O41) -> 27049 | Q41: 1100 | S41: 2590 | AA41: =SUM(Q41:Z41) -> 3690 | AB41: =P41-AA41 -> 23359
A42: =IFERROR(VALUE(A41),0)+1 -> 40 | B42: 47 | C42: 42667 | D42: 35248 | E42: 42671 | F42: 2016-2017 | G42: 42644 | H42: 11510 | I42: 14388 | J42: 1151 | P42: =SUM(H42:O42) -> 27049 | Q42: 1100 | S42: 2590 | AA42: =SUM(Q42:Z42) -> 3690 | AB42: =P42-AA42 -> 23359
A43: =IFERROR(VALUE(A42),0)+1 -> 41 | B43: 54 | C43: 42698 | D43: 40457 | E43: 42705 | F43: 2016-2017 | G43: 42675 | H43: 11510 | I43: 15193 | J43: 1151 | P43: =SUM(H43:O43) -> 27854 | Q43: 1100 | S43: 2670 | AA43: =SUM(Q43:Z43) -> 3770 | AB43: =P43-AA43 -> 24084
A44: =IFERROR(VALUE(A43),0)+1 -> 42 | B44: 59 | C44: 42732 | D44: 45844 | E44: 42739 | F44: 2016-2017 | G44: 42705 | H44: 11510 | I44: 15193 | J44: 1151 | P44: =SUM(H44:O44) -> 27854 | Q44: 1100 | S44: 2670 | AA44: =SUM(Q44:Z44) -> 3770 | AB44: =P44-AA44 -> 24084
A45: =IFERROR(VALUE(A44),0)+1 -> 43 | B45: 65 | C45: 42762 | D45: 50049 | E45: 42767 | F45: 2016-2017 | G45: 42736 | H45: 11510 | I45: 15193 | J45: 1151 | P45: =SUM(H45:O45) -> 27854 | Q45: 1100 | S45: 2670 | AA45: =SUM(Q45:Z45) -> 3770 | AB45: =P45-AA45 -> 24084
A46: =IFERROR(VALUE(A45),0)+1 -> 44 | B46: 71 | C46: 42795 | D46: 55694 | E46: 42797 | F46: 2016-2017 | G46: 42767 | H46: 11510 | I46: 15193 | J46: 1151 | P46: =SUM(H46:O46) -> 27854 | Q46: 1100 | S46: 2670 | AA46: =SUM(Q46:Z46) -> 3770 | AB46: =P46-AA46 -> 24084
A47: =IFERROR(VALUE(A46),0)+1 -> 45 | B47: 29 | C47: 42606 | D47: 26364 | E47: 42628 | F47: 2016-2017 | G47: Aug-16 Salary Arrer | H47: 340 | I47: 425 | J47: 34 | P47: =SUM(H47:O47) -> 799 | S47: 77 | AA47: =SUM(Q47:Z47) -> 77 | AB47: =P47-AA47 -> 722
A48: =IFERROR(VALUE(A47),0)+1 -> 46 | B48: 43 | C48: 42663 | D48: 33239 | E48: 42668 | F48: 2016-2017 | G48: Diwali Bonus | L48: 3387 | P48: =SUM(H48:O48) -> 3387 | AA48: =SUM(Q48:Z48) -> 0 | AB48: =P48-AA48 -> 3387
A49: =IFERROR(VALUE(A48),0)+1 -> 47 | B49: 41 | C49: 42660 | D49: 37085 | E49: 42683 | F49: 2016-2017 | G49: Oct-16 Salary Arrer | I49: 2013 | P49: =SUM(H49:O49) -> 2013 | S49: 201 | AA49: =SUM(Q49:Z49) -> 201 | AB49: =P49-AA49 -> 1812
A50: =IFERROR(VALUE(A49),0)+1 -> 48 | B50: 72 | C50: 42797 | D50: 56302 | E50: 42801 | F50: 2016-2017 | G50: Surrender Leave | H50: 5755 | I50: 7597 | P50: =SUM(H50:O50) -> 13352 | AA50: =SUM(Q50:Z50) -> 0 | AB50: =P50-AA50 -> 13352
A51: =IFERROR(VALUE(A50),0)+1 -> 49 | B51: 52 | C51: 42695 | D51: 41655 | E51: 42712 | F51: 2016-2017 | G51: DA Arrer July to November | I51: 3220 | P51: =SUM(H51:O51) -> 3220 | S51: 324 | AA51: =SUM(Q51:Z51) -> 324 | AB51: =P51-AA51 -> 2896
A52: =IFERROR(VALUE(A51),0)+1 -> 50 | B52: 1 | C52: 42831 | D52: 727 | E52: 42832 | F52: 2017-2018 | G52: 42795 | H52: 11510 | I52: 15193 | J52: 1151 | P52: =SUM(H52:O52) -> 27854 | Q52: 2650 | S52: 2670 | AA52: =SUM(Q52:Z52) -> 5320 | AB52: =P52-AA52 -> 22534
A53: =IFERROR(VALUE(A52),0)+1 -> 51 | B53: 5 | C53: 42856 | D53: 5192 | E53: 42858 | F53: 2017-2018 | G53: 42826 | H53: 11510 | I53: 15654 | J53: 1151 | P53: =SUM(H53:O53) -> 28315 | Q53: 2650 | S53: 2716 | T53: 220 | U53: 33 | AA53: =SUM(Q53:Z53) -> 5619 | AB53: =P53-AA53 -> 22696
A54: =IFERROR(VALUE(A53),0)+1 -> 52 | B54: 11 | C54: 42884 | D54: 10350 | E54: 42887 | F54: 2017-2018 | G54: 42856 | H54: 11510 | I54: 15654 | J54: 1151 | P54: =SUM(H54:O54) -> 28315 | Q54: 2650 | S54: 2716 | AA54: =SUM(Q54:Z54) -> 5366 | AB54: =P54-AA54 -> 22949
A55: =IFERROR(VALUE(A54),0)+1 -> 53 | B55: 18 | C55: 42915 | D55: 15103 | E55: 42917 | F55: 2017-2018 | G55: 42887 | H55: 11510 | I55: 15654 | J55: 1151 | P55: =SUM(H55:O55) -> 28315 | Q55: 2650 | S55: 2716 | AA55: =SUM(Q55:Z55) -> 5366 | AB55: =P55-AA55 -> 22949
A56: =IFERROR(VALUE(A55),0)+1 -> 54 | B56: 25 | C56: 42944 | D56: 20970 | E56: 42951 | F56: 2017-2018 | G56: 42917 | H56: 11510 | I56: 15654 | J56: 1151 | P56: =SUM(H56:O56) -> 28315 | Q56: 2650 | S56: 2716 | AA56: =SUM(Q56:Z56) -> 5366 | AB56: =P56-AA56 -> 22949
A57: =IFERROR(VALUE(A56),0)+1 -> 55 | B57: 32 | C57: 42979 | D57: 24832 | E57: 42984 | F57: 2017-2018 | G57: 42948 | H57: 11510 | I57: 15654 | J57: 1151 | P57: =SUM(H57:O57) -> 28315 | Q57: 2650 | S57: 2716 | AA57: =SUM(Q57:Z57) -> 5366 | AB57: =P57-AA57 -> 22949
A58: =IFERROR(VALUE(A57),0)+1 -> 56 | B58: 36 | C58: 43011 | D58: 29089 | E58: 43014 | F58: 2017-2018 | G58: 42979 | H58: 11510 | I58: 15654 | J58: 1151 | P58: =SUM(H58:O58) -> 28315 | Q58: 2650 | S58: 2716 | AA58: =SUM(Q58:Z58) -> 5366 | AB58: =P58-AA58 -> 22949
A59: =IFERROR(VALUE(A58),0)+1 -> 57 | B59: 45 | C59: 43041 | D59: 37958 | E59: 43045 | F59: 2017-2018 | G59: 43009 | H59: 11510 | I59: 15999 | J59: 1151 | P59: =SUM(H59:O59) -> 28660 | Q59: 2650 | S59: 2751 | AA59: =SUM(Q59:Z59) -> 5401 | AB59: =P59-AA59 -> 23259
A60: =IFERROR(VALUE(A59),0)+1 -> 58 | B60: 50 | C60: 43067 | D60: 41798 | E60: 43070 | F60: 2017-2018 | G60: 43040 | H60: 11510 | I60: 15999 | J60: 1151 | P60: =SUM(H60:O60) -> 28660 | Q60: 2650 | S60: 2751 | AA60: =SUM(Q60:Z60) -> 5401 | AB60: =P60-AA60 -> 23259
A61: =IFERROR(VALUE(A60),0)+1 -> 59 | B61: 54 | C61: 43098 | D61: 47622 | E61: 43103 | F61: 2017-2018 | G61: 43070 | H61: 11510 | I61: 15999 | J61: 1151 | P61: =SUM(H61:O61) -> 28660 | Q61: 2650 | S61: 2751 | AA61: =SUM(Q61:Z61) -> 5401 | AB61: =P61-AA61 -> 23259
A62: =IFERROR(VALUE(A61),0)+1 -> 60 | B62: 58 | C62: 43125 | D62: 52864 | E62: 43134 | F62: 2017-2018 | G62: 43101 | H62: 28700 | I62: 1435 | J62: 2296 | P62: =SUM(H62:O62) -> 32431 | Q62: 2650 | S62: 3014 | AA62: =SUM(Q62:Z62) -> 5664 | AB62: =P62-AA62 -> 26767
A63: =IFERROR(VALUE(A62),0)+1 -> 61 | B63: 67 | C63: 43159 | D63: 59059 | E63: 43166 | F63: 2017-2018 | G63: 43132 | H63: 28700 | I63: 1435 | J63: 2296 | P63: =SUM(H63:O63) -> 32431 | Q63: 2650 | S63: 3014 | AA63: =SUM(Q63:Z63) -> 5664 | AB63: =P63-AA63 -> 26767
A64: =IFERROR(VALUE(A63),0)+1 -> 62 | B64: 4 | C64: 42846 | D64: 3532 | E64: 42852 | F64: 2017-2018 | G64: Salary Arrer Jan to March | I64: 1383 | P64: =SUM(H64:O64) -> 1383 | S64: 138 | AA64: =SUM(Q64:Z64) -> 138 | AB64: =P64-AA64 -> 1245
A65: =IFERROR(VALUE(A64),0)+1 -> 63 | B65: 4 | C65: 42846 | D65: 3532 | E65: 42852 | F65: 2017-2018 | G65: Surrender Leave Arrer | I65: 230 | P65: =SUM(H65:O65) -> 230 | AA65: =SUM(Q65:Z65) -> 0 | AB65: =P65-AA65 -> 230
A66: =IFERROR(VALUE(A65),0)+1 -> 64 | B66: 39 | C66: 43019 | D66: 32674 | E66: 43021 | F66: 2017-2018 | G66: Diwali Bonus | L66: 6774 | P66: =SUM(H66:O66) -> 6774 | AA66: =SUM(Q66:Z66) -> 0 | AB66: =P66-AA66 -> 6774
A67: =IFERROR(VALUE(A66),0)+1 -> 65 | B67: 38 | C67: 43019 | D67: 32614 | E67: 43021 | F67: 2017-2018 | G67: Salary Arrer Jul to Sep | I67: 1035 | P67: =SUM(H67:O67) -> 1035 | S67: 105 | AA67: =SUM(Q67:Z67) -> 105 | AB67: =P67-AA67 -> 930
A68: =IFERROR(VALUE(A67),0)+1 -> 66 | B68: 60 | C68: 43137 | D68: 54288 | E68: 43146 | F68: 2017-2018 | G68: Salary Arrer from Oct to Dec (7th Pay Comm) | H68: 51570 | I68: -43692 | J68: 3435 | P68: =SUM(H68:O68) -> 11313 | S68: 789 | AA68: =SUM(Q68:Z68) -> 789 | AB68: =P68-AA68 -> 10524
A69: =IFERROR(VALUE(A68),0)+1 -> 67 | B69: 66 | C69: 43159 | D69: 58697 | E69: 43165 | F69: 2017-2018 | G69: Surrender Leave | H69: 14350 | I69: 718 | P69: =SUM(H69:O69) -> 15068 | AA69: =SUM(Q69:Z69) -> 0 | AB69: =P69-AA69 -> 15068
A70: =IFERROR(VALUE(A69),0)+1 -> 68 | B70: 1 | C70: 43200 | D70: 2261 | E70: 43206 | F70: 2018-2019 | G70: 43160 | H70: 28700 | I70: 2009 | J70: 2296 | P70: =SUM(H70:O70) -> 33005 | Q70: 3000 | S70: 3071 | AA70: =SUM(Q70:Z70) -> 6071 | AB70: =P70-AA70 -> 26934
A71: =IFERROR(VALUE(A70),0)+1 -> 69 | B71: 13 | C71: 43249 | D71: 12293 | E71: 43249 | F71: 2018-2019 | G71: 43191 | H71: 28700 | I71: 2009 | J71: 2296 | P71: =SUM(H71:O71) -> 33005 | Q71: 3000 | S71: 3071 | T71: 220 | AA71: =SUM(Q71:Z71) -> 6291 | AB71: =P71-AA71 -> 26714
A72: =IFERROR(VALUE(A71),0)+1 -> 70 | B72: 14 | C72: 43249 | D72: 14665 | E72: 43252 | F72: 2018-2019 | G72: 43221 | H72: 28700 | I72: 2009 | J72: 2296 | P72: =SUM(H72:O72) -> 33005 | Q72: 3000 | S72: 3071 | AA72: =SUM(Q72:Z72) -> 6071 | AB72: =P72-AA72 -> 26934
A73: =IFERROR(VALUE(A72),0)+1 -> 71 | B73: 22 | C73: 43276 | D73: 20799 | E73: 43283 | F73: 2018-2019 | G73: 43252 | H73: 28700 | I73: 2009 | J73: 2296 | P73: =SUM(H73:O73) -> 33005 | Q73: 3000 | S73: 3071 | AA73: =SUM(Q73:Z73) -> 6071 | AB73: =P73-AA73 -> 26934
A74: =IFERROR(VALUE(A73),0)+1 -> 72 | B74: 29 | C74: 43307 | D74: 28948 | E74: 43313 | F74: 2018-2019 | G74: 43282 | H74: 29600 | I74: 2072 | J74: 2368 | P74: =SUM(H74:O74) -> 34040 | Q74: 3000 | S74: 3167 | AA74: =SUM(Q74:Z74) -> 6167 | AB74: =P74-AA74 -> 27873
A75: =IFERROR(VALUE(A74),0)+1 -> 73 | B75: 37 | C75: 43340 | D75: 38148 | E75: 43344 | F75: 2018-2019 | G75: 43313 | H75: 29600 | I75: 2072 | J75: 2368 | P75: =SUM(H75:O75) -> 34040 | Q75: 3000 | S75: 3167 | AA75: =SUM(Q75:Z75) -> 6167 | AB75: =P75-AA75 -> 27873
A76: =IFERROR(VALUE(A75),0)+1 -> 74 | B76: 42 | C76: 43378 | D76: 45759 | E76: 43382 | F76: 2018-2019 | G76: 43344 | H76: 29600 | I76: 2072 | J76: 2368 | P76: =SUM(H76:O76) -> 34040 | Q76: 3000 | S76: 3167 | AA76: =SUM(Q76:Z76) -> 6167 | AB76: =P76-AA76 -> 27873
A77: =IFERROR(VALUE(A76),0)+1 -> 75 | B77: 52 | C77: 43409 | D77: 64791 | E77: 43412 | F77: 2018-2019 | G77: 43374 | H77: 29600 | I77: 2664 | J77: 2368 | P77: =SUM(H77:O77) -> 34632 | Q77: 3000 | S77: 3226 | AA77: =SUM(Q77:Z77) -> 6226 | AB77: =P77-AA77 -> 28406
A78: =IFERROR(VALUE(A77),0)+1 -> 76 | B78: 56 | C78: 43440 | D78: 78389 | E78: 43470 | F78: 2018-2019 | G78: 43405 | H78: 29600 | I78: 2664 | J78: 2368 | P78: =SUM(H78:O78) -> 34632 | Q78: 3000 | S78: 3226 | AA78: =SUM(Q78:Z78) -> 6226 | AB78: =P78-AA78 -> 28406
A79: =IFERROR(VALUE(A78),0)+1 -> 77 | B79: 64 | C79: 43500 | D79: 84676 | E79: 43503 | F79: 2018-2019 | G79: 43435 | H79: 29600 | I79: 2664 | J79: 2368 | P79: =SUM(H79:O79) -> 34632 | Q79: 3000 | S79: 3226 | AA79: =SUM(Q79:Z79) -> 6226 | AB79: =P79-AA79 -> 28406
A80: =IFERROR(VALUE(A79),0)+1 -> 78 | B80: 66 | C80: 43500 | D80: 84675 | E80: 43503 | F80: 2018-2019 | G80: 43466 | H80: 29600 | I80: 2664 | J80: 2368 | P80: =SUM(H80:O80) -> 34632 | Q80: 3000 | S80: 3226 | AA80: =SUM(Q80:Z80) -> 6226 | AB80: =P80-AA80 -> 28406
A81: =IFERROR(VALUE(A80),0)+1 -> 79 | B81: 77 | C81: 43524 | D81: 89654 | E81: 43526 | F81: 2018-2019 | G81: 43497 | H81: 29600 | I81: 2664 | J81: 2368 | P81: =SUM(H81:O81) -> 34632 | Q81: 3000 | S81: 3226 | AA81: =SUM(Q81:Z81) -> 6226 | AB81: =P81-AA81 -> 28406
A82: =IFERROR(VALUE(A81),0)+1 -> 80 | B82: 2 | C82: 44305 | D82: 4380 | E82: 43215 | F82: 2018-2019 | G82: Salary Arrer Jan to March | I82: 1148 | P82: =SUM(H82:O82) -> 1148 | S82: 114 | AA82: =SUM(Q82:Z82) -> 114 | AB82: =P82-AA82 -> 1034
A83: =IFERROR(VALUE(A82),0)+1 -> 81 | B83: 2 | C83: 44305 | D83: 4380 | E83: 43215 | F83: 2018-2019 | G83: Surrender Leave Arrer | M83: 287 | P83: =SUM(H83:O83) -> 287 | AA83: =SUM(Q83:Z83) -> 0 | AB83: =P83-AA83 -> 287
A84: =IFERROR(VALUE(A83),0)+1 -> 82 | B84: 49 | C84: 43405 | D84: 57763 | E84: 43407 | F84: 2018-2019 | G84: Diwali Bonus | L84: 6774 | P84: =SUM(H84:O84) -> 6774 | AA84: =SUM(Q84:Z84) -> 0 | AB84: =P84-AA84 -> 6774
A85: =IFERROR(VALUE(A84),0)+1 -> 83 | B85: 43 | C85: 43382 | D85: 51682 | E85: 43403 | F85: 2018-2019 | G85: DA Salary Arrer Jul to Sep | I85: 1776 | P85: =SUM(H85:O85) -> 1776 | S85: 177 | AA85: =SUM(Q85:Z85) -> 177 | AB85: =P85-AA85 -> 1599
A86: =IFERROR(VALUE(A85),0)+1 -> 84 | B86: 7 | C86: 43229 | D86: 10650 | E86: 43239 | F86: 2018-2019 | G86: Salary Arrer (7th Pay Comm 2nd Installment) | H86: 47432 | I86: -41454 | P86: =SUM(H86:O86) -> 5978 | S86: 573 | AA86: =SUM(Q86:Z86) -> 573 | AB86: =P86-AA86 -> 5405
A87: =IFERROR(VALUE(A86),0)+1 -> 85 | B87: 25 | C87: 43298 | D87: 27703 | E87: 43312 | F87: 2018-2019 | G87: Salary Arrer (7th Pay Comm 3rd Installment) | H87: 47432 | I87: -41454 | P87: =SUM(H87:O87) -> 5978 | S87: 573 | AA87: =SUM(Q87:Z87) -> 573 | AB87: =P87-AA87 -> 5405
A88: =IFERROR(VALUE(A87),0)+1 -> 86 | B88: 61 | C88: 43487 | D88: 81940 | E88: 43496 | F88: 2018-2019 | G88: Surrender Leave | H88: 14800 | I88: 1332 | P88: =SUM(H88:O88) -> 16132 | AA88: =SUM(Q88:Z88) -> 0 | AB88: =P88-AA88 -> 16132
A89: =IFERROR(VALUE(A88),0)+1 -> 87 | B89: 45 | C89: 43388 | D89: 61581 | E89: 43409 | F89: 2018-2019 | G89: Salary Arrer (7th Pay Comm 4th Installment) | H89: 63241 | I89: -55281 | P89: =SUM(H89:O89) -> 7960 | S89: 759 | AA89: =SUM(Q89:Z89) -> 759 | AB89: =P89-AA89 -> 7201
A90: =IFERROR(VALUE(A89),0)+1 -> 88 | B90: 1 | C90: 43558 | D90: 2067 | E90: 43567 | F90: 2019-2020 | G90: 43525 | H90: 29600 | I90: 3552 | J90: 2368 | P90: =SUM(H90:O90) -> 35520 | Q90: 3000 | S90: 3315 | AA90: =SUM(Q90:Z90) -> 6315 | AB90: =P90-AA90 -> 29205
A91: =IFERROR(VALUE(A90),0)+1 -> 89 | B91: 3 | C91: 43584 | D91: 7783 | E91: 43586 | F91: 2019-2020 | G91: 43556 | H91: 29600 | I91: 3552 | J91: 2368 | P91: =SUM(H91:O91) -> 35520 | Q91: 3000 | S91: 3315 | T91: 220 | AA91: =SUM(Q91:Z91) -> 6535 | AB91: =P91-AA91 -> 28985
A92: =IFERROR(VALUE(A91),0)+1 -> 90 | B92: 10 | C92: 43626 | D92: 13083 | E92: 43626 | F92: 2019-2020 | G92: 43586 | H92: 29600 | I92: 3552 | J92: 2368 | P92: =SUM(H92:O92) -> 35520 | Q92: 3000 | S92: 3315 | AA92: =SUM(Q92:Z92) -> 6315 | AB92: =P92-AA92 -> 29205
A93: =IFERROR(VALUE(A92),0)+1 -> 91 | B93: 16 | C93: 43643 | D93: 17962 | E93: 43648 | F93: 2019-2020 | G93: 43617 | H93: 29600 | I93: 3552 | J93: 2368 | P93: =SUM(H93:O93) -> 35520 | Q93: 3000 | S93: 3315 | AA93: =SUM(Q93:Z93) -> 6315 | AB93: =P93-AA93 -> 29205
A94: =IFERROR(VALUE(A93),0)+1 -> 92 | B94: 21 | C94: 43679 | D94: 22832 | E94: 43683 | F94: 2019-2020 | G94: 43647 | H94: 30500 | I94: 3660 | J94: 2440 | P94: =SUM(H94:O94) -> 36600 | Q94: 3000 | S94: 3416 | AA94: =SUM(Q94:Z94) -> 6416 | AB94: =P94-AA94 -> 30184
A95: =IFERROR(VALUE(A94),0)+1 -> 93 | B95: 25 | C95: 43704 | D95: 28118 | E95: 43710 | F95: 2019-2020 | G95: 43678 | H95: 30500 | I95: 3660 | J95: 2440 | P95: =SUM(H95:O95) -> 36600 | Q95: 3000 | S95: 3416 | AA95: =SUM(Q95:Z95) -> 6416 | AB95: =P95-AA95 -> 30184
A96: =IFERROR(VALUE(A95),0)+1 -> 94 | B96: 31 | C96: 43734 | D96: 35390 | E96: 43739 | F96: 2019-2020 | G96: 43709 | H96: 30500 | I96: 3660 | J96: 2440 | P96: =SUM(H96:O96) -> 36600 | Q96: 3000 | S96: 3416 | AA96: =SUM(Q96:Z96) -> 6416 | AB96: =P96-AA96 -> 30184
A97: =IFERROR(VALUE(A96),0)+1 -> 95 | B97: 40 | C97: 43763 | D97: 41375 | E97: 43770 | F97: 2019-2020 | G97: 43739 | H97: 30500 | I97: 3660 | J97: 2440 | P97: =SUM(H97:O97) -> 36600 | Q97: 3000 | S97: 3416 | AA97: =SUM(Q97:Z97) -> 6416 | AB97: =P97-AA97 -> 30184
A98: =IFERROR(VALUE(A97),0)+1 -> 96 | B98: 43 | C98: 43796 | D98: 48035 | E98: 43802 | F98: 2019-2020 | G98: 43770 | H98: 30500 | I98: 3660 | J98: 2440 | P98: =SUM(H98:O98) -> 36600 | Q98: 3000 | S98: 3416 | AA98: =SUM(Q98:Z98) -> 6416 | AB98: =P98-AA98 -> 30184
A99: =IFERROR(VALUE(A98),0)+1 -> 97 | B99: 48 | C99: 43829 | D99: 53590 | E99: 43833 | F99: 2019-2020 | G99: 43800 | H99: 30500 | I99: 3660 | J99: 2440 | P99: =SUM(H99:O99) -> 36600 | Q99: 3000 | S99: 3416 | AA99: =SUM(Q99:Z99) -> 6416 | AB99: =P99-AA99 -> 30184
A100: =IFERROR(VALUE(A99),0)+1 -> 98 | B100: 53 | C100: 43859 | D100: 58674 | E100: 43862 | F100: 2019-2020 | G100: 43831 | H100: 30500 | I100: 3660 | J100: 2440 | P100: =SUM(H100:O100) -> 36600 | Q100: 3000 | S100: 3416 | AA100: =SUM(Q100:Z100) -> 6416 | AB100: =P100-AA100 -> 30184
...

Sheet Leave Balance
B1: Last Update on this sheet | C1: 46110 | G1: difference | H1: =SUM(Z5:Z16) -> 2
L3: Pivot on GA55 | O3: Pivot on Left Table | V3: Manual Entry from Raj Kaj
A4: Leave Type | B4: Leave Earned / Cash Payment or Deductable PL | C4: Year | D4: From | E4: To | F4: No of Days/ Months | G4: Leave Earned / Cash Payment or Deductable PL2 | H4: Balance on retrun from leave column | I4: Remark | J4: matched with service book | L4: Row Labels | M4: Total Times PL Cash | O4: Row Labels | P4: Count | Q4: Sum of Leave | V4: Leave Balance | X4: Difference | Z4: count
A5: PL | B5: Leave Earned | C5: 2015 | D5: 42271 | E5: 42369 | F5: 3 Months and 7 Days | G5: 8 | H5: 8 | J5: Yes | L5: Surrender Leave | M5: 8 | O5: PL | P5: 35 | Q5: 174 | V5: PL | W5: 233 | X5: =GETPIVOTDATA("Sum of Leave",$O$4)-W5 -> -59 | Z5: =IF(X5<>0,1,0) -> 1
A6: PL | B6: Leave Earned | C6: 2016 | D6: 42370 | E6: 42551 | F6: 6 Months | G6: 15 | H6: =Table11[[#This Row],[Leave Earned / Cash Payment or Deductable PL2]]+H5 -> 23 | J6: Yes | L6: Grand Total | M6: 8 | O6: Payment | P6: 8 | Q6: -120 | V6: Medical | W6: 120 | X6: =GETPIVOTDATA("Sum of Leave",$O$15)-W6 -> 20 | Z6: =IF(X6<>0,1,0) -> 1
A7: PL | B7: Leave Earned | C7: 2016 | D7: 42552 | E7: 42735 | F7: 6 Months | G7: 15 | H7: =Table11[[#This Row],[Leave Earned / Cash Payment or Deductable PL2]]+H6 -> 38 | J7: Yes | O7: Leave Earned | P7: 23 | Q7: 328
A8: PL | B8: Leave Earned | C8: 2016 | G8: 10 | H8: =Table11[[#This Row],[Leave Earned / Cash Payment or Deductable PL2]]+H7 -> 48 | I8: Transfer From sangriya to Tibbi | J8: Yes | O8: Deductable | P8: 4 | Q8: -34
A9: PL | B9: Leave Earned | C9: 2017 | D9: 42736 | E9: 42916 | F9: 6 Months | G9: 15 | H9: =Table11[[#This Row],[Leave Earned / Cash Payment or Deductable PL2]]+H8 -> 63 | J9: Yes | O9: Grand Total | P9: 35 | Q9: 174
A10: PL | B10: Payment | C10: 2017 | D10: 42795 | G10: -15 | H10: =Table11[[#This Row],[Leave Earned / Cash Payment or Deductable PL2]]+H9 -> 48 | J10: Yes | V10: Payment of PL In GA 55 and Left most table | X10: =GETPIVOTDATA("Name of month",$L$4,"Name of month","Surrender Leave")-GETPIVOTDATA("Leave Earned / Cash Payment or Deductable PL",$O$4,"Leave Type","PL","Leave Earned / Cash Payment or Deductable PL","Payment") -> 0 | Z10: =IF(X10<>0,1,0) -> 0
A11: PL | B11: Leave Earned | C11: 2017 | D11: 42917 | E11: 43100 | F11: 6 Months | G11: 15 | H11: =Table11[[#This Row],[Leave Earned / Cash Payment or Deductable PL2]]+H10 -> 63 | J11: Yes | V11: (Mohit Attendance Sheet PL)-(This sheet PL) | X11: =IFERROR(GETPIVOTDATA("Present Status",'[1]Summary (New)'!$O$3,"Present Status","PL")+GETPIVOTDATA("Leave Earned / Cash Payment or Deductable PL2",$R$4,"Leave Type","PL","Leave Earned / Cash Payment or Deductable PL","Dedutable"),0) -> 0 | Z11: =IF(X11<>0,1,0) -> 0
A12: PL | B12: Deductable | C12: 2017 | D12: 42955 | E12: 42956 | F12: 2 Days | G12: -2 | H12: =Table11[[#This Row],[Leave Earned / Cash Payment or Deductable PL2]]+H11 -> 61 | I12: 2 Days Strike | J12: Yes
A13: PL | B13: Leave Earned | C13: 2018 | D13: 43101 | E13: 43281 | F13: 6 Months | G13: 15 | H13: =Table11[[#This Row],[Leave Earned / Cash Payment or Deductable PL2]]+H12 -> 76 | J13: Yes
A14: PL | B14: Payment | C14: 2018 | D14: 43132 | G14: -15 | H14: =Table11[[#This Row],[Leave Earned / Cash Payment or Deductable PL2]]+H13 -> 61 | J14: Yes
A15: PL | B15: Leave Earned | C15: 2018 | D15: 43282 | E15: 43465 | F15: 6 Months | G15: 15 | H15: =Table11[[#This Row],[Leave Earned / Cash Payment or Deductable PL2]]+H14 -> 76 | J15: Yes | O15: Row Labels | P15: Count | Q15: Sum of Leave
A16: PL | B16: Deductable | C16: 2018 | D16: 43368 | E16: 43378 | F16: 11 Days | G16: -11 | H16: =Table11[[#This Row],[Leave Earned / Cash Payment or Deductable PL2]]+H15 -> 65 | I16: 11 Days Strike | J16: Yes | O16: Medical | P16: 7 | Q16: 140
A17: PL | B17: Leave Earned | C17: 2019 | D17: 43466 | E17: 43646 | F17: 6 Months | G17: 15 | H17: =Table11[[#This Row],[Leave Earned / Cash Payment or Deductable PL2]]+H16 -> 80 | J17: Yes | O17: Leave Earned | P17: 7 | Q17: 140
A18: PL | B18: Payment | C18: 2019 | D18: 43466 | G18: -15 | H18: =Table11[[#This Row],[Leave Earned / Cash Payment or Deductable PL2]]+H17 -> 65 | J18: Yes | O18: Grand Total | P18: 7 | Q18: 140
A19: PL | B19: Leave Earned | C19: 2019 | D19: 43647 | E19: 43830 | F19: 6 Months | G19: 15 | H19: =Table11[[#This Row],[Leave Earned / Cash Payment or Deductable PL2]]+H18 -> 80 | J19: Yes
A20: PL | B20: Leave Earned | C20: 2020 | D20: 43831 | E20: 44012 | F20: 6 Months | G20: 15 | H20: =Table11[[#This Row],[Leave Earned / Cash Payment or Deductable PL2]]+H19 -> 95 | J20: Yes
A21: PL | B21: Payment | C21: 2020 | D21: 43862 | G21: -15 | H21: =Table11[[#This Row],[Leave Earned / Cash Payment or Deductable PL2]]+H20 -> 80 | J21: Yes
A22: PL | B22: Leave Earned | C22: 2020 | D22: 44013 | E22: 44196 | F22: 6 Months | G22: 15 | H22: =Table11[[#This Row],[Leave Earned / Cash Payment or Deductable PL2]]+H21 -> 95 | J22: Yes
A23: PL | B23: Payment | C23: 2020 | D23: 44044 | G23: -15 | H23: =Table11[[#This Row],[Leave Earned / Cash Payment or Deductable PL2]]+H22 -> 80 | J23: Yes
A24: PL | B24: Leave Earned | C24: 2021 | D24: 44197 | E24: 44377 | F24: 6 Months | G24: 15 | H24: =Table11[[#This Row],[Leave Earned / Cash Payment or Deductable PL2]]+H23 -> 95 | J24: Yes
A25: PL | B25: Payment | C25: 2021 | D25: 44348 | G25: -15 | H25: =Table11[[#This Row],[Leave Earned / Cash Payment or Deductable PL2]]+H24 -> 80 | J25: Yes
A26: PL | B26: Leave Earned | C26: 2021 | D26: 44378 | E26: 44561 | F26: 6 Months | G26: 15 | H26: =Table11[[#This Row],[Leave Earned / Cash Payment or Deductable PL2]]+H25 -> 95 | J26: Yes
A27: PL | B27: Leave Earned | C27: 2022 | D27: 44562 | E27: 44742 | F27: 6 Months | G27: 15 | H27: =Table11[[#This Row],[Leave Earned / Cash Payment or Deductable PL2]]+H26 -> 110 | J27: Yes
A28: PL | B28: Payment | C28: 2022 | D28: 44682 | G28: -15 | H28: =Table11[[#This Row],[Leave Earned / Cash Payment or Deductable PL2]]+H27 -> 95 | J28: Yes
A29: PL | B29: Leave Earned | C29: 2022 | D29: 44743 | E29: 44926 | F29: 6 Months | G29: 15 | H29: =Table11[[#This Row],[Leave Earned / Cash Payment or Deductable PL2]]+H28 -> 110 | J29: Yes
A30: PL | B30: Leave Earned | C30: 2023 | D30: 44927 | E30: 45107 | F30: 6 Months | G30: 15 | H30: =Table11[[#This Row],[Leave Earned / Cash Payment or Deductable PL2]]+H29 -> 125 | J30: Yes
A31: PL | B31: Deductable | C31: 2023 | D31: 45040 | E31: 45048 | F31: 9 Days | G31: -9 | H31: =Table11[[#This Row],[Leave Earned / Cash Payment or Deductable PL2]]+H30 -> 116 | I31: 9 Days Strike | J31: Yes
A32: PL | B32: Leave Earned | C32: 2023 | D32: 45108 | E32: 45291 | F32: 6 Months | G32: 15 | H32: =Table11[[#This Row],[Leave Earned / Cash Payment or Deductable PL2]]+H31 -> 131 | J32: Yes
A33: PL | B33: Leave Earned | C33: 2024 | D33: 45292 | E33: 45473 | F33: 6 Months | G33: 15 | H33: =Table11[[#This Row],[Leave Earned / Cash Payment or Deductable PL2]]+H32 -> 146 | J33: Yes
A34: PL | B34: Leave Earned | C34: 2024 | D34: 45474 | E34: 45657 | F34: 6 Months | G34: 15 | H34: =Table11[[#This Row],[Leave Earned / Cash Payment or Deductable PL2]]+H33 -> 161 | J34: Yes
A35: PL | B35: Leave Earned | C35: 2025 | D35: 45658 | E35: 45838 | F35: 6 Months | G35: 15 | H35: =Table11[[#This Row],[Leave Earned / Cash Payment or Deductable PL2]]+H34 -> 176 | J35: Yes
A36: PL | B36: Payment | C36: 2025 | D36: 45778 | G36: -15 | H36: =Table11[[#This Row],[Leave Earned / Cash Payment or Deductable PL2]]+H35 -> 161 | J36: Yes
A37: PL | B37: Leave Earned | C37: 2025 | D37: 45839 | E37: 46022 | F37: 6 Months | G37: 15 | H37: =Table11[[#This Row],[Leave Earned / Cash Payment or Deductable PL2]]+H36 -> 176 | J37: Yes
A38: PL | B38: Leave Earned | C38: 2025 | G38: 10 | H38: =Table11[[#This Row],[Leave Earned / Cash Payment or Deductable PL2]]+H37 -> 186 | I38: Transfer From Tibbi to Jaipur | J38: Pending to check
A39: PL | B39: Deductable | C39: 2025 | D39: 45985 | E39: 45996 | G39: -12 | H39: =Table11[[#This Row],[Leave Earned / Cash Payment or Deductable PL2]]+H38 -> 174 | I39: in two terms PL taken | J39: Pending to check
A54: Leave Type | B54: Leave Earned / Cash Payment or Deductable PL | C54: Year | D54: From | E54: To | F54: No of Days/ Months | G54: Leave Earned / Cash Payment or Deductable PL2 | H54: Balance on retrun from leave column | I54: Remark | J54: matched with service book
A55: Medical | B55: Leave Earned | D55: 42271 | E55: 42636 | F55: 1 Year | G55: 20 | H55: 20 | J55: Yes
A56: Medical | B56: Leave Earned | D56: 42637 | E56: 43001 | F56: 1 Year | G56: 20 | H56: =G56+H55 -> 40 | J56: Yes
A57: Medical | B57: Leave Earned | D57: 43002 | E57: 43366 | F57: 1 Year | G57: 20 | H57: =G57+H56 -> 60 | J57: Yes
A58: Medical | B58: Leave Earned | D58: 43367 | E58: 43731 | F58: 1 Year | G58: 20 | H58: =G58+H57 -> 80 | J58: Yes
A59: Medical | B59: Leave Earned | D59: 43732 | E59: 44097 | F59: 1 Year | G59: 20 | H59: =G59+H58 -> 100 | J59: Yes
A60: Medical | B60: Leave Earned | D60: 44098 | E60: 44462 | F60: 1 Year | G60: 20 | H60: =G60+H59 -> 120 | J60: Yes
A61: Medical | B61: Leave Earned | D61: 44463 | E61: 44827 | F61: 1 Year | G61: 20 | H61: =G61+H60 -> 140 | J61: Yes
A62: Medical | B62: Leave Earned | D62: 44828 | E62: 45192 | F62: 1 Year | G62: 20 | H62: =G62+H61 -> 160 | J62: Yes
A63: Medical | B63: Leave Earned | D63: 45193 | E63: 45558 | F63: 1 Year | G63: 20 | H63: =G63+H62 -> 180 | J63: Yes
A64: Medical | B64: Leave Earned | D64: 45559 | E64: 45923 | F64: 1 Year | G64: 20 | H64: =G64+H63 -> 200
A65: Medical | B65: Leave Earned | D65: 45924 | E65: 46288 | F65: 1 Year | G65: 20 | H65: =G65+H64 -> 220

Sheet GPF
A1: =COUNTA(A4:A1048576) -> 49 | B1: =COUNTA(B4:B1048576) -> 49 | C1: =COUNTA(C4:C1048576) -> 49 | D1: =COUNTA(D4:D1048576) -> 49 | E1: =COUNTA(E4:E1048576) -> 49 | P1: =MAX(O:O) -> 225562.72 | R1: =COUNTA(R4:R1048576) -> 107
A2: From GA-55 of excel sheet | F2: From SIPF Portal (new) | O2: Calculations | S2: =SUM(S4:S1048576) -> 57 | U2: Last Update on this sheet | V2: 46110
A3: S. No. | B3: Bill No | C3: Bill Date | D3: TV No | E3: TV Date | F3: M | G3: FY | H3: Month | I3: GPF Deduction | J3: DA Arrears | K3: Withdrawl /Claim | L3: Withdrawl Repayment | M3: Other Arrears | N3: Total | O3: New Balance | P3: Interest Rate | Q3: Interest | R3: Remark | S3: Correction Needed | T3: interest by portal
F4: Apr | G4: 2012-2013 | H4: =CONCATENATE(F4,"-",RIGHT(LEFT(G4,4),2)) -> Apr-12 | N4: =I4+J4+L4+M4-K4 -> 0 | O4: =N4 -> 0 | P4: 0.088 | Q4: =O4*P4/12 -> 0 | S4: =IF(OR(R4="",R4="ok"),0,1) -> 0 | AB4: Sum of Total | AP4: Sum of Interest
F5: May | G5: =G4 -> 2012-2013 | H5: =CONCATENATE(F5,"-",RIGHT(LEFT(G5,4),2)) -> May-12 | N5: =I5+J5+L5+M5-K5 -> 0 | O5: =O4+N5 -> 0 | P5: 0.088 | Q5: =O5*P5/12 -> 0 | S5: =IF(OR(R5="",R5="ok"),0,1) -> 0 | AB5: Row Labels | AC5: Jan | AD5: Feb | AE5: Mar | AF5: Apr | AG5: May | AH5: Jun | AI5: Jul | AJ5: Aug | AK5: Sep | AL5: Oct | AM5: Nov | AN5: Dec | AO5: Grand Total | AP5: Row Labels | AQ5: (blank) | AR5: Grand Total | AS5: New Balance
F6: Jun | G6: =G5 -> 2012-2013 | H6: =CONCATENATE(F6,"-",RIGHT(LEFT(G6,4),2)) -> Jun-12 | N6: =I6+J6+L6+M6-K6 -> 0 | O6: =O5+N6 -> 0 | P6: 0.088 | Q6: =O6*P6/12 -> 0 | S6: =IF(OR(R6="",R6="ok"),0,1) -> 0 | AB6: 2012-2013 | AC6: 0 | AD6: 0 | AE6: 0 | AF6: 0 | AG6: 0 | AH6: 0 | AI6: 0 | AJ6: 0 | AK6: 0 | AL6: 0 | AM6: 0 | AN6: 0 | AO6: 0 | AP6: 2012-2013 | AQ6: 0 | AR6: 0 | AS6: =AO6+AR6 -> 0
F7: Jul | G7: =G6 -> 2012-2013 | H7: =CONCATENATE(F7,"-",RIGHT(LEFT(G7,4),2)) -> Jul-12 | N7: =I7+J7+L7+M7-K7 -> 0 | O7: =O6+N7 -> 0 | P7: 0.088 | Q7: =O7*P7/12 -> 0 | S7: =IF(OR(R7="",R7="ok"),0,1) -> 0 | AB7: 2013-2014 | AC7: 0 | AD7: 0 | AE7: 0 | AF7: 0 | AG7: 0 | AH7: 0 | AI7: 0 | AJ7: 0 | AK7: 0 | AL7: 0 | AM7: 0 | AN7: 0 | AO7: 0 | AP7: 2013-2014 | AQ7: 0 | AR7: 0 | AS7: =AO7+AR7 -> 0
F8: Aug | G8: =G7 -> 2012-2013 | H8: =CONCATENATE(F8,"-",RIGHT(LEFT(G8,4),2)) -> Aug-12 | N8: =I8+J8+L8+M8-K8 -> 0 | O8: =O7+N8 -> 0 | P8: 0.088 | Q8: =O8*P8/12 -> 0 | S8: =IF(OR(R8="",R8="ok"),0,1) -> 0 | AB8: 2014-2015 | AC8: 0 | AD8: 0 | AE8: 0 | AF8: 0 | AG8: 0 | AH8: 0 | AI8: 0 | AJ8: 0 | AK8: 0 | AL8: 0 | AM8: 0 | AN8: 0 | AO8: 0 | AP8: 2014-2015 | AQ8: 0 | AR8: 0 | AS8: =AO8+AR8 -> 0
F9: Sep | G9: =G8 -> 2012-2013 | H9: =CONCATENATE(F9,"-",RIGHT(LEFT(G9,4),2)) -> Sep-12 | N9: =I9+J9+L9+M9-K9 -> 0 | O9: =O8+N9 -> 0 | P9: 0.088 | Q9: =O9*P9/12 -> 0 | S9: =IF(OR(R9="",R9="ok"),0,1) -> 0 | AB9: 2015-2016 | AC9: 0 | AD9: 0 | AE9: 0 | AF9: 0 | AG9: 0 | AH9: 0 | AI9: 0 | AJ9: 0 | AK9: 0 | AL9: 0 | AM9: 0 | AN9: 0 | AO9: 0 | AP9: 2015-2016 | AQ9: 0 | AR9: 0 | AS9: =AO9+AR9 -> 0
F10: Oct | G10: =G9 -> 2012-2013 | H10: =CONCATENATE(F10,"-",RIGHT(LEFT(G10,4),2)) -> Oct-12 | N10: =I10+J10+L10+M10-K10 -> 0 | O10: =O9+N10 -> 0 | P10: 0.088 | Q10: =O10*P10/12 -> 0 | S10: =IF(OR(R10="",R10="ok"),0,1) -> 0 | AB10: 2016-2017 | AC10: 0 | AD10: 0 | AE10: 0 | AF10: 0 | AG10: 0 | AH10: 0 | AI10: 0 | AJ10: 0 | AK10: 0 | AL10: 0 | AM10: 0 | AN10: 0 | AO10: 0 | AP10: 2016-2017 | AQ10: 0 | AR10: 0 | AS10: =AO10+AR10 -> 0
F11: Nov | G11: =G10 -> 2012-2013 | H11: =CONCATENATE(F11,"-",RIGHT(LEFT(G11,4),2)) -> Nov-12 | N11: =I11+J11+L11+M11-K11 -> 0 | O11: =O10+N11 -> 0 | P11: 0.088 | Q11: =O11*P11/12 -> 0 | S11: =IF(OR(R11="",R11="ok"),0,1) -> 0 | AB11: 2017-2018 | AC11: 0 | AD11: 0 | AE11: 0 | AF11: 0 | AG11: 0 | AH11: 0 | AI11: 0 | AJ11: 0 | AK11: 0 | AL11: 0 | AM11: 0 | AN11: 0 | AO11: 0 | AP11: 2017-2018 | AQ11: 0 | AR11: 0 | AS11: =AO11+AR11 -> 0
F12: Dec | G12: =G11 -> 2012-2013 | H12: =CONCATENATE(F12,"-",RIGHT(LEFT(G12,4),2)) -> Dec-12 | N12: =I12+J12+L12+M12-K12 -> 0 | O12: =O11+N12 -> 0 | P12: 0.088 | Q12: =O12*P12/12 -> 0 | S12: =IF(OR(R12="",R12="ok"),0,1) -> 0 | AB12: 2018-2019 | AC12: 0 | AD12: 0 | AE12: 0 | AF12: 0 | AG12: 0 | AH12: 0 | AI12: 0 | AJ12: 0 | AK12: 0 | AL12: 0 | AM12: 0 | AN12: 0 | AO12: 0 | AP12: 2018-2019 | AQ12: 0 | AR12: 0 | AS12: =AO12+AR12 -> 0
F13: Jan | G13: =G12 -> 2012-2013 | H13: =CONCATENATE(F13,"-",RIGHT(RIGHT(G13,4),2)) -> Jan-13 | N13: =I13+J13+L13+M13-K13 -> 0 | O13: =O12+N13 -> 0 | P13: 0.088 | Q13: =O13*P13/12 -> 0 | S13: =IF(OR(R13="",R13="ok"),0,1) -> 0 | AB13: 2019-2020 | AC13: 0 | AD13: 0 | AE13: 0 | AF13: 0 | AG13: 0 | AH13: 0 | AI13: 0 | AJ13: 0 | AK13: 0 | AL13: 0 | AM13: 0 | AN13: 0 | AO13: 0 | AP13: 2019-2020 | AQ13: 0 | AR13: 0 | AS13: =AO13+AR13 -> 0
F14: Feb | G14: =G13 -> 2012-2013 | H14: =CONCATENATE(F14,"-",RIGHT(RIGHT(G14,4),2)) -> Feb-13 | N14: =I14+J14+L14+M14-K14 -> 0 | O14: =O13+N14 -> 0 | P14: 0.088 | Q14: =O14*P14/12 -> 0 | S14: =IF(OR(R14="",R14="ok"),0,1) -> 0 | AB14: 2020-2021 | AC14: 0 | AD14: 0 | AE14: 0 | AF14: 0 | AG14: 0 | AH14: 0 | AI14: 0 | AJ14: 0 | AK14: 0 | AL14: 0 | AM14: 5081 | AN14: 0 | AO14: 5081 | AP14: 2020-2021 | AQ14: 150.31292 | AR14: 150.31292 | AS14: =AO14+AR14 -> 5231.3129
F15: Mar | G15: =G14 -> 2012-2013 | H15: =CONCATENATE(F15,"-",RIGHT(RIGHT(G15,4),2)) -> Mar-13 | N15: =I15+J15+L15+M15-K15 -> 0 | O15: =O14+N15 -> 0 | P15: 0.088 | Q15: =O15*P15/12 -> 0 | S15: =IF(OR(R15="",R15="ok"),0,1) -> 0 | AB15: 2021-2022 | AC15: 0 | AD15: 0 | AE15: 0 | AF15: 0 | AG15: 0 | AH15: 0 | AI15: 0 | AJ15: 0 | AK15: 0 | AL15: 0 | AM15: 3387 | AN15: 2616 | AO15: 6003 | AP15: 2021-2022 | AQ15: 533.53397 | AR15: 533.53397 | AS15: =AO15+AR15 -> 6536.534
G16: =G15 -> 2012-2013 | I16: =SUM(I4:I15) -> 0 | J16: =SUM(J4:J15) -> 0 | K16: =SUM(K4:K15) -> 0 | L16: =SUM(L4:L15) -> 0 | M16: =SUM(M4:M15) -> 0 | N16: =SUM(N4:N15) -> 0 | O16: =O15+Q16 -> 0 | Q16: =SUM(Q4:Q15) -> 0 | S16: =IF(OR(R16="",R16="ok"),0,1) -> 0 | AB16: 2022-2023 | AC16: 2114 | AD16: 2100 | AE16: 2100 | AF16: 0 | AG16: 0 | AH16: 7107 | AI16: 2100 | AJ16: 2100 | AK16: 2100 | AL16: 3794 | AM16: 2100 | AN16: 6096 | AO16: 31711 | AP16: 2022-2023 | AQ16: 1970.0971 | AR16: 1970.0971 | AS16: =AO16+AR16 -> 33681.097
F17: Apr | G17: =CONCATENATE(RIGHT(G4,4),"-",RIGHT(G4,4)+1) -> 2013-2014 | H17: =CONCATENATE(F17,"-",RIGHT(LEFT(G17,4),2)) -> Apr-13 | N17: =I17+J17+L17+M17-K17 -> 0 | O17: =O16+N17 -> 0 | P17: 0.087 | Q17: =O17*P17/12 -> 0 | S17: =IF(OR(R17="",R17="ok"),0,1) -> 0 | AB17: 2023-2024 | AC17: 7828 | AD17: 2100 | AE17: 2100 | AF17: 2100 | AG17: 2100 | AH17: 2100 | AI17: 2100 | AJ17: 6276 | AK17: 2100 | AL17: 2100 | AM17: 3794 | AN17: 2100 | AO17: 36798 | AP17: 2023-2024 | AQ17: 4545.4752 | AR17: 4545.4752 | AS17: =AO17+AR17 -> 41343.475
F18: May | G18: =G17 -> 2013-2014 | H18: =CONCATENATE(F18,"-",RIGHT(LEFT(G18,4),2)) -> May-13 | N18: =I18+J18+L18+M18-K18 -> 0 | O18: =O17+N18 -> 0 | P18: 0.087 | Q18: =O18*P18/12 -> 0 | S18: =IF(OR(R18="",R18="ok"),0,1) -> 0 | AB18: 2024-2025 | AC18: 2100 | AD18: 2100 | AE18: 2100 | AF18: 2100 | AG18: 4964 | AH18: 2100 | AI18: 2100 | AJ18: 2100 | AK18: 2100 | AL18: 5894 | AM18: 4428 | AN18: 2100 | AO18: 34186 | AP18: 2024-2025 | AQ18: 7521.3674 | AR18: 7521.3674 | AS18: =AO18+AR18 -> 41707.367
F19: Jun | G19: =G18 -> 2013-2014 | H19: =CONCATENATE(F19,"-",RIGHT(LEFT(G19,4),2)) -> Jun-13 | N19: =I19+J19+L19+M19-K19 -> 0 | O19: =O18+N19 -> 0 | P19: 0.087 | Q19: =O19*P19/12 -> 0 | S19: =IF(OR(R19="",R19="ok"),0,1) -> 0 | AB19: 2025-2026 | AC19: 2100 | AD19: 2100 | AE19: 2100 | AF19: 4314 | AG19: 2100 | AH19: 2100 | AI19: 2100 | AJ19: 2100 | AK19: 2100 | AL19: 3794 | AM19: 5520 | AN19: 2100 | AO19: 32528 | AP19: Grand Total | AQ19: 14720.787 | AR19: 14720.787 | AS19: =AO19+AR19 -> 47248.787
F20: Jul | G20: =G19 -> 2013-2014 | H20: =CONCATENATE(F20,"-",RIGHT(LEFT(G20,4),2)) -> Jul-13 | N20: =I20+J20+L20+M20-K20 -> 0 | O20: =O19+N20 -> 0 | P20: 0.087 | Q20: =O20*P20/12 -> 0 | S20: =IF(OR(R20="",R20="ok"),0,1) -> 0 | AB20: 2026-2027 | AC20: 0 | AD20: 0 | AE20: 0 | AF20: 0 | AG20: 0 | AH20: 0 | AI20: 0 | AJ20: 0 | AK20: 0 | AL20: 0 | AM20: 0 | AN20: 0 | AO20: 0
F21: Aug | G21: =G20 -> 2013-2014 | H21: =CONCATENATE(F21,"-",RIGHT(LEFT(G21,4),2)) -> Aug-13 | N21: =I21+J21+L21+M21-K21 -> 0 | O21: =O20+N21 -> 0 | P21: 0.087 | Q21: =O21*P21/12 -> 0 | S21: =IF(OR(R21="",R21="ok"),0,1) -> 0 | AB21: 2027-2028 | AC21: 0 | AD21: 0 | AE21: 0 | AF21: 0 | AG21: 0 | AH21: 0 | AI21: 0 | AJ21: 0 | AK21: 0 | AL21: 0 | AM21: 0 | AN21: 0 | AO21: 0
F22: Sep | G22: =G21 -> 2013-2014 | H22: =CONCATENATE(F22,"-",RIGHT(LEFT(G22,4),2)) -> Sep-13 | N22: =I22+J22+L22+M22-K22 -> 0 | O22: =O21+N22 -> 0 | P22: 0.087 | Q22: =O22*P22/12 -> 0 | S22: =IF(OR(R22="",R22="ok"),0,1) -> 0 | AB22: 2028-2029 | AC22: 0 | AD22: 0 | AE22: 0 | AF22: 0 | AG22: 0 | AH22: 0 | AI22: 0 | AJ22: 0 | AK22: 0 | AL22: 0 | AM22: 0 | AN22: 0 | AO22: 0
F23: Oct | G23: =G22 -> 2013-2014 | H23: =CONCATENATE(F23,"-",RIGHT(LEFT(G23,4),2)) -> Oct-13 | N23: =I23+J23+L23+M23-K23 -> 0 | O23: =O22+N23 -> 0 | P23: 0.087 | Q23: =O23*P23/12 -> 0 | S23: =IF(OR(R23="",R23="ok"),0,1) -> 0 | AB23: 2029-2030 | AC23: 0 | AD23: 0 | AE23: 0 | AF23: 0 | AG23: 0 | AH23: 0 | AI23: 0 | AJ23: 0 | AK23: 0 | AL23: 0 | AM23: 0 | AN23: 0 | AO23: 0
F24: Nov | G24: =G23 -> 2013-2014 | H24: =CONCATENATE(F24,"-",RIGHT(LEFT(G24,4),2)) -> Nov-13 | N24: =I24+J24+L24+M24-K24 -> 0 | O24: =O23+N24 -> 0 | P24: 0.087 | Q24: =O24*P24/12 -> 0 | S24: =IF(OR(R24="",R24="ok"),0,1) -> 0 | AB24: Grand Total | AC24: 14142 | AD24: 8400 | AE24: 8400 | AF24: 8514 | AG24: 9164 | AH24: 13407 | AI24: 8400 | AJ24: 12576 | AK24: 8400 | AL24: 15582 | AM24: 24310 | AN24: 15012 | AO24: 146307
F25: Dec | G25: =G24 -> 2013-2014 | H25: =CONCATENATE(F25,"-",RIGHT(LEFT(G25,4),2)) -> Dec-13 | N25: =I25+J25+L25+M25-K25 -> 0 | O25: =O24+N25 -> 0 | P25: 0.087 | Q25: =O25*P25/12 -> 0 | S25: =IF(OR(R25="",R25="ok"),0,1) -> 0
F26: Jan | G26: =G25 -> 2013-2014 | H26: =CONCATENATE(F26,"-",RIGHT(RIGHT(G26,4),2)) -> Jan-14 | N26: =I26+J26+L26+M26-K26 -> 0 | O26: =O25+N26 -> 0 | P26: 0.087 | Q26: =O26*P26/12 -> 0 | S26: =IF(OR(R26="",R26="ok"),0,1) -> 0
F27: Feb | G27: =G26 -> 2013-2014 | H27: =CONCATENATE(F27,"-",RIGHT(RIGHT(G27,4),2)) -> Feb-14 | N27: =I27+J27+L27+M27-K27 -> 0 | O27: =O26+N27 -> 0 | P27: 0.087 | Q27: =O27*P27/12 -> 0 | S27: =IF(OR(R27="",R27="ok"),0,1) -> 0
F28: Mar | G28: =G27 -> 2013-2014 | H28: =CONCATENATE(F28,"-",RIGHT(RIGHT(G28,4),2)) -> Mar-14 | N28: =I28+J28+L28+M28-K28 -> 0 | O28: =O27+N28 -> 0 | P28: 0.087 | Q28: =O28*P28/12 -> 0 | S28: =IF(OR(R28="",R28="ok"),0,1) -> 0
G29: =G28 -> 2013-2014 | I29: =SUM(I17:I28) -> 0 | J29: =SUM(J17:J28) -> 0 | K29: =SUM(K17:K28) -> 0 | L29: =SUM(L17:L28) -> 0 | M29: =SUM(M17:M28) -> 0 | N29: =SUM(N17:N28) -> 0 | O29: =O28+Q29 -> 0 | Q29: =SUM(Q17:Q28) -> 0 | S29: =IF(OR(R29="",R29="ok"),0,1) -> 0
F30: Apr | G30: =CONCATENATE(RIGHT(G17,4),"-",RIGHT(G17,4)+1) -> 2014-2015 | H30: =CONCATENATE(F30,"-",RIGHT(LEFT(G30,4),2)) -> Apr-14 | N30: =I30+J30+L30+M30-K30 -> 0 | O30: =O29+N30 -> 0 | P30: 0.087 | Q30: =O30*P30/12 -> 0 | S30: =IF(OR(R30="",R30="ok"),0,1) -> 0
F31: May | G31: =G30 -> 2014-2015 | H31: =CONCATENATE(F31,"-",RIGHT(LEFT(G31,4),2)) -> May-14 | N31: =I31+J31+L31+M31-K31 -> 0 | O31: =O30+N31 -> 0 | P31: 0.087 | Q31: =O31*P31/12 -> 0 | S31: =IF(OR(R31="",R31="ok"),0,1) -> 0
F32: Jun | G32: =G31 -> 2014-2015 | H32: =CONCATENATE(F32,"-",RIGHT(LEFT(G32,4),2)) -> Jun-14 | N32: =I32+J32+L32+M32-K32 -> 0 | O32: =O31+N32 -> 0 | P32: 0.087 | Q32: =O32*P32/12 -> 0 | S32: =IF(OR(R32="",R32="ok"),0,1) -> 0
F33: Jul | G33: =G32 -> 2014-2015 | H33: =CONCATENATE(F33,"-",RIGHT(LEFT(G33,4),2)) -> Jul-14 | N33: =I33+J33+L33+M33-K33 -> 0 | O33: =O32+N33 -> 0 | P33: 0.087 | Q33: =O33*P33/12 -> 0 | S33: =IF(OR(R33="",R33="ok"),0,1) -> 0
F34: Aug | G34: =G33 -> 2014-2015 | H34: =CONCATENATE(F34,"-",RIGHT(LEFT(G34,4),2)) -> Aug-14 | N34: =I34+J34+L34+M34-K34 -> 0 | O34: =O33+N34 -> 0 | P34: 0.087 | Q34: =O34*P34/12 -> 0 | S34: =IF(OR(R34="",R34="ok"),0,1) -> 0
F35: Sep | G35: =G34 -> 2014-2015 | H35: =CONCATENATE(F35,"-",RIGHT(LEFT(G35,4),2)) -> Sep-14 | N35: =I35+J35+L35+M35-K35 -> 0 | O35: =O34+N35 -> 0 | P35: 0.087 | Q35: =O35*P35/12 -> 0 | S35: =IF(OR(R35="",R35="ok"),0,1) -> 0
F36: Oct | G36: =G35 -> 2014-2015 | H36: =CONCATENATE(F36,"-",RIGHT(LEFT(G36,4),2)) -> Oct-14 | N36: =I36+J36+L36+M36-K36 -> 0 | O36: =O35+N36 -> 0 | P36: 0.087 | Q36: =O36*P36/12 -> 0 | S36: =IF(OR(R36="",R36="ok"),0,1) -> 0
F37: Nov | G37: =G36 -> 2014-2015 | H37: =CONCATENATE(F37,"-",RIGHT(LEFT(G37,4),2)) -> Nov-14 | N37: =I37+J37+L37+M37-K37 -> 0 | O37: =O36+N37 -> 0 | P37: 0.087 | Q37: =O37*P37/12 -> 0 | S37: =IF(OR(R37="",R37="ok"),0,1) -> 0
F38: Dec | G38: =G37 -> 2014-2015 | H38: =CONCATENATE(F38,"-",RIGHT(LEFT(G38,4),2)) -> Dec-14 | N38: =I38+J38+L38+M38-K38 -> 0 | O38: =O37+N38 -> 0 | P38: 0.087 | Q38: =O38*P38/12 -> 0 | S38: =IF(OR(R38="",R38="ok"),0,1) -> 0
F39: Jan | G39: =G38 -> 2014-2015 | H39: =CONCATENATE(F39,"-",RIGHT(RIGHT(G39,4),2)) -> Jan-15 | N39: =I39+J39+L39+M39-K39 -> 0 | O39: =O38+N39 -> 0 | P39: 0.087 | Q39: =O39*P39/12 -> 0 | S39: =IF(OR(R39="",R39="ok"),0,1) -> 0
F40: Feb | G40: =G39 -> 2014-2015 | H40: =CONCATENATE(F40,"-",RIGHT(RIGHT(G40,4),2)) -> Feb-15 | N40: =I40+J40+L40+M40-K40 -> 0 | O40: =O39+N40 -> 0 | P40: 0.087 | Q40: =O40*P40/12 -> 0 | S40: =IF(OR(R40="",R40="ok"),0,1) -> 0
F41: Mar | G41: =G40 -> 2014-2015 | H41: =CONCATENATE(F41,"-",RIGHT(RIGHT(G41,4),2)) -> Mar-15 | N41: =I41+J41+L41+M41-K41 -> 0 | O41: =O40+N41 -> 0 | P41: 0.087 | Q41: =O41*P41/12 -> 0 | S41: =IF(OR(R41="",R41="ok"),0,1) -> 0
G42: =G41 -> 2014-2015 | I42: =SUM(I30:I41) -> 0 | J42: =SUM(J30:J41) -> 0 | K42: =SUM(K30:K41) -> 0 | L42: =SUM(L30:L41) -> 0 | M42: =SUM(M30:M41) -> 0 | N42: =SUM(N30:N41) -> 0 | O42: =O41+Q42 -> 0 | Q42: =SUM(Q30:Q41) -> 0 | S42: =IF(OR(R42="",R42="ok"),0,1) -> 0
F43: Apr | G43: =CONCATENATE(RIGHT(G30,4),"-",RIGHT(G30,4)+1) -> 2015-2016 | H43: =CONCATENATE(F43,"-",RIGHT(LEFT(G43,4),2)) -> Apr-15 | N43: =I43+J43+L43+M43-K43 -> 0 | O43: =O42+N43 -> 0 | P43: 0.087 | Q43: =O43*P43/12 -> 0 | S43: =IF(OR(R43="",R43="ok"),0,1) -> 0
F44: May | G44: =G43 -> 2015-2016 | H44: =CONCATENATE(F44,"-",RIGHT(LEFT(G44,4),2)) -> May-15 | N44: =I44+J44+L44+M44-K44 -> 0 | O44: =O43+N44 -> 0 | P44: 0.087 | Q44: =O44*P44/12 -> 0 | S44: =IF(OR(R44="",R44="ok"),0,1) -> 0
F45: Jun | G45: =G44 -> 2015-2016 | H45: =CONCATENATE(F45,"-",RIGHT(LEFT(G45,4),2)) -> Jun-15 | N45: =I45+J45+L45+M45-K45 -> 0 | O45: =O44+N45 -> 0 | P45: 0.087 | Q45: =O45*P45/12 -> 0 | S45: =IF(OR(R45="",R45="ok"),0,1) -> 0
F46: Jul | G46: =G45 -> 2015-2016 | H46: =CONCATENATE(F46,"-",RIGHT(LEFT(G46,4),2)) -> Jul-15 | N46: =I46+J46+L46+M46-K46 -> 0 | O46: =O45+N46 -> 0 | P46: 0.087 | Q46: =O46*P46/12 -> 0 | S46: =IF(OR(R46="",R46="ok"),0,1) -> 0
F47: Aug | G47: =G46 -> 2015-2016 | H47: =CONCATENATE(F47,"-",RIGHT(LEFT(G47,4),2)) -> Aug-15 | N47: =I47+J47+L47+M47-K47 -> 0 | O47: =O46+N47 -> 0 | P47: 0.087 | Q47: =O47*P47/12 -> 0 | S47: =IF(OR(R47="",R47="ok"),0,1) -> 0
F48: Sep | G48: =G47 -> 2015-2016 | H48: =CONCATENATE(F48,"-",RIGHT(LEFT(G48,4),2)) -> Sep-15 | N48: =I48+J48+L48+M48-K48 -> 0 | O48: =O47+N48 -> 0 | P48: 0.087 | Q48: =O48*P48/12 -> 0 | S48: =IF(OR(R48="",R48="ok"),0,1) -> 0
F49: Oct | G49: =G48 -> 2015-2016 | H49: =CONCATENATE(F49,"-",RIGHT(LEFT(G49,4),2)) -> Oct-15 | N49: =I49+J49+L49+M49-K49 -> 0 | O49: =O48+N49 -> 0 | P49: 0.087 | Q49: =O49*P49/12 -> 0 | S49: =IF(OR(R49="",R49="ok"),0,1) -> 0
F50: Nov | G50: =G49 -> 2015-2016 | H50: =CONCATENATE(F50,"-",RIGHT(LEFT(G50,4),2)) -> Nov-15 | N50: =I50+J50+L50+M50-K50 -> 0 | O50: =O49+N50 -> 0 | P50: 0.087 | Q50: =O50*P50/12 -> 0 | S50: =IF(OR(R50="",R50="ok"),0,1) -> 0
F51: Dec | G51: =G50 -> 2015-2016 | H51: =CONCATENATE(F51,"-",RIGHT(LEFT(G51,4),2)) -> Dec-15 | N51: =I51+J51+L51+M51-K51 -> 0 | O51: =O50+N51 -> 0 | P51: 0.087 | Q51: =O51*P51/12 -> 0 | S51: =IF(OR(R51="",R51="ok"),0,1) -> 0
F52: Jan | G52: =G51 -> 2015-2016 | H52: =CONCATENATE(F52,"-",RIGHT(RIGHT(G52,4),2)) -> Jan-16 | N52: =I52+J52+L52+M52-K52 -> 0 | O52: =O51+N52 -> 0 | P52: 0.087 | Q52: =O52*P52/12 -> 0 | S52: =IF(OR(R52="",R52="ok"),0,1) -> 0
F53: Feb | G53: =G52 -> 2015-2016 | H53: =CONCATENATE(F53,"-",RIGHT(RIGHT(G53,4),2)) -> Feb-16 | N53: =I53+J53+L53+M53-K53 -> 0 | O53: =O52+N53 -> 0 | P53: 0.087 | Q53: =O53*P53/12 -> 0 | S53: =IF(OR(R53="",R53="ok"),0,1) -> 0
F54: Mar | G54: =G53 -> 2015-2016 | H54: =CONCATENATE(F54,"-",RIGHT(RIGHT(G54,4),2)) -> Mar-16 | N54: =I54+J54+L54+M54-K54 -> 0 | O54: =O53+N54 -> 0 | P54: 0.087 | Q54: =O54*P54/12 -> 0 | S54: =IF(OR(R54="",R54="ok"),0,1) -> 0
G55: =G54 -> 2015-2016 | I55: =SUM(I43:I54) -> 0 | J55: =SUM(J43:J54) -> 0 | K55: =SUM(K43:K54) -> 0 | L55: =SUM(L43:L54) -> 0 | M55: =SUM(M43:M54) -> 0 | N55: =SUM(N43:N54) -> 0 | O55: =O54+Q55 -> 0 | Q55: =SUM(Q43:Q54) -> 0 | S55: =IF(OR(R55="",R55="ok"),0,1) -> 0
F56: Apr | G56: =CONCATENATE(RIGHT(G43,4),"-",RIGHT(G43,4)+1) -> 2016-2017 | H56: =CONCATENATE(F56,"-",RIGHT(LEFT(G56,4),2)) -> Apr-16 | N56: =I56+J56+L56+M56-K56 -> 0 | O56: =O55+N56 -> 0 | P56: 0.081 | Q56: =O56*P56/12 -> 0 | S56: =IF(OR(R56="",R56="ok"),0,1) -> 0
F57: May | G57: =G56 -> 2016-2017 | H57: =CONCATENATE(F57,"-",RIGHT(LEFT(G57,4),2)) -> May-16 | N57: =I57+J57+L57+M57-K57 -> 0 | O57: =O56+N57 -> 0 | P57: 0.081 | Q57: =O57*P57/12 -> 0 | S57: =IF(OR(R57="",R57="ok"),0,1) -> 0
F58: Jun | G58: =G57 -> 2016-2017 | H58: =CONCATENATE(F58,"-",RIGHT(LEFT(G58,4),2)) -> Jun-16 | N58: =I58+J58+L58+M58-K58 -> 0 | O58: =O57+N58 -> 0 | P58: 0.081 | Q58: =O58*P58/12 -> 0 | S58: =IF(OR(R58="",R58="ok"),0,1) -> 0
F59: Jul | G59: =G58 -> 2016-2017 | H59: =CONCATENATE(F59,"-",RIGHT(LEFT(G59,4),2)) -> Jul-16 | N59: =I59+J59+L59+M59-K59 -> 0 | O59: =O58+N59 -> 0 | P59: 0.081 | Q59: =O59*P59/12 -> 0 | S59: =IF(OR(R59="",R59="ok"),0,1) -> 0
F60: Aug | G60: =G59 -> 2016-2017 | H60: =CONCATENATE(F60,"-",RIGHT(LEFT(G60,4),2)) -> Aug-16 | N60: =I60+J60+L60+M60-K60 -> 0 | O60: =O59+N60 -> 0 | P60: 0.081 | Q60: =O60*P60/12 -> 0 | S60: =IF(OR(R60="",R60="ok"),0,1) -> 0
F61: Sep | G61: =G60 -> 2016-2017 | H61: =CONCATENATE(F61,"-",RIGHT(LEFT(G61,4),2)) -> Sep-16 | N61: =I61+J61+L61+M61-K61 -> 0 | O61: =O60+N61 -> 0 | P61: 0.081 | Q61: =O61*P61/12 -> 0 | S61: =IF(OR(R61="",R61="ok"),0,1) -> 0
F62: Oct | G62: =G61 -> 2016-2017 | H62: =CONCATENATE(F62,"-",RIGHT(LEFT(G62,4),2)) -> Oct-16 | N62: =I62+J62+L62+M62-K62 -> 0 | O62: =O61+N62 -> 0 | P62: 0.08 | Q62: =O62*P62/12 -> 0 | S62: =IF(OR(R62="",R62="ok"),0,1) -> 0
F63: Nov | G63: =G62 -> 2016-2017 | H63: =CONCATENATE(F63,"-",RIGHT(LEFT(G63,4),2)) -> Nov-16 | N63: =I63+J63+L63+M63-K63 -> 0 | O63: =O62+N63 -> 0 | P63: 0.08 | Q63: =O63*P63/12 -> 0 | S63: =IF(OR(R63="",R63="ok"),0,1) -> 0
F64: Dec | G64: =G63 -> 2016-2017 | H64: =CONCATENATE(F64,"-",RIGHT(LEFT(G64,4),2)) -> Dec-16 | N64: =I64+J64+L64+M64-K64 -> 0 | O64: =O63+N64 -> 0 | P64: 0.08 | Q64: =O64*P64/12 -> 0 | S64: =IF(OR(R64="",R64="ok"),0,1) -> 0
F65: Jan | G65: =G64 -> 2016-2017 | H65: =CONCATENATE(F65,"-",RIGHT(RIGHT(G65,4),2)) -> Jan-17 | N65: =I65+J65+L65+M65-K65 -> 0 | O65: =O64+N65 -> 0 | P65: 0.08 | Q65: =O65*P65/12 -> 0 | S65: =IF(OR(R65="",R65="ok"),0,1) -> 0
F66: Feb | G66: =G65 -> 2016-2017 | H66: =CONCATENATE(F66,"-",RIGHT(RIGHT(G66,4),2)) -> Feb-17 | N66: =I66+J66+L66+M66-K66 -> 0 | O66: =O65+N66 -> 0 | P66: 0.08 | Q66: =O66*P66/12 -> 0 | S66: =IF(OR(R66="",R66="ok"),0,1) -> 0
F67: Mar | G67: =G66 -> 2016-2017 | H67: =CONCATENATE(F67,"-",RIGHT(RIGHT(G67,4),2)) -> Mar-17 | N67: =I67+J67+L67+M67-K67 -> 0 | O67: =O66+N67 -> 0 | P67: 0.08 | Q67: =O67*P67/12 -> 0 | S67: =IF(OR(R67="",R67="ok"),0,1) -> 0
G68: =G67 -> 2016-2017 | I68: =SUM(I56:I67) -> 0 | J68: =SUM(J56:J67) -> 0 | K68: =SUM(K56:K67) -> 0 | L68: =SUM(L56:L67) -> 0 | M68: =SUM(M56:M67) -> 0 | N68: =SUM(N56:N67) -> 0 | O68: =O67+Q68 -> 0 | Q68: =SUM(Q56:Q67) -> 0 | S68: =IF(OR(R68="",R68="ok"),0,1) -> 0
F69: Apr | G69: =CONCATENATE(RIGHT(G56,4),"-",RIGHT(G56,4)+1) -> 2017-2018 | H69: =CONCATENATE(F69,"-",RIGHT(LEFT(G69,4),2)) -> Apr-17 | N69: =I69+J69+L69+M69-K69 -> 0 | O69: =O68+N69 -> 0 | P69: 0.079 | Q69: =O69*P69/12 -> 0 | S69: =IF(OR(R69="",R69="ok"),0,1) -> 0
F70: May | G70: =G69 -> 2017-2018 | H70: =CONCATENATE(F70,"-",RIGHT(LEFT(G70,4),2)) -> May-17 | N70: =I70+J70+L70+M70-K70 -> 0 | O70: =O69+N70 -> 0 | P70: 0.079 | Q70: =O70*P70/12 -> 0 | S70: =IF(OR(R70="",R70="ok"),0,1) -> 0
F71: Jun | G71: =G70 -> 2017-2018 | H71: =CONCATENATE(F71,"-",RIGHT(LEFT(G71,4),2)) -> Jun-17 | N71: =I71+J71+L71+M71-K71 -> 0 | O71: =O70+N71 -> 0 | P71: 0.079 | Q71: =O71*P71/12 -> 0 | S71: =IF(OR(R71="",R71="ok"),0,1) -> 0
F72: Jul | G72: =G71 -> 2017-2018 | H72: =CONCATENATE(F72,"-",RIGHT(LEFT(G72,4),2)) -> Jul-17 | N72: =I72+J72+L72+M72-K72 -> 0 | O72: =O71+N72 -> 0 | P72: 0.078 | Q72: =O72*P72/12 -> 0 | S72: =IF(OR(R72="",R72="ok"),0,1) -> 0
F73: Aug | G73: =G72 -> 2017-2018 | H73: =CONCATENATE(F73,"-",RIGHT(LEFT(G73,4),2)) -> Aug-17 | N73: =I73+J73+L73+M73-K73 -> 0 | O73: =O72+N73 -> 0 | P73: 0.078 | Q73: =O73*P73/12 -> 0 | S73: =IF(OR(R73="",R73="ok"),0,1) -> 0
F74: Sep | G74: =G73 -> 2017-2018 | H74: =CONCATENATE(F74,"-",RIGHT(LEFT(G74,4),2)) -> Sep-17 | N74: =I74+J74+L74+M74-K74 -> 0 | O74: =O73+N74 -> 0 | P74: 0.078 | Q74: =O74*P74/12 -> 0 | S74: =IF(OR(R74="",R74="ok"),0,1) -> 0
F75: Oct | G75: =G74 -> 2017-2018 | H75: =CONCATENATE(F75,"-",RIGHT(LEFT(G75,4),2)) -> Oct-17 | N75: =I75+J75+L75+M75-K75 -> 0 | O75: =O74+N75 -> 0 | P75: 0.078 | Q75: =O75*P75/12 -> 0 | S75: =IF(OR(R75="",R75="ok"),0,1) -> 0
F76: Nov | G76: =G75 -> 2017-2018 | H76: =CONCATENATE(F76,"-",RIGHT(LEFT(G76,4),2)) -> Nov-17 | N76: =I76+J76+L76+M76-K76 -> 0 | O76: =O75+N76 -> 0 | P76: 0.078 | Q76: =O76*P76/12 -> 0 | S76: =IF(OR(R76="",R76="ok"),0,1) -> 0
F77: Dec | G77: =G76 -> 2017-2018 | H77: =CONCATENATE(F77,"-",RIGHT(LEFT(G77,4),2)) -> Dec-17 | N77: =I77+J77+L77+M77-K77 -> 0 | O77: =O76+N77 -> 0 | P77: 0.078 | Q77: =O77*P77/12 -> 0 | S77: =IF(OR(R77="",R77="ok"),0,1) -> 0
F78: Jan | G78: =G77 -> 2017-2018 | H78: =CONCATENATE(F78,"-",RIGHT(RIGHT(G78,4),2)) -> Jan-18 | N78: =I78+J78+L78+M78-K78 -> 0 | O78: =O77+N78 -> 0 | P78: 0.076 | Q78: =O78*P78/12 -> 0 | S78: =IF(OR(R78="",R78="ok"),0,1) -> 0
F79: Feb | G79: =G78 -> 2017-2018 | H79: =CONCATENATE(F79,"-",RIGHT(RIGHT(G79,4),2)) -> Feb-18 | N79: =I79+J79+L79+M79-K79 -> 0 | O79: =O78+N79 -> 0 | P79: 0.076 | Q79: =O79*P79/12 -> 0 | S79: =IF(OR(R79="",R79="ok"),0,1) -> 0
F80: Mar | G80: =G79 -> 2017-2018 | H80: =CONCATENATE(F80,"-",RIGHT(RIGHT(G80,4),2)) -> Mar-18 | N80: =I80+J80+L80+M80-K80 -> 0 | O80: =O79+N80 -> 0 | P80: 0.076 | Q80: =O80*P80/12 -> 0 | S80: =IF(OR(R80="",R80="ok"),0,1) -> 0
G81: =G80 -> 2017-2018 | I81: =SUM(I69:I80) -> 0 | J81: =SUM(J69:J80) -> 0 | K81: =SUM(K69:K80) -> 0 | L81: =SUM(L69:L80) -> 0 | M81: =SUM(M69:M80) -> 0 | N81: =SUM(N69:N80) -> 0 | O81: =O80+Q81 -> 0 | Q81: =SUM(Q69:Q80) -> 0 | S81: =IF(OR(R81="",R81="ok"),0,1) -> 0
F82: Apr | G82: =CONCATENATE(RIGHT(G69,4),"-",RIGHT(G69,4)+1) -> 2018-2019 | H82: =CONCATENATE(F82,"-",RIGHT(LEFT(G82,4),2)) -> Apr-18 | N82: =I82+J82+L82+M82-K82 -> 0 | O82: =O81+N82 -> 0 | P82: 0.076 | Q82: =O82*P82/12 -> 0 | S82: =IF(OR(R82="",R82="ok"),0,1) -> 0
F83: May | G83: =G82 -> 2018-2019 | H83: =CONCATENATE(F83,"-",RIGHT(LEFT(G83,4),2)) -> May-18 | N83: =I83+J83+L83+M83-K83 -> 0 | O83: =O82+N83 -> 0 | P83: 0.076 | Q83: =O83*P83/12 -> 0 | S83: =IF(OR(R83="",R83="ok"),0,1) -> 0
F84: Jun | G84: =G83 -> 2018-2019 | H84: =CONCATENATE(F84,"-",RIGHT(LEFT(G84,4),2)) -> Jun-18 | N84: =I84+J84+L84+M84-K84 -> 0 | O84: =O83+N84 -> 0 | P84: 0.076 | Q84: =O84*P84/12 -> 0 | S84: =IF(OR(R84="",R84="ok"),0,1) -> 0
F85: Jul | G85: =G84 -> 2018-2019 | H85: =CONCATENATE(F85,"-",RIGHT(LEFT(G85,4),2)) -> Jul-18 | N85: =I85+J85+L85+M85-K85 -> 0 | O85: =O84+N85 -> 0 | P85: 0.076 | Q85: =O85*P85/12 -> 0 | S85: =IF(OR(R85="",R85="ok"),0,1) -> 0
F86: Aug | G86: =G85 -> 2018-2019 | H86: =CONCATENATE(F86,"-",RIGHT(LEFT(G86,4),2)) -> Aug-18 | N86: =I86+J86+L86+M86-K86 -> 0 | O86: =O85+N86 -> 0 | P86: 0.076 | Q86: =O86*P86/12 -> 0 | S86: =IF(OR(R86="",R86="ok"),0,1) -> 0
F87: Sep | G87: =G86 -> 2018-2019 | H87: =CONCATENATE(F87,"-",RIGHT(LEFT(G87,4),2)) -> Sep-18 | N87: =I87+J87+L87+M87-K87 -> 0 | O87: =O86+N87 -> 0 | P87: 0.076 | Q87: =O87*P87/12 -> 0 | S87: =IF(OR(R87="",R87="ok"),0,1) -> 0
F88: Oct | G88: =G87 -> 2018-2019 | H88: =CONCATENATE(F88,"-",RIGHT(LEFT(G88,4),2)) -> Oct-18 | N88: =I88+J88+L88+M88-K88 -> 0 | O88: =O87+N88 -> 0 | P88: 0.08 | Q88: =O88*P88/12 -> 0 | S88: =IF(OR(R88="",R88="ok"),0,1) -> 0
F89: Nov | G89: =G88 -> 2018-2019 | H89: =CONCATENATE(F89,"-",RIGHT(LEFT(G89,4),2)) -> Nov-18 | N89: =I89+J89+L89+M89-K89 -> 0 | O89: =O88+N89 -> 0 | P89: 0.08 | Q89: =O89*P89/12 -> 0 | S89: =IF(OR(R89="",R89="ok"),0,1) -> 0
F90: Dec | G90: =G89 -> 2018-2019 | H90: =CONCATENATE(F90,"-",RIGHT(LEFT(G90,4),2)) -> Dec-18 | N90: =I90+J90+L90+M90-K90 -> 0 | O90: =O89+N90 -> 0 | P90: 0.08 | Q90: =O90*P90/12 -> 0 | S90: =IF(OR(R90="",R90="ok"),0,1) -> 0
F91: Jan | G91: =G90 -> 2018-2019 | H91: =CONCATENATE(F91,"-",RIGHT(RIGHT(G91,4),2)) -> Jan-19 | N91: =I91+J91+L91+M91-K91 -> 0 | O91: =O90+N91 -> 0 | P91: 0.08 | Q91: =O91*P91/12 -> 0 | S91: =IF(OR(R91="",R91="ok"),0,1) -> 0
F92: Feb | G92: =G91 -> 2018-2019 | H92: =CONCATENATE(F92,"-",RIGHT(RIGHT(G92,4),2)) -> Feb-19 | N92: =I92+J92+L92+M92-K92 -> 0 | O92: =O91+N92 -> 0 | P92: 0.08 | Q92: =O92*P92/12 -> 0 | S92: =IF(OR(R92="",R92="ok"),0,1) -> 0
F93: Mar | G93: =G92 -> 2018-2019 | H93: =CONCATENATE(F93,"-",RIGHT(RIGHT(G93,4),2)) -> Mar-19 | N93: =I93+J93+L93+M93-K93 -> 0 | O93: =O92+N93 -> 0 | P93: 0.08 | Q93: =O93*P93/12 -> 0 | S93: =IF(OR(R93="",R93="ok"),0,1) -> 0
G94: =G93 -> 2018-2019 | I94: =SUM(I82:I93) -> 0 | J94: =SUM(J82:J93) -> 0 | K94: =SUM(K82:K93) -> 0 | L94: =SUM(L82:L93) -> 0 | M94: =SUM(M82:M93) -> 0 | N94: =SUM(N82:N93) -> 0 | O94: =O93+Q94 -> 0 | Q94: =SUM(Q82:Q93) -> 0 | S94: =IF(OR(R94="",R94="ok"),0,1) -> 0
F95: Apr | G95: =CONCATENATE(RIGHT(G82,4),"-",RIGHT(G82,4)+1) -> 2019-2020 | H95: =CONCATENATE(F95,"-",RIGHT(LEFT(G95,4),2)) -> Apr-19 | N95: =I95+J95+L95+M95-K95 -> 0 | O95: =O94+N95 -> 0 | P95: 0.08 | Q95: =O95*P95/12 -> 0 | S95: =IF(OR(R95="",R95="ok"),0,1) -> 0
F96: May | G96: =G95 -> 2019-2020 | H96: =CONCATENATE(F96,"-",RIGHT(LEFT(G96,4),2)) -> May-19 | N96: =I96+J96+L96+M96-K96 -> 0 | O96: =O95+N96 -> 0 | P96: 0.08 | Q96: =O96*P96/12 -> 0 | S96: =IF(OR(R96="",R96="ok"),0,1) -> 0
F97: Jun | G97: =G96 -> 2019-2020 | H97: =CONCATENATE(F97,"-",RIGHT(LEFT(G97,4),2)) -> Jun-19 | N97: =I97+J97+L97+M97-K97 -> 0 | O97: =O96+N97 -> 0 | P97: 0.08 | Q97: =O97*P97/12 -> 0 | S97: =IF(OR(R97="",R97="ok"),0,1) -> 0
F98: Jul | G98: =G97 -> 2019-2020 | H98: =CONCATENATE(F98,"-",RIGHT(LEFT(G98,4),2)) -> Jul-19 | N98: =I98+J98+L98+M98-K98 -> 0 | O98: =O97+N98 -> 0 | P98: 0.079 | Q98: =O98*P98/12 -> 0 | S98: =IF(OR(R98="",R98="ok"),0,1) -> 0
F99: Aug | G99: =G98 -> 2019-2020 | H99: =CONCATENATE(F99,"-",RIGHT(LEFT(G99,4),2)) -> Aug-19 | N99: =I99+J99+L99+M99-K99 -> 0 | O99: =O98+N99 -> 0 | P99: 0.079 | Q99: =O99*P99/12 -> 0 | S99: =IF(OR(R99="",R99="ok"),0,1) -> 0
F100: Sep | G100: =G99 -> 2019-2020 | H100: =CONCATENATE(F100,"-",RIGHT(LEFT(G100,4),2)) -> Sep-19 | N100: =I100+J100+L100+M100-K100 -> 0 | O100: =O99+N100 -> 0 | P100: 0.079 | Q100: =O100*P100/12 -> 0 | S100: =IF(OR(R100="",R100="ok"),0,1) -> 0
...

Sheet SI (SSO ID New)
A1: This Data is From SIPF Portal (Through SSO ID)(NEW) | R1: error at bx4 cell | S1: =BX4 -> 2 | V1: Last Update on this sheet | W1: 46110 | CS1: Differenece of pivot of left most and pivot of (sso id new with detail) this must be zero , if not zero then update both sheets (SI(SSO ID NEW) and SI (SSO ID NEW WITH DETAIL))
R2: error at di5 cell | S2: =DI5 -> 0 | AP2: this pivot table is on left most data | BF2: difference on sso id year wise data and pivot table | CB2: this pivot is on sheet Si(sso id new with detail)
E3: =SUM(Table2[Premium Usual]) -> 472000 | F3: =SUM(Table2[Incremental Premium]) -> 0 | G3: =SUM(Table2[Arrear Usual]) -> 5000 | H3: =SUM(Table2[Loan Installment]) -> 65178 | I3: =SUM(Table2[Loan Interest]) -> 0 | J3: =SUM(Table2[Service Tax]) -> 0 | K3: =SUM(Table2[Recovery Amount]) -> 0 | L3: =SUM(Table2[Total Premium]) -> 542178 | M3: =SUM(Table2[Loan]) -> 434500 | N3: =SUM(Table2[Claim]) -> 0 | O3: =SUM(Table2[Refund]) -> 0 | P3: =SUM(Table2[Check Status with ga 55]) -> 0 | Q3: =SUM(Table2[CORRECTION NEEDED]) -> 1 | X3: this data is from sso id new portal | AP3: Sum of Total (automatic) | BX3: errors
A4: FY | B4: Month | C4: Salary Month | D4: Transaction Mode | E4: Premium Usual | F4: Incremental Premium | G4: Arrear Usual | H4: Loan Installment | I4: Loan Interest | J4: Service Tax | K4: Recovery Amount | L4: Total Premium | M4: Loan | N4: Claim | O4: Refund | P4: Check Status with ga 55 | Q4: CORRECTION NEEDED | R4: TV month or Encashment Month and year | S4: TV month or Encashment Month | T4: TV year or Encashment Year | U4: Total (automatic) | W4: Sr No. | X4: Financial Year | Y4: April | Z4: May | AA4: June | AB4: July | AC4: Aug | AD4: Sept | AE4: Oct | AF4: Nov | AG4: Dec | AH4: Jan | AI4: Feb | AJ4: March | AK4: Total | AL4: Loan | AM4: Claim | AN4: REFUND | AP4: Row Labels | AQ4: Jan | AR4: Feb | AS4: Mar | AT4: Apr | AU4: May | AV4: Jun | AW4: Jul | AX4: Aug | AY4: Sep | AZ4: Oct | BA4: Nov | BB4: Dec | BC4: Grand Total | BF4: Sr No. | BG4: Financial Year | BH4: April | BI4: May | BJ4: June | BK4: July | BL4: Aug | BM4: Sept | BN4: Oct | BO4: Nov | BP4: Dec | BQ4: Jan | BR4: Feb | BS4: March | BT4: Total | BU4: Loan | BV4: Claim | BX4: =SUM(BX5:BX11) -> 2 | CB4: Sum of Total Premium | CS4: Sum | DI4: errors
A5: 2016-2017 | B5: 42614 | C5: 201610 | D5: ONLINE | E5: 2200 | F5: 0 | G5: 0 | H5: 0 | I5: 0 | J5: 0 | K5: 0 | L5: 2200 | M5: 0 | N5: 0 | O5: 0 | P5: OK | Q5: =IF(Table2[[#This Row],[Check Status with ga 55]]="ok",0,1) -> 0 | R5: =IFERROR(CONCATENATE(TEXT(RIGHT(C5,2)*29,"mmm"),"-",RIGHT(LEFT(C5,4),2)),"") -> Oct-16 | S5: =IFERROR((TEXT(RIGHT(C5,2)*29,"mmm")),"") -> Oct | T5: =IFERROR(RIGHT(LEFT(C5,4),2),"") -> 16 | U5: =Table2[[#This Row],[Total Premium]]+Table2[[#This Row],[Loan]] -> 2200 | W5: 1 | X5: 2025-2026 | Y5: 5000 | Z5: 5000 | AA5: 5000 | AB5: 12242 | AC5: 12242 | AD5: 12242 | AE5: 12242 | AF5: 12242 | AG5: 12242 | AH5: 12242 | AI5: 12242 | AJ5: 12242 | AK5: 125178 | AL5: 434500 | AM5: 0 | AN5: 0 | AP5: 2025-2026 | AQ5: 12242 | AR5: 12242 | AS5: 12242 | AT5: 5000 | AU5: 439500 | AV5: 5000 | AW5: 12242 | AX5: 12242 | AY5: 12242 | AZ5: 12242 | BA5: 12242 | BB5: 12242 | BC5: 559678 | BF5: =IFERROR(Table5[[#This Row],[Sr No.]],"") -> 1 | BG5: =IFERROR(Table5[[#This Row],[Financial Year]],"") -> 2025-2026 | BH5: =Y5-AT5 -> 0 | BI5: =Z5-AU5 -> -434500 | BJ5: =AA5-AV5 -> 0 | BK5: =AB5-AW5 -> 0 | BL5: =AC5-AX5 -> 0 | BM5: =AD5-AY5 -> 0 | BN5: =AE5-AZ5 -> 0 | BO5: =AF5-BA5 -> 0 | BP5: =AG5-BB5 -> 0 | BQ5: =AH5-AQ5 -> 0 | BR5: =AI5-AR5 -> 0 | BS5: =AJ5-AS5 -> 0 | BT5: =AK5-BC5 -> -434500 | BX5: =13-COUNTIF(BH5:BT5,0) -> 2 | CB5: Row Labels | CC5: Jan | CD5: Feb | CE5: Mar | CF5: Apr | CG5: May | CH5: Jun | CI5: Jul | CJ5: Aug | CK5: Sep | CL5: Oct | CM5: Nov | CN5: Dec | CO5: Grand Total | CS5: Row Label | CT5: =CC5 -> Jan | CU5: =CD5 -> Feb | CV5: =CE5 -> Mar | CW5: =CF5 -> Apr | CX5: =CG5 -> May | CY5: =CH5 -> Jun | CZ5: =CI5 -> Jul | DA5: =CJ5 -> Aug | ... DF5: =CO5 -> Grand Total | DI5: =SUM(DI6:DI29) -> 0
A6: 2016-2017 | B6: 42430 | C6: 201604 | D6: DED | E6: 1100 | F6: 0 | G6: 0 | H6: 0 | I6: 0 | J6: 0 | K6: 0 | L6: 1100 | M6: 0 | N6: 0 | O6: 0 | P6: OK | Q6: =IF(Table2[[#This Row],[Check Status with ga 55]]="ok",0,"Correction Needed") -> 0 | R6: =IFERROR(CONCATENATE(TEXT(RIGHT(C6,2)*29,"mmm"),"-",RIGHT(LEFT(C6,4),2)),"") -> Apr-16 | S6: =IFERROR((TEXT(RIGHT(C6,2)*29,"mmm")),"") -> Apr | T6: =IFERROR(RIGHT(LEFT(C6,4),2),"") -> 16 | U6: =Table2[[#This Row],[Total Premium]]+Table2[[#This Row],[Loan]] -> 1100 | W6: 2 | X6: 2024-2025 | Y6: 5000 | Z6: 5000 | AA6: 5000 | AB6: 5000 | AC6: 5000 | AD6: 5000 | AE6: 10000 | AF6: 0 | AG6: 5000 | AH6: 5000 | AI6: 5000 | AJ6: 5000 | AK6: 60000 | AL6: 0 | AM6: 0 | AN6: 0 | AP6: 2024-2025 | AQ6: 5000 | AR6: 5000 | AS6: 5000 | AT6: 5000 | AU6: 5000 | AV6: 5000 | AW6: 5000 | AX6: 5000 | AY6: 5000 | AZ6: 10000 | BB6: 5000 | BC6: 60000 | BF6: =IFERROR(Table5[[#This Row],[Sr No.]],"") -> 2 | BG6: =IFERROR(Table5[[#This Row],[Financial Year]],"") -> 2024-2025 | BH6: =Y6-AT6 -> 0 | BI6: =Z6-AU6 -> 0 | BJ6: =AA6-AV6 -> 0 | BK6: =AB6-AW6 -> 0 | BL6: =AC6-AX6 -> 0 | BM6: =AD6-AY6 -> 0 | BN6: =AE6-AZ6 -> 0 | BO6: =AF6-BA6 -> 0 | BP6: =AG6-BB6 -> 0 | BQ6: =AH6-AQ6 -> 0 | BR6: =AI6-AR6 -> 0 | BS6: =AJ6-AS6 -> 0 | BT6: =AK6-BC6 -> 0 | BX6: =13-COUNTIF(BH6:BT6,0) -> 0 | CB6: 2025-2026 | CC6: 12242 | CD6: 12242 | CE6: 12242 | CF6: 5000 | CG6: 439500 | CH6: 5000 | CI6: 12242 | CJ6: 12242 | CK6: 12242 | CL6: 12242 | CM6: 12242 | CN6: 12242 | CO6: 559678 | CS6: =CB6 -> 2025-2026 | CT6: =CC6-AQ5 -> 0 | CU6: =CD6-AR5 -> 0 | CV6: =CE6-AS5 -> 0 | CW6: =CF6-AT5 -> 0 | CX6: =CG6-AU5 -> 0 | CY6: =CH6-AV5 -> 0 | CZ6: =CI6-AW5 -> 0 | DA6: =CJ6-AX5 -> 0 | ... DF6: =CO6-BC5 -> 0 | DI6: =13-COUNTIF(CT6:DF6,0) -> 0
A7: 2016-2017 | B7: 42461 | C7: 201605 | D7: DED | E7: 1100 | F7: 0 | G7: 0 | H7: 0 | I7: 0 | J7: 0 | K7: 0 | L7: 1100 | M7: 0 | N7: 0 | O7: 0 | P7: OK | Q7: =IF(Table2[[#This Row],[Check Status with ga 55]]="ok",0,1) -> 0 | R7: =IFERROR(CONCATENATE(TEXT(RIGHT(C7,2)*29,"mmm"),"-",RIGHT(LEFT(C7,4),2)),"") -> May-16 | S7: =IFERROR((TEXT(RIGHT(C7,2)*29,"mmm")),"") -> May | T7: =IFERROR(RIGHT(LEFT(C7,4),2),"") -> 16 | U7: =Table2[[#This Row],[Total Premium]]+Table2[[#This Row],[Loan]] -> 1100 | W7: 3 | X7: 2023-2024 | Y7: 5000 | Z7: 5000 | AA7: 5000 | AB7: 5000 | AC7: 5000 | AD7: 5000 | AE7: 5000 | AF7: 5000 | AG7: 5000 | AH7: 5000 | AI7: 5000 | AJ7: 5000 | AK7: 60000 | AL7: 0 | AM7: 0 | AN7: 0 | AP7: 2023-2024 | AQ7: 5000 | AR7: 5000 | AS7: 5000 | AT7: 5000 | AU7: 5000 | AV7: 5000 | AW7: 5000 | AX7: 5000 | AY7: 5000 | AZ7: 5000 | BA7: 5000 | BB7: 5000 | BC7: 60000 | BF7: =IFERROR(Table5[[#This Row],[Sr No.]],"") -> 3 | BG7: =IFERROR(Table5[[#This Row],[Financial Year]],"") -> 2023-2024 | BH7: =Y7-AT7 -> 0 | BI7: =Z7-AU7 -> 0 | BJ7: =AA7-AV7 -> 0 | BK7: =AB7-AW7 -> 0 | BL7: =AC7-AX7 -> 0 | BM7: =AD7-AY7 -> 0 | BN7: =AE7-AZ7 -> 0 | BO7: =AF7-BA7 -> 0 | BP7: =AG7-BB7 -> 0 | BQ7: =AH7-AQ7 -> 0 | BR7: =AI7-AR7 -> 0 | BS7: =AJ7-AS7 -> 0 | BT7: =AK7-BC7 -> 0 | BX7: =13-COUNTIF(BH7:BT7,0) -> 0 | CB7: 2024-2025 | CC7: 5000 | CD7: 5000 | CE7: 5000 | CF7: 5000 | CG7: 5000 | CH7: 5000 | CI7: 5000 | CJ7: 5000 | CK7: 5000 | CL7: 10000 | CN7: 5000 | CO7: 60000 | CS7: =CB7 -> 2024-2025 | CT7: =CC7-AQ6 -> 0 | CU7: =CD7-AR6 -> 0 | CV7: =CE7-AS6 -> 0 | CW7: =CF7-AT6 -> 0 | CX7: =CG7-AU6 -> 0 | CY7: =CH7-AV6 -> 0 | CZ7: =CI7-AW6 -> 0 | DA7: =CJ7-AX6 -> 0 | ... DF7: =CO7-BC6 -> 0 | DI7: =13-COUNTIF(CT7:DF7,0) -> 0
A8: 2016-2017 | B8: 42491 | C8: 201606 | D8: DED | E8: 1100 | F8: 0 | G8: 0 | H8: 0 | I8: 0 | J8: 0 | K8: 0 | L8: 1100 | M8: 0 | N8: 0 | O8: 0 | P8: OK | Q8: =IF(Table2[[#This Row],[Check Status with ga 55]]="ok",0,1) -> 0 | R8: =IFERROR(CONCATENATE(TEXT(RIGHT(C8,2)*29,"mmm"),"-",RIGHT(LEFT(C8,4),2)),"") -> Jun-16 | S8: =IFERROR((TEXT(RIGHT(C8,2)*29,"mmm")),"") -> Jun | T8: =IFERROR(RIGHT(LEFT(C8,4),2),"") -> 16 | U8: =Table2[[#This Row],[Total Premium]]+Table2[[#This Row],[Loan]] -> 1100 | W8: 4 | X8: 2022-2023 | Y8: 5000 | Z8: 5000 | AA8: 5000 | AB8: 5000 | AC8: 5000 | AD8: 5000 | AE8: 5000 | AF8: 5000 | AG8: 5000 | AH8: 5000 | AI8: 5000 | AJ8: 5000 | AK8: 60000 | AL8: 0 | AM8: 0 | AN8: 0 | AP8: 2022-2023 | AQ8: 5000 | AR8: 5000 | AS8: 5000 | AT8: 5000 | AU8: 5000 | AV8: 5000 | AW8: 5000 | AX8: 5000 | AY8: 5000 | AZ8: 5000 | BA8: 5000 | BB8: 5000 | BC8: 60000 | BF8: =IFERROR(Table5[[#This Row],[Sr No.]],"") -> 4 | BG8: =IFERROR(Table5[[#This Row],[Financial Year]],"") -> 2022-2023 | BH8: =Y8-AT8 -> 0 | BI8: =Z8-AU8 -> 0 | BJ8: =AA8-AV8 -> 0 | BK8: =AB8-AW8 -> 0 | BL8: =AC8-AX8 -> 0 | BM8: =AD8-AY8 -> 0 | BN8: =AE8-AZ8 -> 0 | BO8: =AF8-BA8 -> 0 | BP8: =AG8-BB8 -> 0 | BQ8: =AH8-AQ8 -> 0 | BR8: =AI8-AR8 -> 0 | BS8: =AJ8-AS8 -> 0 | BT8: =AK8-BC8 -> 0 | BX8: =13-COUNTIF(BH8:BT8,0) -> 0 | CB8: 2023-2024 | CC8: 5000 | CD8: 5000 | CE8: 5000 | CF8: 5000 | CG8: 5000 | CH8: 5000 | CI8: 5000 | CJ8: 5000 | CK8: 5000 | CL8: 5000 | CM8: 5000 | CN8: 5000 | CO8: 60000 | CS8: =CB8 -> 2023-2024 | CT8: =CC8-AQ7 -> 0 | CU8: =CD8-AR7 -> 0 | CV8: =CE8-AS7 -> 0 | CW8: =CF8-AT7 -> 0 | CX8: =CG8-AU7 -> 0 | CY8: =CH8-AV7 -> 0 | CZ8: =CI8-AW7 -> 0 | DA8: =CJ8-AX7 -> 0 | ... DF8: =CO8-BC7 -> 0 | DI8: =13-COUNTIF(CT8:DF8,0) -> 0
A9: 2016-2017 | B9: 42522 | C9: 201607 | D9: DED | E9: 1100 | F9: 0 | G9: 0 | H9: 0 | I9: 0 | J9: 0 | K9: 0 | L9: 1100 | M9: 0 | N9: 0 | O9: 0 | P9: OK | Q9: =IF(Table2[[#This Row],[Check Status with ga 55]]="ok",0,1) -> 0 | R9: =IFERROR(CONCATENATE(TEXT(RIGHT(C9,2)*29,"mmm"),"-",RIGHT(LEFT(C9,4),2)),"") -> Jul-16 | S9: =IFERROR((TEXT(RIGHT(C9,2)*29,"mmm")),"") -> Jul | T9: =IFERROR(RIGHT(LEFT(C9,4),2),"") -> 16 | U9: =Table2[[#This Row],[Total Premium]]+Table2[[#This Row],[Loan]] -> 1100 | W9: 5 | X9: 2021-2022 | Y9: 5000 | Z9: 5000 | AA9: 5000 | AB9: 5000 | AC9: 5000 | AD9: 5000 | AE9: 5000 | AF9: 5000 | AG9: 5000 | AH9: 5000 | AI9: 5000 | AJ9: 5000 | AK9: 60000 | AL9: 0 | AM9: 0 | AN9: 0 | AP9: 2021-2022 | AQ9: 5000 | AR9: 5000 | AS9: 5000 | AT9: 5000 | AU9: 5000 | AV9: 5000 | AW9: 5000 | AX9: 5000 | AY9: 5000 | AZ9: 5000 | BA9: 5000 | BB9: 5000 | BC9: 60000 | BF9: =IFERROR(Table5[[#This Row],[Sr No.]],"") -> 5 | BG9: =IFERROR(Table5[[#This Row],[Financial Year]],"") -> 2021-2022 | BH9: =Y9-AT9 -> 0 | BI9: =Z9-AU9 -> 0 | BJ9: =AA9-AV9 -> 0 | BK9: =AB9-AW9 -> 0 | BL9: =AC9-AX9 -> 0 | BM9: =AD9-AY9 -> 0 | BN9: =AE9-AZ9 -> 0 | BO9: =AF9-BA9 -> 0 | BP9: =AG9-BB9 -> 0 | BQ9: =AH9-AQ9 -> 0 | BR9: =AI9-AR9 -> 0 | BS9: =AJ9-AS9 -> 0 | BT9: =AK9-BC9 -> 0 | BX9: =13-COUNTIF(BH9:BT9,0) -> 0 | CB9: 2022-2023 | CC9: 5000 | CD9: 5000 | CE9: 5000 | CF9: 5000 | CG9: 5000 | CH9: 5000 | CI9: 5000 | CJ9: 5000 | CK9: 5000 | CL9: 5000 | CM9: 5000 | CN9: 5000 | CO9: 60000 | CS9: =CB9 -> 2022-2023 | CT9: =CC9-AQ8 -> 0 | CU9: =CD9-AR8 -> 0 | CV9: =CE9-AS8 -> 0 | CW9: =CF9-AT8 -> 0 | CX9: =CG9-AU8 -> 0 | CY9: =CH9-AV8 -> 0 | CZ9: =CI9-AW8 -> 0 | DA9: =CJ9-AX8 -> 0 | ... DF9: =CO9-BC8 -> 0 | DI9: =13-COUNTIF(CT9:DF9,0) -> 0
A10: 2016-2017 | B10: 42552 | C10: 201608 | D10: DED | E10: 1100 | F10: 0 | G10: 0 | H10: 0 | I10: 0 | J10: 0 | K10: 0 | L10: 1100 | M10: 0 | N10: 0 | O10: 0 | P10: OK | Q10: =IF(Table2[[#This Row],[Check Status with ga 55]]="ok",0,1) -> 0 | R10: =IFERROR(CONCATENATE(TEXT(RIGHT(C10,2)*29,"mmm"),"-",RIGHT(LEFT(C10,4),2)),"") -> Aug-16 | S10: =IFERROR((TEXT(RIGHT(C10,2)*29,"mmm")),"") -> Aug | T10: =IFERROR(RIGHT(LEFT(C10,4),2),"") -> 16 | U10: =Table2[[#This Row],[Total Premium]]+Table2[[#This Row],[Loan]] -> 1100 | W10: 6 | X10: 2020-2021 | Y10: 0 | Z10: 5000 | AA10: 10000 | AB10: 5000 | AC10: 5000 | AD10: 5000 | AE10: 5000 | AF10: 5000 | AG10: 5000 | AH10: 5000 | AI10: 5000 | AJ10: 5000 | AK10: 60000 | AL10: 0 | AM10: 0 | AN10: 0 | AP10: 2020-2021 | AQ10: 5000 | AR10: 5000 | AS10: 5000 | AT10: 0 | AU10: 5000 | AV10: 10000 | AW10: 5000 | AX10: 5000 | AY10: 5000 | AZ10: 5000 | BA10: 5000 | BB10: 5000 | BC10: 60000 | BF10: =IFERROR(Table5[[#This Row],[Sr No.]],"") -> 6 | BG10: =IFERROR(Table5[[#This Row],[Financial Year]],"") -> 2020-2021 | BH10: =Y10-AT10 -> 0 | BI10: =Z10-AU10 -> 0 | BJ10: =AA10-AV10 -> 0 | BK10: =AB10-AW10 -> 0 | BL10: =AC10-AX10 -> 0 | BM10: =AD10-AY10 -> 0 | BN10: =AE10-AZ10 -> 0 | BO10: =AF10-BA10 -> 0 | BP10: =AG10-BB10 -> 0 | BQ10: =AH10-AQ10 -> 0 | BR10: =AI10-AR10 -> 0 | BS10: =AJ10-AS10 -> 0 | BT10: =AK10-BC10 -> 0 | BX10: =13-COUNTIF(BH10:BT10,0) -> 0 | CB10: 2021-2022 | CC10: 5000 | CD10: 5000 | CE10: 5000 | CF10: 5000 | CG10: 5000 | CH10: 5000 | CI10: 5000 | CJ10: 5000 | CK10: 5000 | CL10: 5000 | CM10: 5000 | CN10: 5000 | CO10: 60000 | CS10: =CB10 -> 2021-2022 | CT10: =CC10-AQ9 -> 0 | CU10: =CD10-AR9 -> 0 | CV10: =CE10-AS9 -> 0 | CW10: =CF10-AT9 -> 0 | CX10: =CG10-AU9 -> 0 | CY10: =CH10-AV9 -> 0 | CZ10: =CI10-AW9 -> 0 | DA10: =CJ10-AX9 -> 0 | ... DF10: =CO10-BC9 -> 0 | DI10: =13-COUNTIF(CT10:DF10,0) -> 0
A11: 2016-2017 | B11: 42583 | C11: 201609 | D11: DED | E11: 1100 | F11: 0 | G11: 0 | H11: 0 | I11: 0 | J11: 0 | K11: 0 | L11: 1100 | M11: 0 | N11: 0 | O11: 0 | P11: OK | Q11: =IF(Table2[[#This Row],[Check Status with ga 55]]="ok",0,1) -> 0 | R11: =IFERROR(CONCATENATE(TEXT(RIGHT(C11,2)*29,"mmm"),"-",RIGHT(LEFT(C11,4),2)),"") -> Sep-16 | S11: =IFERROR((TEXT(RIGHT(C11,2)*29,"mmm")),"") -> Sep | T11: =IFERROR(RIGHT(LEFT(C11,4),2),"") -> 16 | U11: =Table2[[#This Row],[Total Premium]]+Table2[[#This Row],[Loan]] -> 1100 | W11: 7 | X11: 2019-2020 | Y11: 3000 | Z11: 3000 | AA11: 3000 | AB11: 3000 | AC11: 3000 | AD11: 3000 | AE11: 3000 | AF11: 3000 | AG11: 3000 | AH11: 3000 | AI11: 3000 | AJ11: 3000 | AK11: 36000 | AL11: 0 | AM11: 0 | AN11: 0 | AP11: 2019-2020 | AQ11: 3000 | AR11: 3000 | AS11: 3000 | AT11: 3000 | AU11: 3000 | AV11: 3000 | AW11: 3000 | AX11: 3000 | AY11: 3000 | AZ11: 3000 | BA11: 3000 | BB11: 3000 | BC11: 36000 | BF11: =IFERROR(Table5[[#This Row],[Sr No.]],"") -> 7 | BG11: =IFERROR(Table5[[#This Row],[Financial Year]],"") -> 2019-2020 | BH11: =Y11-AT11 -> 0 | BI11: =Z11-AU11 -> 0 | BJ11: =AA11-AV11 -> 0 | BK11: =AB11-AW11 -> 0 | BL11: =AC11-AX11 -> 0 | BM11: =AD11-AY11 -> 0 | BN11: =AE11-AZ11 -> 0 | BO11: =AF11-BA11 -> 0 | BP11: =AG11-BB11 -> 0 | BQ11: =AH11-AQ11 -> 0 | BR11: =AI11-AR11 -> 0 | BS11: =AJ11-AS11 -> 0 | BT11: =AK11-BC11 -> 0 | BX11: =13-COUNTIF(BH11:BT11,0) -> 0 | CB11: 2020-2021 | CC11: 5000 | CD11: 5000 | CE11: 5000 | CG11: 5000 | CH11: 10000 | CI11: 5000 | CJ11: 5000 | CK11: 5000 | CL11: 5000 | CM11: 5000 | CN11: 5000 | CO11: 60000 | CS11: =CB11 -> 2020-2021 | CT11: =CC11-AQ10 -> 0 | CU11: =CD11-AR10 -> 0 | CV11: =CE11-AS10 -> 0 | CW11: =CF11-AT10 -> 0 | CX11: =CG11-AU10 -> 0 | CY11: =CH11-AV10 -> 0 | CZ11: =CI11-AW10 -> 0 | DA11: =CJ11-AX10 -> 0 | ... DF11: =CO11-BC10 -> 0 | DI11: =13-COUNTIF(CT11:DF11,0) -> 0
A12: 2016-2017 | B12: 42644 | D12: ONLINE | E12: 0 | F12: 0 | G12: 0 | H12: 0 | I12: 0 | J12: 0 | K12: 0 | L12: 0 | M12: 0 | N12: 0 | O12: 0 | P12: OK | Q12: =IF(Table2[[#This Row],[Check Status with ga 55]]="ok",0,1) -> 0 | R12: =IFERROR(CONCATENATE(TEXT(RIGHT(C12,2)*29,"mmm"),"-",RIGHT(LEFT(C12,4),2)),"") | S12: =IFERROR((TEXT(RIGHT(C12,2)*29,"mmm")),"") | T12: =IFERROR(RIGHT(LEFT(C12,4),2),"") | U12: =Table2[[#This Row],[Total Premium]]+Table2[[#This Row],[Loan]] -> 0 | W12: 8 | X12: 2018-2019 | Y12: 3000 | Z12: 3000 | AA12: 3000 | AB12: 3000 | AC12: 3000 | AD12: 3000 | AE12: 3000 | AF12: 3000 | AG12: 0 | AH12: 3000 | AI12: 6000 | AJ12: 3000 | AK12: 36000 | AL12: 0 | AM12: 0 | AN12: 0 | AP12: 2018-2019 | AQ12: 3000 | AR12: 6000 | AS12: 3000 | AT12: 3000 | AU12: 3000 | AV12: 3000 | AW12: 3000 | AX12: 3000 | AY12: 3000 | AZ12: 3000 | BA12: 3000 | BC12: 36000 | BF12: =IFERROR(Table5[[#This Row],[Sr No.]],"") -> 8 | BG12: =IFERROR(Table5[[#This Row],[Financial Year]],"") -> 2018-2019 | BH12: =Y12-AT12 -> 0 | BI12: =Z12-AU12 -> 0 | BJ12: =AA12-AV12 -> 0 | BK12: =AB12-AW12 -> 0 | BL12: =AC12-AX12 -> 0 | BM12: =AD12-AY12 -> 0 | BN12: =AE12-AZ12 -> 0 | BO12: =AF12-BA12 -> 0 | BP12: =AG12-BB12 -> 0 | BQ12: =AH12-AQ12 -> 0 | BR12: =AI12-AR12 -> 0 | BS12: =AJ12-AS12 -> 0 | BT12: =AK12-BC12 -> 0 | BX12: =13-COUNTIF(BH12:BT12,0) -> 0 | CB12: 2019-2020 | CC12: 3000 | CD12: 3000 | CE12: 3000 | CF12: 3000 | CG12: 3000 | CH12: 3000 | CI12: 3000 | CJ12: 3000 | CK12: 3000 | CL12: 3000 | CM12: 3000 | CN12: 3000 | CO12: 36000 | CS12: =CB12 -> 2019-2020 | CT12: =CC12-AQ11 -> 0 | CU12: =CD12-AR11 -> 0 | CV12: =CE12-AS11 -> 0 | CW12: =CF12-AT11 -> 0 | CX12: =CG12-AU11 -> 0 | CY12: =CH12-AV11 -> 0 | CZ12: =CI12-AW11 -> 0 | DA12: =CJ12-AX11 -> 0 | ... DF12: =CO12-BC11 -> 0 | DI12: =13-COUNTIF(CT12:DF12,0) -> 0
A13: 2016-2017 | B13: 42675 | C13: 201612 | D13: DED | E13: 1100 | F13: 0 | G13: 0 | H13: 0 | I13: 0 | J13: 0 | K13: 0 | L13: 1100 | M13: 0 | N13: 0 | O13: 0 | P13: OK | Q13: =IF(Table2[[#This Row],[Check Status with ga 55]]="ok",0,1) -> 0 | R13: =IFERROR(CONCATENATE(TEXT(RIGHT(C13,2)*29,"mmm"),"-",RIGHT(LEFT(C13,4),2)),"") -> Dec-16 | S13: =IFERROR((TEXT(RIGHT(C13,2)*29,"mmm")),"") -> Dec | T13: =IFERROR(RIGHT(LEFT(C13,4),2),"") -> 16 | U13: =Table2[[#This Row],[Total Premium]]+Table2[[#This Row],[Loan]] -> 1100 | W13: 9 | X13: 2017-2018 | Y13: 2650 | Z13: 2650 | AA13: 2650 | AB13: 2650 | AC13: 2650 | AD13: 2650 | AE13: 2650 | AF13: 2650 | AG13: 2650 | AH13: 2650 | AI13: 2650 | AJ13: 2650 | AK13: 31800 | AL13: 0 | AM13: 0 | AN13: 0 | AP13: 2017-2018 | AQ13: 2650 | AR13: 2650 | AS13: 2650 | AT13: 2650 | AU13: 2650 | AV13: 2650 | AW13: 2650 | AX13: 2650 | AY13: 2650 | AZ13: 2650 | BA13: 2650 | BB13: 2650 | BC13: 31800 | BF13: =IFERROR(Table5[[#This Row],[Sr No.]],"") -> 9 | BG13: =IFERROR(Table5[[#This Row],[Financial Year]],"") -> 2017-2018 | BH13: =Y13-AT13 -> 0 | BI13: =Z13-AU13 -> 0 | BJ13: =AA13-AV13 -> 0 | BK13: =AB13-AW13 -> 0 | BL13: =AC13-AX13 -> 0 | BM13: =AD13-AY13 -> 0 | BN13: =AE13-AZ13 -> 0 | BO13: =AF13-BA13 -> 0 | BP13: =AG13-BB13 -> 0 | BQ13: =AH13-AQ13 -> 0 | BR13: =AI13-AR13 -> 0 | BS13: =AJ13-AS13 -> 0 | BT13: =AK13-BC13 -> 0 | BX13: =13-COUNTIF(BH13:BT13,0) -> 0 | CB13: 2018-2019 | CC13: 3000 | CD13: 6000 | CE13: 3000 | CF13: 3000 | CG13: 3000 | CH13: 3000 | CI13: 3000 | CJ13: 3000 | CK13: 3000 | CL13: 3000 | CM13: 3000 | CO13: 36000 | CS13: =CB13 -> 2018-2019 | CT13: =CC13-AQ12 -> 0 | CU13: =CD13-AR12 -> 0 | CV13: =CE13-AS12 -> 0 | CW13: =CF13-AT12 -> 0 | CX13: =CG13-AU12 -> 0 | CY13: =CH13-AV12 -> 0 | CZ13: =CI13-AW12 -> 0 | DA13: =CJ13-AX12 -> 0 | ... DF13: =CO13-BC12 -> 0 | DI13: =13-COUNTIF(CT13:DF13,0) -> 0
A14: 2016-2017 | B14: 42705 | C14: 201701 | D14: DED | E14: 1100 | F14: 0 | G14: 0 | H14: 0 | I14: 0 | J14: 0 | K14: 0 | L14: 1100 | M14: 0 | N14: 0 | O14: 0 | P14: OK | Q14: =IF(Table2[[#This Row],[Check Status with ga 55]]="ok",0,1) -> 0 | R14: =IFERROR(CONCATENATE(TEXT(RIGHT(C14,2)*29,"mmm"),"-",RIGHT(LEFT(C14,4),2)),"") -> Jan-17 | S14: =IFERROR((TEXT(RIGHT(C14,2)*29,"mmm")),"") -> Jan | T14: =IFERROR(RIGHT(LEFT(C14,4),2),"") -> 17 | U14: =Table2[[#This Row],[Total Premium]]+Table2[[#This Row],[Loan]] -> 1100 | W14: 10 | X14: 2016-2017 | Y14: 1100 | Z14: 1100 | AA14: 1100 | AB14: 1100 | AC14: 1100 | AD14: 1100 | AE14: 2200 | AF14: 0 | AG14: 1100 | AH14: 1100 | AI14: 1100 | AJ14: 1100 | AK14: 13200 | AL14: 0 | AM14: 0 | AN14: 0 | AP14: 2016-2017 | AQ14: 1100 | AR14: 1100 | AS14: 1100 | AT14: 1100 | AU14: 1100 | AV14: 1100 | AW14: 1100 | AX14: 1100 | AY14: 1100 | AZ14: 2200 | BB14: 1100 | BC14: 13200 | BF14: =IFERROR(Table5[[#This Row],[Sr No.]],"") -> 10 | BG14: =IFERROR(Table5[[#This Row],[Financial Year]],"") -> 2016-2017 | BH14: =Y14-AT14 -> 0 | BI14: =Z14-AU14 -> 0 | BJ14: =AA14-AV14 -> 0 | BK14: =AB14-AW14 -> 0 | BL14: =AC14-AX14 -> 0 | BM14: =AD14-AY14 -> 0 | BN14: =AE14-AZ14 -> 0 | BO14: =AF14-BA14 -> 0 | BP14: =AG14-BB14 -> 0 | BQ14: =AH14-AQ14 -> 0 | BR14: =AI14-AR14 -> 0 | BS14: =AJ14-AS14 -> 0 | BT14: =AK14-BC14 -> 0 | BX14: =13-COUNTIF(BH14:BT14,0) -> 0 | CB14: 2017-2018 | CC14: 2650 | CD14: 2650 | CE14: 2650 | CF14: 2650 | CG14: 2650 | CH14: 2650 | CI14: 2650 | CJ14: 2650 | CK14: 2650 | CL14: 2650 | CM14: 2650 | CN14: 2650 | CO14: 31800 | CS14: =CB14 -> 2017-2018 | CT14: =CC14-AQ13 -> 0 | CU14: =CD14-AR13 -> 0 | CV14: =CE14-AS13 -> 0 | CW14: =CF14-AT13 -> 0 | CX14: =CG14-AU13 -> 0 | CY14: =CH14-AV13 -> 0 | CZ14: =CI14-AW13 -> 0 | DA14: =CJ14-AX13 -> 0 | ... DF14: =CO14-BC13 -> 0 | DI14: =13-COUNTIF(CT14:DF14,0) -> 0
A15: 2016-2017 | B15: 42736 | C15: 201702 | D15: DED | E15: 1100 | F15: 0 | G15: 0 | H15: 0 | I15: 0 | J15: 0 | K15: 0 | L15: 1100 | M15: 0 | N15: 0 | O15: 0 | P15: OK | Q15: =IF(Table2[[#This Row],[Check Status with ga 55]]="ok",0,1) -> 0 | R15: =IFERROR(CONCATENATE(TEXT(RIGHT(C15,2)*29,"mmm"),"-",RIGHT(LEFT(C15,4),2)),"") -> Feb-17 | S15: =IFERROR((TEXT(RIGHT(C15,2)*29,"mmm")),"") -> Feb | T15: =IFERROR(RIGHT(LEFT(C15,4),2),"") -> 17 | U15: =Table2[[#This Row],[Total Premium]]+Table2[[#This Row],[Loan]] -> 1100 | Y15: =SUM(Y5:Y14) -> 34750 | Z15: =SUM(Z5:Z14) -> 39750 | AA15: =SUM(AA5:AA14) -> 44750 | AB15: =SUM(AB5:AB14) -> 46992 | AC15: =SUM(AC5:AC14) -> 46992 | AD15: =SUM(AD5:AD14) -> 46992 | AE15: =SUM(AE5:AE14) -> 53092 | AF15: =SUM(AF5:AF14) -> 40892 | ... AN15: =SUM(AN5:AN14) -> 0 | AP15: Grand Total | AQ15: 46992 | AR15: 49992 | AS15: 46992 | AT15: 34750 | AU15: 474250 | AV15: 44750 | AW15: 46992 | AX15: 46992 | AY15: 46992 | AZ15: 53092 | BA15: 40892 | BB15: 43992 | BC15: 976678 | BF15: =IFERROR(Table5[[#This Row],[Sr No.]],"") | BG15: =IFERROR(Table5[[#This Row],[Financial Year]],"") | BH15: =Y15-AT15 -> 0 | BI15: =Z15-AU15 -> -434500 | BJ15: =AA15-AV15 -> 0 | BK15: =AB15-AW15 -> 0 | BL15: =AC15-AX15 -> 0 | BM15: =AD15-AY15 -> 0 | BN15: =AE15-AZ15 -> 0 | BO15: =AF15-BA15 -> 0 | BP15: =AG15-BB15 -> 0 | BQ15: =AH15-AQ15 -> 0 | BR15: =AI15-AR15 -> 0 | BS15: =AJ15-AS15 -> 0 | BT15: =AK15-BC15 -> -434500 | BX15: =13-COUNTIF(BH15:BT15,0) -> 2 | CB15: 2016-2017 | CC15: 1100 | CD15: 1100 | CE15: 1100 | CF15: 1100 | CG15: 1100 | CH15: 1100 | CI15: 1100 | CJ15: 1100 | CK15: 1100 | CL15: 2200 | CN15: 1100 | CO15: 13200 | CS15: =CB15 -> 2016-2017 | CT15: =CC15-AQ14 -> 0 | CU15: =CD15-AR14 -> 0 | CV15: =CE15-AS14 -> 0 | CW15: =CF15-AT14 -> 0 | CX15: =CG15-AU14 -> 0 | CY15: =CH15-AV14 -> 0 | CZ15: =CI15-AW14 -> 0 | DA15: =CJ15-AX14 -> 0 | ... DF15: =CO15-BC14 -> 0 | DI15: =13-COUNTIF(CT15:DF15,0) -> 0
A16: 2016-2017 | B16: 42767 | C16: 201703 | D16: DED | E16: 1100 | F16: 0 | G16: 0 | H16: 0 | I16: 0 | J16: 0 | K16: 0 | L16: 1100 | M16: 0 | N16: 0 | O16: 0 | P16: OK | Q16: =IF(Table2[[#This Row],[Check Status with ga 55]]="ok",0,1) -> 0 | R16: =IFERROR(CONCATENATE(TEXT(RIGHT(C16,2)*29,"mmm"),"-",RIGHT(LEFT(C16,4),2)),"") -> Mar-17 | S16: =IFERROR((TEXT(RIGHT(C16,2)*29,"mmm")),"") -> Mar | T16: =IFERROR(RIGHT(LEFT(C16,4),2),"") -> 17 | U16: =Table2[[#This Row],[Total Premium]]+Table2[[#This Row],[Loan]] -> 1100 | BF16: =IFERROR(Table5[[#This Row],[Sr No.]],"") | BG16: =IFERROR(Table5[[#This Row],[Financial Year]],"") | BH16: =Y16-AT16 -> 0 | BI16: =Z16-AU16 -> 0 | BJ16: =AA16-AV16 -> 0 | BK16: =AB16-AW16 -> 0 | BL16: =AC16-AX16 -> 0 | BM16: =AD16-AY16 -> 0 | BN16: =AE16-AZ16 -> 0 | BO16: =AF16-BA16 -> 0 | BP16: =AG16-BB16 -> 0 | BQ16: =AH16-AQ16 -> 0 | BR16: =AI16-AR16 -> 0 | BS16: =AJ16-AS16 -> 0 | BT16: =AK16-BC16 -> 0 | BX16: =13-COUNTIF(BH16:BT16,0) -> 0 | CB16: Grand Total | CC16: 46992 | CD16: 49992 | CE16: 46992 | CF16: 34750 | CG16: 474250 | CH16: 44750 | CI16: 46992 | CJ16: 46992 | CK16: 46992 | CL16: 53092 | CM16: 40892 | CN16: 43992 | CO16: 976678
A17: 2017-2018 | B17: 42795 | C17: 201704 | D17: DED | E17: 2650 | F17: 0 | G17: 0 | H17: 0 | I17: 0 | J17: 0 | K17: 0 | L17: 2650 | M17: 0 | N17: 0 | O17: 0 | P17: OK | Q17: =IF(Table2[[#This Row],[Check Status with ga 55]]="ok",0,1) -> 0 | R17: =IFERROR(CONCATENATE(TEXT(RIGHT(C17,2)*29,"mmm"),"-",RIGHT(LEFT(C17,4),2)),"") -> Apr-17 | S17: =IFERROR((TEXT(RIGHT(C17,2)*29,"mmm")),"") -> Apr | T17: =IFERROR(RIGHT(LEFT(C17,4),2),"") -> 17 | U17: =Table2[[#This Row],[Total Premium]]+Table2[[#This Row],[Loan]] -> 2650
A18: 2017-2018 | B18: 42826 | C18: 201705 | D18: DED | E18: 2650 | F18: 0 | G18: 0 | H18: 0 | I18: 0 | J18: 0 | K18: 0 | L18: 2650 | M18: 0 | N18: 0 | O18: 0 | P18: OK | Q18: =IF(Table2[[#This Row],[Check Status with ga 55]]="ok",0,1) -> 0 | R18: =IFERROR(CONCATENATE(TEXT(RIGHT(C18,2)*29,"mmm"),"-",RIGHT(LEFT(C18,4),2)),"") -> May-17 | S18: =IFERROR((TEXT(RIGHT(C18,2)*29,"mmm")),"") -> May | T18: =IFERROR(RIGHT(LEFT(C18,4),2),"") -> 17 | U18: =Table2[[#This Row],[Total Premium]]+Table2[[#This Row],[Loan]] -> 2650
A19: 2017-2018 | B19: 42856 | C19: 201706 | D19: DED | E19: 2650 | F19: 0 | G19: 0 | H19: 0 | I19: 0 | J19: 0 | K19: 0 | L19: 2650 | M19: 0 | N19: 0 | O19: 0 | P19: OK | Q19: =IF(Table2[[#This Row],[Check Status with ga 55]]="ok",0,1) -> 0 | R19: =IFERROR(CONCATENATE(TEXT(RIGHT(C19,2)*29,"mmm"),"-",RIGHT(LEFT(C19,4),2)),"") -> Jun-17 | S19: =IFERROR((TEXT(RIGHT(C19,2)*29,"mmm")),"") -> Jun | T19: =IFERROR(RIGHT(LEFT(C19,4),2),"") -> 17 | U19: =Table2[[#This Row],[Total Premium]]+Table2[[#This Row],[Loan]] -> 2650
A20: 2017-2018 | B20: 42887 | C20: 201707 | D20: DED | E20: 2650 | F20: 0 | G20: 0 | H20: 0 | I20: 0 | J20: 0 | K20: 0 | L20: 2650 | M20: 0 | N20: 0 | O20: 0 | P20: OK | Q20: =IF(Table2[[#This Row],[Check Status with ga 55]]="ok",0,1) -> 0 | R20: =IFERROR(CONCATENATE(TEXT(RIGHT(C20,2)*29,"mmm"),"-",RIGHT(LEFT(C20,4),2)),"") -> Jul-17 | S20: =IFERROR((TEXT(RIGHT(C20,2)*29,"mmm")),"") -> Jul | T20: =IFERROR(RIGHT(LEFT(C20,4),2),"") -> 17 | U20: =Table2[[#This Row],[Total Premium]]+Table2[[#This Row],[Loan]] -> 2650
A21: 2017-2018 | B21: 42917 | C21: 201708 | D21: DED | E21: 2650 | F21: 0 | G21: 0 | H21: 0 | I21: 0 | J21: 0 | K21: 0 | L21: 2650 | M21: 0 | N21: 0 | O21: 0 | P21: OK | Q21: =IF(Table2[[#This Row],[Check Status with ga 55]]="ok",0,1) -> 0 | R21: =IFERROR(CONCATENATE(TEXT(RIGHT(C21,2)*29,"mmm"),"-",RIGHT(LEFT(C21,4),2)),"") -> Aug-17 | S21: =IFERROR((TEXT(RIGHT(C21,2)*29,"mmm")),"") -> Aug | T21: =IFERROR(RIGHT(LEFT(C21,4),2),"") -> 17 | U21: =Table2[[#This Row],[Total Premium]]+Table2[[#This Row],[Loan]] -> 2650
A22: 2017-2018 | B22: 42948 | C22: 201709 | D22: DED | E22: 2650 | F22: 0 | G22: 0 | H22: 0 | I22: 0 | J22: 0 | K22: 0 | L22: 2650 | M22: 0 | N22: 0 | O22: 0 | P22: OK | Q22: =IF(Table2[[#This Row],[Check Status with ga 55]]="ok",0,1) -> 0 | R22: =IFERROR(CONCATENATE(TEXT(RIGHT(C22,2)*29,"mmm"),"-",RIGHT(LEFT(C22,4),2)),"") -> Sep-17 | S22: =IFERROR((TEXT(RIGHT(C22,2)*29,"mmm")),"") -> Sep | T22: =IFERROR(RIGHT(LEFT(C22,4),2),"") -> 17 | U22: =Table2[[#This Row],[Total Premium]]+Table2[[#This Row],[Loan]] -> 2650
A23: 2017-2018 | B23: 42979 | C23: 201710 | D23: DED | E23: 2650 | F23: 0 | G23: 0 | H23: 0 | I23: 0 | J23: 0 | K23: 0 | L23: 2650 | M23: 0 | N23: 0 | O23: 0 | P23: OK | Q23: =IF(Table2[[#This Row],[Check Status with ga 55]]="ok",0,1) -> 0 | R23: =IFERROR(CONCATENATE(TEXT(RIGHT(C23,2)*29,"mmm"),"-",RIGHT(LEFT(C23,4),2)),"") -> Oct-17 | S23: =IFERROR((TEXT(RIGHT(C23,2)*29,"mmm")),"") -> Oct | T23: =IFERROR(RIGHT(LEFT(C23,4),2),"") -> 17 | U23: =Table2[[#This Row],[Total Premium]]+Table2[[#This Row],[Loan]] -> 2650
A24: 2017-2018 | B24: 43009 | C24: 201711 | D24: DED | E24: 2650 | F24: 0 | G24: 0 | H24: 0 | I24: 0 | J24: 0 | K24: 0 | L24: 2650 | M24: 0 | N24: 0 | O24: 0 | P24: OK | Q24: =IF(Table2[[#This Row],[Check Status with ga 55]]="ok",0,1) -> 0 | R24: =IFERROR(CONCATENATE(TEXT(RIGHT(C24,2)*29,"mmm"),"-",RIGHT(LEFT(C24,4),2)),"") -> Nov-17 | S24: =IFERROR((TEXT(RIGHT(C24,2)*29,"mmm")),"") -> Nov | T24: =IFERROR(RIGHT(LEFT(C24,4),2),"") -> 17 | U24: =Table2[[#This Row],[Total Premium]]+Table2[[#This Row],[Loan]] -> 2650
A25: 2017-2018 | B25: 43040 | C25: 201712 | D25: DED | E25: 2650 | F25: 0 | G25: 0 | H25: 0 | I25: 0 | J25: 0 | K25: 0 | L25: 2650 | M25: 0 | N25: 0 | O25: 0 | P25: OK | Q25: =IF(Table2[[#This Row],[Check Status with ga 55]]="ok",0,1) -> 0 | R25: =IFERROR(CONCATENATE(TEXT(RIGHT(C25,2)*29,"mmm"),"-",RIGHT(LEFT(C25,4),2)),"") -> Dec-17 | S25: =IFERROR((TEXT(RIGHT(C25,2)*29,"mmm")),"") -> Dec | T25: =IFERROR(RIGHT(LEFT(C25,4),2),"") -> 17 | U25: =Table2[[#This Row],[Total Premium]]+Table2[[#This Row],[Loan]] -> 2650
A26: 2017-2018 | B26: 43070 | C26: 201801 | D26: DED | E26: 2650 | F26: 0 | G26: 0 | H26: 0 | I26: 0 | J26: 0 | K26: 0 | L26: 2650 | M26: 0 | N26: 0 | O26: 0 | P26: OK | Q26: =IF(Table2[[#This Row],[Check Status with ga 55]]="ok",0,1) -> 0 | R26: =IFERROR(CONCATENATE(TEXT(RIGHT(C26,2)*29,"mmm"),"-",RIGHT(LEFT(C26,4),2)),"") -> Jan-18 | S26: =IFERROR((TEXT(RIGHT(C26,2)*29,"mmm")),"") -> Jan | T26: =IFERROR(RIGHT(LEFT(C26,4),2),"") -> 18 | U26: =Table2[[#This Row],[Total Premium]]+Table2[[#This Row],[Loan]] -> 2650
A27: 2017-2018 | B27: 43101 | C27: 201802 | D27: DED | E27: 2650 | F27: 0 | G27: 0 | H27: 0 | I27: 0 | J27: 0 | K27: 0 | L27: 2650 | M27: 0 | N27: 0 | O27: 0 | P27: OK | Q27: =IF(Table2[[#This Row],[Check Status with ga 55]]="ok",0,1) -> 0 | R27: =IFERROR(CONCATENATE(TEXT(RIGHT(C27,2)*29,"mmm"),"-",RIGHT(LEFT(C27,4),2)),"") -> Feb-18 | S27: =IFERROR((TEXT(RIGHT(C27,2)*29,"mmm")),"") -> Feb | T27: =IFERROR(RIGHT(LEFT(C27,4),2),"") -> 18 | U27: =Table2[[#This Row],[Total Premium]]+Table2[[#This Row],[Loan]] -> 2650
A28: 2017-2018 | B28: 43132 | C28: 201803 | D28: DED | E28: 2650 | F28: 0 | G28: 0 | H28: 0 | I28: 0 | J28: 0 | K28: 0 | L28: 2650 | M28: 0 | N28: 0 | O28: 0 | P28: OK | Q28: =IF(Table2[[#This Row],[Check Status with ga 55]]="ok",0,1) -> 0 | R28: =IFERROR(CONCATENATE(TEXT(RIGHT(C28,2)*29,"mmm"),"-",RIGHT(LEFT(C28,4),2)),"") -> Mar-18 | S28: =IFERROR((TEXT(RIGHT(C28,2)*29,"mmm")),"") -> Mar | T28: =IFERROR(RIGHT(LEFT(C28,4),2),"") -> 18 | U28: =Table2[[#This Row],[Total Premium]]+Table2[[#This Row],[Loan]] -> 2650
... A36: 2018-2019 | B36: 43374 | C36: 201811 | D36: DED | E36: 3000 | F36: 0 | G36: 0 | H36: 0 | I36: 0 | J36: 0 | K36: 0 | L36: 3000 | M36: 0 | N36: 0 | O36: 0 | P36: OK | Q36: =IF(Table2[[#This Row],[Check Status with ga 55]]="ok",0,1) -> 0 | R36: =IFERROR(CONCATENATE(TEXT(RIGHT(C36,2)*29,"mmm"),"-",RIGHT(LEFT(C36,4),2)),"") -> Nov-18 | S36: =IFERROR((TEXT(RIGHT(C36,2)*29,"mmm")),"") -> Nov | T36: =IFERROR(RIGHT(LEFT(C36,4),2),"") -> 18 | U36: =Table2[[#This Row],[Total Premium]]+Table2[[#This Row],[Loan]] -> 3000
A37: 2018-2019 | B37: 43405 | D37: ONLINE | E37: 0 | F37: 0 | G37: 0 | H37: 0 | I37: 0 | J37: 0 | K37: 0 | L37: 0 | M37: 0 | N37: 0 | O37: 0 | P37: OK | Q37: =IF(Table2[[#This Row],[Check Status with ga 55]]="ok",0,1) -> 0 | R37: =IFERROR(CONCATENATE(TEXT(RIGHT(C37,2)*29,"mmm"),"-",RIGHT(LEFT(C37,4),2)),"") | S37: =IFERROR((TEXT(RIGHT(C37,2)*29,"mmm")),"") | T37: =IFERROR(RIGHT(LEFT(C37,4),2),"") | U37: =Table2[[#This Row],[Total Premium]]+Table2[[#This Row],[Loan]] -> 0
A38: 2018-2019 | B38: 43435 | C38: 201901 | D38: DED | E38: 3000 | F38: 0 | G38: 0 | H38: 0 | I38: 0 | J38: 0 | K38: 0 | L38: 3000 | M38: 0 | N38: 0 | O38: 0 | P38: OK | Q38: =IF(Table2[[#This Row],[Check Status with ga 55]]="ok",0,1) -> 0 | R38: =IFERROR(CONCATENATE(TEXT(RIGHT(C38,2)*29,"mmm"),"-",RIGHT(LEFT(C38,4),2)),"") -> Jan-19 | S38: =IFERROR((TEXT(RIGHT(C38,2)*29,"mmm")),"") -> Jan | T38: =IFERROR(RIGHT(LEFT(C38,4),2),"") -> 19 | U38: =Table2[[#This Row],[Total Premium]]+Table2[[#This Row],[Loan]] -> 3000
A39: 2018-2019 | B39: 43466 | C39: 201902 | D39: DED | E39: 6000 | F39: 0 | G39: 0 | H39: 0 | I39: 0 | J39: 0 | K39: 0 | L39: 6000 | M39: 0 | N39: 0 | O39: 0 | P39: OK | Q39: =IF(Table2[[#This Row],[Check Status with ga 55]]="ok",0,1) -> 0 | R39: =IFERROR(CONCATENATE(TEXT(RIGHT(C39,2)*29,"mmm"),"-",RIGHT(LEFT(C39,4),2)),"") -> Feb-19 | S39: =IFERROR((TEXT(RIGHT(C39,2)*29,"mmm")),"") -> Feb | T39: =IFERROR(RIGHT(LEFT(C39,4),2),"") -> 19 | U39: =Table2[[#This Row],[Total Premium]]+Table2[[#This Row],[Loan]] -> 6000
A40: 2018-2019 | B40: 43497 | C40: 201903 | D40: DED | E40: 3000 | F40: 0 | G40: 0 | H40: 0 | I40: 0 | J40: 0 | K40: 0 | L40: 3000 | M40: 0 | N40: 0 | O40: 0 | P40: OK | Q40: =IF(Table2[[#This Row],[Check Status with ga 55]]="ok",0,1) -> 0 | R40: =IFERROR(CONCATENATE(TEXT(RIGHT(C40,2)*29,"mmm"),"-",RIGHT(LEFT(C40,4),2)),"") -> Mar-19 | S40: =IFERROR((TEXT(RIGHT(C40,2)*29,"mmm")),"") -> Mar | T40: =IFERROR(RIGHT(LEFT(C40,4),2),"") -> 19 | U40: =Table2[[#This Row],[Total Premium]]+Table2[[#This Row],[Loan]] -> 3000
A41: 2019-2020 | B41: 43525 | C41: 201904 | D41: DED | E41: 3000 | F41: 0 | G41: 0 | H41: 0 | I41: 0 | J41: 0 | K41: 0 | L41: 3000 | M41: 0 | N41: 0 | O41: 0 | P41: OK | Q41: =IF(Table2[[#This Row],[Check Status with ga 55]]="ok",0,1) -> 0 | R41: =IFERROR(CONCATENATE(TEXT(RIGHT(C41,2)*29,"mmm"),"-",RIGHT(LEFT(C41,4),2)),"") -> Apr-19 | S41: =IFERROR((TEXT(RIGHT(C41,2)*29,"mmm")),"") -> Apr | T41: =IFERROR(RIGHT(LEFT(C41,4),2),"") -> 19 | U41: =Table2[[#This Row],[Total Premium]]+Table2[[#This Row],[Loan]] -> 3000
A42: 2019-2020 | B42: 43556 | C42: 201905 | D42: DED | E42: 3000 | F42: 0 | G42: 0 | H42: 0 | I42: 0 | J42: 0 | K42: 0 | L42: 3000 | M42: 0 | N42: 0 | O42: 0 | P42: OK | Q42: =IF(Table2[[#This Row],[Check Status with ga 55]]="ok",0,1) -> 0 | R42: =IFERROR(CONCATENATE(TEXT(RIGHT(C42,2)*29,"mmm"),"-",RIGHT(LEFT(C42,4),2)),"") -> May-19 | S42: =IFERROR((TEXT(RIGHT(C42,2)*29,"mmm")),"") -> May | T42: =IFERROR(RIGHT(LEFT(C42,4),2),"") -> 19 | U42: =Table2[[#This Row],[Total Premium]]+Table2[[#This Row],[Loan]] -> 3000
A43: 2019-2020 | B43: 43586 | C43: 201906 | D43: DED | E43: 3000 | F43: 0 | G43: 0 | H43: 0 | I43: 0 | J43: 0 | K43: 0 | L43: 3000 | M43: 0 | N43: 0 | O43: 0 | P43: OK | Q43: =IF(Table2[[#This Row],[Check Status with ga 55]]="ok",0,1) -> 0 | R43: =IFERROR(CONCATENATE(TEXT(RIGHT(C43,2)*29,"mmm"),"-",RIGHT(LEFT(C43,4),2)),"") -> Jun-19 | S43: =IFERROR((TEXT(RIGHT(C43,2)*29,"mmm")),"") -> Jun | T43: =IFERROR(RIGHT(LEFT(C43,4),2),"") -> 19 | U43: =Table2[[#This Row],[Total Premium]]+Table2[[#This Row],[Loan]] -> 3000
A44: 2019-2020 | B44: 43617 | C44: 201907 | D44: DED | E44: 3000 | F44: 0 | G44: 0 | H44: 0 | I44: 0 | J44: 0 | K44: 0 | L44: 3000 | M44: 0 | N44: 0 | O44: 0 | P44: OK | Q44: =IF(Table2[[#This Row],[Check Status with ga 55]]="ok",0,1) -> 0 | R44: =IFERROR(CONCATENATE(TEXT(RIGHT(C44,2)*29,"mmm"),"-",RIGHT(LEFT(C44,4),2)),"") -> Jul-19 | S44: =IFERROR((TEXT(RIGHT(C44,2)*29,"mmm")),"") -> Jul | T44: =IFERROR(RIGHT(LEFT(C44,4),2),"") -> 19 | U44: =Table2[[#This Row],[Total Premium]]+Table2[[#This Row],[Loan]] -> 3000
A45: 2019-2020 | B45: 43647 | C45: 201908 | D45: DED | E45: 3000 | F45: 0 | G45: 0 | H45: 0 | I45: 0 | J45: 0 | K45: 0 | L45: 3000 | M45: 0 | N45: 0 | O45: 0 | P45: OK | Q45: =IF(Table2[[#This Row],[Check Status with ga 55]]="ok",0,1) -> 0 | R45: =IFERROR(CONCATENATE(TEXT(RIGHT(C45,2)*29,"mmm"),"-",RIGHT(LEFT(C45,4),2)),"") -> Aug-19 | S45: =IFERROR((TEXT(RIGHT(C45,2)*29,"mmm")),"") -> Aug | T45: =IFERROR(RIGHT(LEFT(C45,4),2),"") -> 19 | U45: =Table2[[#This Row],[Total Premium]]+Table2[[#This Row],[Loan]] -> 3000
A46: 2019-2020 | B46: 43678 | C46: 201909 | D46: DED | E46: 3000 | F46: 0 | G46: 0 | H46: 0 | I46: 0 | J46: 0 | K46: 0 | L46: 3000 | M46: 0 | N46: 0 | O46: 0 | P46: OK | Q46: =IF(Table2[[#This Row],[Check Status with ga 55]]="ok",0,1) -> 0 | R46: =IFERROR(CONCATENATE(TEXT(RIGHT(C46,2)*29,"mmm"),"-",RIGHT(LEFT(C46,4),2)),"") -> Sep-19 | S46: =IFERROR((TEXT(RIGHT(C46,2)*29,"mmm")),"") -> Sep | T46: =IFERROR(RIGHT(LEFT(C46,4),2),"") -> 19 | U46: =Table2[[#This Row],[Total Premium]]+Table2[[#This Row],[Loan]] -> 3000
A47: 2019-2020 | B47: 43709 | C47: 201910 | D47: DED | E47: 3000 | F47: 0 | G47: 0 | H47: 0 | I47: 0 | J47: 0 | K47: 0 | L47: 3000 | M47: 0 | N47: 0 | O47: 0 | P47: OK | Q47: =IF(Table2[[#This Row],[Check Status with ga 55]]="ok",0,1) -> 0 | R47: =IFERROR(CONCATENATE(TEXT(RIGHT(C47,2)*29,"mmm"),"-",RIGHT(LEFT(C47,4),2)),"") -> Oct-19 | S47: =IFERROR((TEXT(RIGHT(C47,2)*29,"mmm")),"") -> Oct | T47: =IFERROR(RIGHT(LEFT(C47,4),2),"") -> 19 | U47: =Table2[[#This Row],[Total Premium]]+Table2[[#This Row],[Loan]] -> 3000
A48: 2019-2020 | B48: 43739 | C48: 201911 | D48: DED | E48: 3000 | F48: 0 | G48: 0 | H48: 0 | I48: 0 | J48: 0 | K48: 0 | L48: 3000 | M48: 0 | N48: 0 | O48: 0 | P48: OK | Q48: =IF(Table2[[#This Row],[Check Status with ga 55]]="ok",0,1) -> 0 | R48: =IFERROR(CONCATENATE(TEXT(RIGHT(C48,2)*29,"mmm"),"-",RIGHT(LEFT(C48,4),2)),"") -> Nov-19 | S48: =IFERROR((TEXT(RIGHT(C48,2)*29,"mmm")),"") -> Nov | T48: =IFERROR(RIGHT(LEFT(C48,4),2),"") -> 19 | U48: =Table2[[#This Row],[Total Premium]]+Table2[[#This Row],[Loan]] -> 3000
A49: 2019-2020 | B49: 43770 | C49: 201912 | D49: DED | E49: 3000 | F49: 0 | G49: 0 | H49: 0 | I49: 0 | J49: 0 | K49: 0 | L49: 3000 | M49: 0 | N49: 0 | O49: 0 | P49: OK | Q49: =IF(Table2[[#This Row],[Check Status with ga 55]]="ok",0,1) -> 0 | R49: =IFERROR(CONCATENATE(TEXT(RIGHT(C49,2)*29,"mmm"),"-",RIGHT(LEFT(C49,4),2)),"") -> Dec-19 | S49: =IFERROR((TEXT(RIGHT(C49,2)*29,"mmm")),"") -> Dec | T49: =IFERROR(RIGHT(LEFT(C49,4),2),"") -> 19 | U49: =Table2[[#This Row],[Total Premium]]+Table2[[#This Row],[Loan]] -> 3000
... A107: 2024-2025 | B107: 45536 | C107: 202410 | D107: DED | E107: 10000 | F107: 0 | G107: 0 | H107: 0 | I107: 0 | J107: 0 | K107: 0 | L107: 10000 | M107: 0 | N107: 0 | O107: 0 | P107: OK | Q107: =IF(Table2[[#This Row],[Check Status with ga 55]]="ok",0,1) -> 0 | R107: =IFERROR(CONCATENATE(TEXT(RIGHT(C107,2)*29,"mmm"),"-",RIGHT(LEFT(C107,4),2)),"") -> Oct-24 | S107: =IFERROR((TEXT(RIGHT(C107,2)*29,"mmm")),"") -> Oct | T107: =IFERROR(RIGHT(LEFT(C107,4),2),"") -> 24 | U107: =Table2[[#This Row],[Total Premium]]+Table2[[#This Row],[Loan]] -> 10000
A108: 2024-2025 | B108: 45566 | D108: ONLINE | E108: 0 | F108: 0 | G108: 0 | H108: 0 | I108: 0 | J108: 0 | K108: 0 | L108: 0 | M108: 0 | N108: 0 | O108: 0 | P108: OK | Q108: =IF(Table2[[#This Row],[Check Status with ga 55]]="ok",0,1) -> 0 | R108: =IFERROR(CONCATENATE(TEXT(RIGHT(C108,2)*29,"mmm"),"-",RIGHT(LEFT(C108,4),2)),"") | S108: =IFERROR((TEXT(RIGHT(C108,2)*29,"mmm")),"") | T108: =IFERROR(RIGHT(LEFT(C108,4),2),"") | U108: =Table2[[#This Row],[Total Premium]]+Table2[[#This Row],[Loan]] -> 0
A109: 2024-2025 | B109: 45597 | C109: 202412 | D109: DED | E109: 5000 | F109: 0 | G109: 0 | H109: 0 | I109: 0 | J109: 0 | K109: 0 | L109: 5000 | M109: 0 | N109: 0 | O109: 0 | P109: OK | Q109: =IF(Table2[[#This Row],[Check Status with ga 55]]="ok",0,1) -> 0 | R109: =IFERROR(CONCATENATE(TEXT(RIGHT(C109,2)*29,"mmm"),"-",RIGHT(LEFT(C109,4),2)),"") -> Dec-24 | S109: =IFERROR((TEXT(RIGHT(C109,2)*29,"mmm")),"") -> Dec | T109: =IFERROR(RIGHT(LEFT(C109,4),2),"") -> 24 | U109: =Table2[[#This Row],[Total Premium]]+Table2[[#This Row],[Loan]] -> 5000
A110: 2024-2025 | B110: 45627 | C110: 202501 | D110: DED | E110: 5000 | F110: 0 | G110: 0 | H110: 0 | I110: 0 | J110: 0 | K110: 0 | L110: 5000 | M110: 0 | N110: 0 | O110: 0 | P110: OK | Q110: =IF(Table2[[#This Row],[Check Status with ga 55]]="ok",0,1) -> 0 | R110: =IFERROR(CONCATENATE(TEXT(RIGHT(C110,2)*29,"mmm"),"-",RIGHT(LEFT(C110,4),2)),"") -> Jan-25 | S110: =IFERROR((TEXT(RIGHT(C110,2)*29,"mmm")),"") -> Jan | T110: =IFERROR(RIGHT(LEFT(C110,4),2),"") -> 25 | U110: =Table2[[#This Row],[Total Premium]]+Table2[[#This Row],[Loan]] -> 5000
A111: 2024-2025 | B111: 45658 | C111: 202502 | D111: DED | E111: 5000 | F111: 0 | G111: 0 | H111: 0 | I111: 0 | J111: 0 | K111: 0 | L111: 5000 | M111: 0 | N111: 0 | O111: 0 | P111: OK | Q111: =IF(Table2[[#This Row],[Check Status with ga 55]]="ok",0,1) -> 0 | R111: =IFERROR(CONCATENATE(TEXT(RIGHT(C111,2)*29,"mmm"),"-",RIGHT(LEFT(C111,4),2)),"") -> Feb-25 | S111: =IFERROR((TEXT(RIGHT(C111,2)*29,"mmm")),"") -> Feb | T111: =IFERROR(RIGHT(LEFT(C111,4),2),"") -> 25 | U111: =Table2[[#This Row],[Total Premium]]+Table2[[#This Row],[Loan]] -> 5000
A112: 2024-2025 | B112: 45689 | C112: 202503 | D112: DED | E112: 5000 | F112: 0 | G112: 0 | H112: 0 | I112: 0 | J112: 0 | K112: 0 | L112: 5000 | M112: 0 | N112: 0 | O112: 0 | P112: OK | Q112: =IF(Table2[[#This Row],[Check Status with ga 55]]="ok",0,1) -> 0 | R112: =IFERROR(CONCATENATE(TEXT(RIGHT(C112,2)*29,"mmm"),"-",RIGHT(LEFT(C112,4),2)),"") -> Mar-25 | S112: =IFERROR((TEXT(RIGHT(C112,2)*29,"mmm")),"") -> Mar | T112: =IFERROR(RIGHT(LEFT(C112,4),2),"") -> 25 | U112: =Table2[[#This Row],[Total Premium]]+Table2[[#This Row],[Loan]] -> 5000
A113: 2025-2026 | B113: 45717 | C113: 202504 | D113: DED | E113: 5000 | F113: 0 | G113: 0 | H113: 0 | I113: 0 | J113: 0 | K113: 0 | L113: 5000 | M113: 0 | N113: 0 | O113: 0 | P113: OK | Q113: =IF(Table2[[#This Row],[Check Status with ga 55]]="ok",0,1) -> 0 | R113: =IFERROR(CONCATENATE(TEXT(RIGHT(C113,2)*29,"mmm"),"-",RIGHT(LEFT(C113,4),2)),"") -> Apr-25 | S113: =IFERROR((TEXT(RIGHT(C113,2)*29,"mmm")),"") -> Apr | T113: =IFERROR(RIGHT(LEFT(C113,4),2),"") -> 25 | U113: =Table2[[#This Row],[Total Premium]]+Table2[[#This Row],[Loan]] -> 5000
A114: 2025-2026 | B114: 45748 | C114: 202505 | D114: ONLINE | E114: 0 | F114: 0 | G114: 0 | H114: 0 | I114: 0 | J114: 0 | K114: 0 | L114: 0 | M114: 434500 | N114: 0 | O114: 0 | Q114: =IF(Table2[[#This Row],[Check Status with ga 55]]="ok",0,1) -> 1 | R114: =IFERROR(CONCATENATE(TEXT(RIGHT(C114,2)*29,"mmm"),"-",RIGHT(LEFT(C114,4),2)),"") -> May-25 | S114: =IFERROR((TEXT(RIGHT(C114,2)*29,"mmm")),"") -> May | T114: =IFERROR(RIGHT(LEFT(C114,4),2),"") -> 25 | U114: =Table2[[#This Row],[Total Premium]]+Table2[[#This Row],[Loan]] -> 434500
A115: 2025-2026 | B115: 45748 | C115: 202505 | D115: DED | E115: 5000 | F115: 0 | G115: 0 | H115: 0 | I115: 0 | J115: 0 | K115: 0 | L115: 5000 | M115: 0 | N115: 0 | O115: 0 | P115: OK | Q115: =IF(Table2[[#This Row],[Check Status with ga 55]]="ok",0,1) -> 0 | R115: =IFERROR(CONCATENATE(TEXT(RIGHT(C115,2)*29,"mmm"),"-",RIGHT(LEFT(C115,4),2)),"") -> May-25 | S115: =IFERROR((TEXT(RIGHT(C115,2)*29,"mmm")),"") -> May | T115: =IFERROR(RIGHT(LEFT(C115,4),2),"") -> 25 | U115: =Table2[[#This Row],[Total Premium]]+Table2[[#This Row],[Loan]] -> 5000
A116: 2025-2026 | B116: 45778 | C116: 202506 | D116: DED | E116: 5000 | F116: 0 | G116: 0 | H116: 0 | I116: 0 | J116: 0 | K116: 0 | L116: 5000 | M116: 0 | N116: 0 | O116: 0 | P116: OK | Q116: =IF(Table2[[#This Row],[Check Status with ga 55]]="ok",0,1) -> 0 | R116: =IFERROR(CONCATENATE(TEXT(RIGHT(C116,2)*29,"mmm"),"-",RIGHT(LEFT(C116,4),2)),"") -> Jun-25 | S116: =IFERROR((TEXT(RIGHT(C116,2)*29,"mmm")),"") -> Jun | T116: =IFERROR(RIGHT(LEFT(C116,4),2),"") -> 25 | U116: =Table2[[#This Row],[Total Premium]]+Table2[[#This Row],[Loan]] -> 5000
A117: 2025-2026 | B117: 45809 | C117: 202507 | D117: DED | E117: 5000 | F117: 0 | G117: 0 | H117: 7242 | I117: 0 | J117: 0 | K117: 0 | L117: 12242 | M117: 0 | N117: 0 | O117: 0 | P117: OK | Q117: =IF(Table2[[#This Row],[Check Status with ga 55]]="ok",0,1) -> 0 | R117: =IFERROR(CONCATENATE(TEXT(RIGHT(C117,2)*29,"mmm"),"-",RIGHT(LEFT(C117,4),2)),"") -> Jul-25 | S117: =IFERROR((TEXT(RIGHT(C117,2)*29,"mmm")),"") -> Jul | T117: =IFERROR(RIGHT(LEFT(C117,4),2),"") -> 25 | U117: =Table2[[#This Row],[Total Premium]]+Table2[[#This Row],[Loan]] -> 12242
A118: 2025-2026 | B118: 45839 | C118: 202508 | D118: DED | E118: 5000 | F118: 0 | G118: 0 | H118: 7242 | I118: 0 | J118: 0 | K118: 0 | L118: 12242 | M118: 0 | N118: 0 | O118: 0 | P118: OK | Q118: =IF(Table2[[#This Row],[Check Status with ga 55]]="ok",0,1) -> 0 | R118: =IFERROR(CONCATENATE(TEXT(RIGHT(C118,2)*29,"mmm"),"-",RIGHT(LEFT(C118,4),2)),"") -> Aug-25 | S118: =IFERROR((TEXT(RIGHT(C118,2)*29,"mmm")),"") -> Aug | T118: =IFERROR(RIGHT(LEFT(C118,4),2),"") -> 25 | U118: =Table2[[#This Row],[Total Premium]]+Table2[[#This Row],[Loan]] -> 12242
A119: 2025-2026 | B119: 45870 | C119: 202509 | D119: DED | E119: 5000 | F119: 0 | G119: 0 | H119: 7242 | I119: 0 | J119: 0 | K119: 0 | L119: 12242 | M119: 0 | N119: 0 | O119: 0 | P119: OK | Q119: =IF(Table2[[#This Row],[Check Status with ga 55]]="ok",0,1) -> 0 | R119: =IFERROR(CONCATENATE(TEXT(RIGHT(C119,2)*29,"mmm"),"-",RIGHT(LEFT(C119,4),2)),"") -> Sep-25 | S119: =IFERROR((TEXT(RIGHT(C119,2)*29,"mmm")),"") -> Sep | T119: =IFERROR(RIGHT(LEFT(C119,4),2),"") -> 25 | U119: =Table2[[#This Row],[Total Premium]]+Table2[[#This Row],[Loan]] -> 12242
A120: 2025-2026 | B120: 45901 | C120: 202510 | D120: DED | E120: 5000 | F120: 0 | G120: 0 | H120: 7242 | I120: 0 | J120: 0 | K120: 0 | L120: 12242 | M120: 0 | N120: 0 | O120: 0 | P120: OK | Q120: =IF(Table2[[#This Row],[Check Status with ga 55]]="ok",0,1) -> 0 | R120: =IFERROR(CONCATENATE(TEXT(RIGHT(C120,2)*29,"mmm"),"-",RIGHT(LEFT(C120,4),2)),"") -> Oct-25 | S120: =IFERROR((TEXT(RIGHT(C120,2)*29,"mmm")),"") -> Oct | T120: =IFERROR(RIGHT(LEFT(C120,4),2),"") -> 25 | U120: =Table2[[#This Row],[Total Premium]]+Table2[[#This Row],[Loan]] -> 12242
A121: 2025-2026 | B121: 45931 | C121: 202511 | D121: DED | E121: 5000 | F121: 0 | G121: 0 | H121: 7242 | I121: 0 | J121: 0 | K121: 0 | L121: 12242 | M121: 0 | N121: 0 | O121: 0 | P121: OK | Q121: =IF(Table2[[#This Row],[Check Status with ga 55]]="ok",0,1) -> 0 | R121: =IFERROR(CONCATENATE(TEXT(RIGHT(C121,2)*29,"mmm"),"-",RIGHT(LEFT(C121,4),2)),"") -> Nov-25 | S121: =IFERROR((TEXT(RIGHT(C121,2)*29,"mmm")),"") -> Nov | T121: =IFERROR(RIGHT(LEFT(C121,4),2),"") -> 25 | U121: =Table2[[#This Row],[Total Premium]]+Table2[[#This Row],[Loan]] -> 12242
A122: 2025-2026 | B122: 45962 | C122: 202512 | D122: DED | E122: 5000 | F122: 0 | G122: 0 | H122: 7242 | I122: 0 | J122: 0 | K122: 0 | L122: 12242 | M122: 0 | N122: 0 | O122: 0 | P122: OK | Q122: =IF(Table2[[#This Row],[Check Status with ga 55]]="ok",0,1) -> 0 | R122: =IFERROR(CONCATENATE(TEXT(RIGHT(C122,2)*29,"mmm"),"-",RIGHT(LEFT(C122,4),2)),"") -> Dec-25 | S122: =IFERROR((TEXT(RIGHT(C122,2)*29,"mmm")),"") -> Dec | T122: =IFERROR(RIGHT(LEFT(C122,4),2),"") -> 25 | U122: =Table2[[#This Row],[Total Premium]]+Table2[[#This Row],[Loan]] -> 12242
A123: 2025-2026 | B123: 45992 | C123: 202601 | D123: DED | E123: 5000 | F123: 0 | G123: 0 | H123: 7242 | I123: 0 | J123: 0 | K123: 0 | L123: 12242 | M123: 0 | N123: 0 | O123: 0 | P123: OK | Q123: =IF(Table2[[#This Row],[Check Status with ga 55]]="ok",0,1) -> 0 | R123: =IFERROR(CONCATENATE(TEXT(RIGHT(C123,2)*29,"mmm"),"-",RIGHT(LEFT(C123,4),2)),"") -> Jan-26 | S123: =IFERROR((TEXT(RIGHT(C123,2)*29,"mmm")),"") -> Jan | T123: =IFERROR(RIGHT(LEFT(C123,4),2),"") -> 26 | U123: =Table2[[#This Row],[Total Premium]]+Table2[[#This Row],[Loan]] -> 12242
A124: 2025-2026 | B124: 46023 | C124: 202602 | D124: DED | E124: 5000 | F124: 0 | G124: 0 | H124: 7242 | I124: 0 | J124: 0 | K124: 0 | L124: 12242 | M124: 0 | N124: 0 | O124: 0 | P124: OK | Q124: =IF(Table2[[#This Row],[Check Status with ga 55]]="ok",0,1) -> 0 | R124: =IFERROR(CONCATENATE(TEXT(RIGHT(C124,2)*29,"mmm"),"-",RIGHT(LEFT(C124,4),2)),"") -> Feb-26 | S124: =IFERROR((TEXT(RIGHT(C124,2)*29,"mmm")),"") -> Feb | T124: =IFERROR(RIGHT(LEFT(C124,4),2),"") -> 26 | U124: =Table2[[#This Row],[Total Premium]]+Table2[[#This Row],[Loan]] -> 12242
A125: 2025-2026 | B125: 46054 | C125: 202603 | D125: DED | E125: 5000 | F125: 0 | G125: 0 | H125: 7242 | I125: 0 | J125: 0 | K125: 0 | L125: 12242 | M125: 0 | N125: 0 | O125: 0 | P125: OK | Q125: =IF(Table2[[#This Row],[Check Status with ga 55]]="ok",0,1) -> 0 | R125: =IFERROR(CONCATENATE(TEXT(RIGHT(C125,2)*29,"mmm"),"-",RIGHT(LEFT(C125,4),2)),"") -> Mar-26 | S125: =IFERROR((TEXT(RIGHT(C125,2)*29,"mmm")),"") -> Mar | T125: =IFERROR(RIGHT(LEFT(C125,4),2),"") -> 26 | U125: =Table2[[#This Row],[Total Premium]]+Table2[[#This Row],[Loan]] -> 12242

Sheet SI (SSO ID New with Detail)
A1: FY | B1: Month | C1: Sr.No | D1: Salary Date | E1: Encashment Date | F1: TV No | G1: Total Premium | H1: Transaction Type | I1: UNIT | J1: DDO | K1: Office | L1: TV month or Encashment Month | M1: TV year or Encashment Year | N1: remark | Q1: TV No | R1: TV Date | S1: FY | T1: SI | V1: tvno | W1: date | X1: si | Y1: >0 or <0 | AB1: =SUM(V:V) -> 0 | AC1: =SUM(W:W) -> 0 | AD1: =SUM(X:X) -> 0 | AG1: Last Update on this sheet | AH1: 46110
A2: 2016-2017 | B2: 42430 | C2: 1 | D2: 42430 | E2: 42485 | F2: 2179 | G2: 1100 | H2: ONLINE | I2: HANUMANGARH | J2: 22956-CHC SANGARIA | K2: Community Health Center, Sangaria (Hanumangarh) | L2: =TEXT(E2,"mmm") -> Apr | M2: =TEXT(E2,"yy") -> 16 | N2: ok | Q2: 2179 | R2: 42485 | S2: 2016-2017 | T2: 1100 | V2: =F2-Q2 -> 0 | W2: =E2-R2 -> 0 | X2: =G2-T2 -> 0 | Y2: =V2+W2+X2 -> 0
A3: 2016-2017 | B3: 42461 | C3: 1 | D3: 42461 | E3: 42492 | F3: 3158 | G3: 1100 | H3: ONLINE | I3: HANUMANGARH | J3: 22956-CHC SANGARIA | K3: Community Health Center, Sangaria (Hanumangarh) | L3: =TEXT(E3,"mmm") -> May | M3: =TEXT(E3,"yy") -> 16 | N3: ok | Q3: 3158 | R3: 42492 | S3: 2016-2017 | T3: 1100 | V3: =F3-Q3 -> 0 | W3: =E3-R3 -> 0 | X3: =G3-T3 -> 0 | Y3: =V3+W3+X3 -> 0
A4: 2016-2017 | B4: 42491 | C4: 1 | D4: 42491 | E4: 42549 | F4: 13185 | G4: 1100 | H4: ONLINE | I4: HANUMANGARH | J4: Analyst Cum Programmer DOIT&amp;C HANUMANGARH | K4: Office of Analyst cum programmer(Dy Director) DoIT&C Hanumangarh | L4: =TEXT(E4,"mmm") -> Jun | M4: =TEXT(E4,"yy") -> 16 | N4: ok | Q4: 13185 | R4: 42549 | S4: 2016-2017 | T4: 1100 | V4: =F4-Q4 -> 0 | W4: =E4-R4 -> 0 | X4: =G4-T4 -> 0 | Y4: =V4+W4+X4 -> 0
A5: 2016-2017 | B5: 42522 | C5: 1 | D5: 42522 | E5: 42553 | F5: 14705 | G5: 1100 | H5: ONLINE | I5: HANUMANGARH | J5: Analyst Cum Programmer DOIT&amp;C HANUMANGARH | K5: Office of Analyst cum programmer(Dy Director) DoIT&C Hanumangarh | L5: =TEXT(E5,"mmm") -> Jul | M5: =TEXT(E5,"yy") -> 16 | N5: ok | Q5: 14705 | R5: 42553 | S5: 2016-2017 | T5: 1100 | V5: =F5-Q5 -> 0 | W5: =E5-R5 -> 0 | X5: =G5-T5 -> 0 | Y5: =V5+W5+X5 -> 0 | AB5: total of SI in column T | AC5: =SUM(T:T) -> 976678 | AE5: SI Deduction in Pivot sheet SI | AF5: =GETPIVOTDATA(" SI",Pivots!$A$3)+GETPIVOTDATA("SI Loan EMI",Pivots!$A$3) -> 542178
A6: 2016-2017 | B6: 42552 | C6: 1 | D6: 42552 | E6: 42586 | F6: 19959 | G6: 1100 | H6: ONLINE | I6: HANUMANGARH | J6: Analyst Cum Programmer DOIT&amp;C HANUMANGARH | K6: Office of Analyst cum programmer(Dy Director) DoIT&C Hanumangarh | L6: =TEXT(E6,"mmm") -> Aug | M6: =TEXT(E6,"yy") -> 16 | N6: ok | Q6: 19959 | R6: 42586 | S6: 2016-2017 | T6: 1100 | V6: =F6-Q6 -> 0 | W6: =E6-R6 -> 0 | X6: =G6-T6 -> 0 | Y6: =V6+W6+X6 -> 0 | AB6: total of SI in column G | AC6: =SUM(G:G) -> 976678 | AE6: difference (pivot sheet-cell ab) | AF6: =AF5-AC5+GETPIVOTDATA("SI Loan ",Pivots!$A$3) -> 0
A7: 2016-2017 | B7: 42583 | C7: 1 | D7: 42583 | E7: 42614 | F7: 23893 | G7: 1100 | H7: ONLINE | I7: HANUMANGARH | J7: Analyst Cum Programmer DOIT&amp;C HANUMANGARH | K7: Office of Analyst cum programmer(Dy Director) DoIT&C Hanumangarh | L7: =TEXT(E7,"mmm") -> Sep | M7: =TEXT(E7,"yy") -> 16 | N7: ok | Q7: 23893 | R7: 42614 | S7: 2016-2017 | T7: 1100 | V7: =F7-Q7 -> 0 | W7: =E7-R7 -> 0 | X7: =G7-T7 -> 0 | Y7: =V7+W7+X7 -> 0 | AB7: Difference (T-G) | AC7: =AC5-AC6 -> 0
A8: 2016-2017 | B8: 42614 | C8: 1 | D8: 42644 | E8: 42671 | F8: 35248 | G8: 1100 | H8: ONLINE | I8: HANUMANGARH | J8: Analyst Cum Programmer DOIT&amp;C HANUMANGARH | K8: Office of Analyst cum programmer(Dy Director) DoIT&C Hanumangarh | L8: =TEXT(E8,"mmm") -> Oct | M8: =TEXT(E8,"yy") -> 16 | N8: ok | Q8: 35248 | R8: 42671 | S8: 2016-2017 | T8: 1100 | V8: =F8-Q8 -> 0 | W8: =E8-R8 -> 0 | X8: =G8-T8 -> 0 | Y8: =V8+W8+X8 -> 0 | AB8: no of enteries effected | AC8: =SUM(Y:Y) -> 0
A9: 2016-2017 | B9: 42614 | C9: 3 | D9: 42614 | E9: 42644 | F9: 28883 | G9: 1100 | H9: ONLINE | I9: HANUMANGARH | J9: Analyst Cum Programmer DOIT&amp;C HANUMANGARH | K9: Office of Analyst cum programmer(Dy Director) DoIT&C Hanumangarh | L9: =TEXT(E9,"mmm") -> Oct | M9: =TEXT(E9,"yy") -> 16 | N9: ok | Q9: 28883 | R9: 42644 | S9: 2016-2017 | T9: 1100 | V9: =F9-Q9 -> 0 | W9: =E9-R9 -> 0 | X9: =G9-T9 -> 0 | Y9: =V9+W9+X9 -> 0
A10: 2016-2017 | B10: 42675 | C10: 1 | D10: 42675 | E10: 42705 | F10: 40457 | G10: 1100 | H10: ONLINE | I10: HANUMANGARH | J10: Analyst Cum Programmer DOIT&amp;C HANUMANGARH | K10: Office of Analyst cum programmer(Dy Director) DoIT&C Hanumangarh | L10: =TEXT(E10,"mmm") -> Dec | M10: =TEXT(E10,"yy") -> 16 | N10: ok | Q10: 40457 | R10: 42705 | S10: 2016-2017 | T10: 1100 | V10: =F10-Q10 -> 0 | W10: =E10-R10 -> 0 | X10: =G10-T10 -> 0 | Y10: =V10+W10+X10 -> 0
A11: 2016-2017 | B11: 42705 | C11: 1 | D11: 42705 | E11: 42739 | F11: 45844 | G11: 1100 | H11: ONLINE | I11: HANUMANGARH | J11: Analyst Cum Programmer DOIT&amp;C HANUMANGARH | K11: Office of Analyst cum programmer(Dy Director) DoIT&C Hanumangarh | L11: =TEXT(E11,"mmm") -> Jan | M11: =TEXT(E11,"yy") -> 17 | N11: ok | Q11: 45844 | R11: 42739 | S11: 2016-2017 | T11: 1100 | V11: =F11-Q11 -> 0 | W11: =E11-R11 -> 0 | X11: =G11-T11 -> 0 | Y11: =V11+W11+X11 -> 0
A12: 2016-2017 | B12: 42736 | C12: 1 | D12: 42736 | E12: 42767 | F12: 50049 | G12: 1100 | H12: ONLINE | I12: HANUMANGARH | J12: Analyst Cum Programmer DOIT&amp;C HANUMANGARH | K12: Office of Analyst cum programmer(Dy Director) DoIT&C Hanumangarh | L12: =TEXT(E12,"mmm") -> Feb | M12: =TEXT(E12,"yy") -> 17 | N12: ok | Q12: 50049 | R12: 42767 | S12: 2016-2017 | T12: 1100 | V12: =F12-Q12 -> 0 | W12: =E12-R12 -> 0 | X12: =G12-T12 -> 0 | Y12: =V12+W12+X12 -> 0
A13: 2016-2017 | B13: 42767 | C13: 1 | D13: 42767 | E13: 42797 | F13: 55694 | G13: 1100 | H13: ONLINE | I13: HANUMANGARH | J13: Analyst Cum Programmer DOIT&amp;C HANUMANGARH | K13: Office of Analyst cum programmer(Dy Director) DoIT&C Hanumangarh | L13: =TEXT(E13,"mmm") -> Mar | M13: =TEXT(E13,"yy") -> 17 | N13: ok | Q13: 55694 | R13: 42797 | S13: 2016-2017 | T13: 1100 | V13: =F13-Q13 -> 0 | W13: =E13-R13 -> 0 | X13: =G13-T13 -> 0 | Y13: =V13+W13+X13 -> 0
A14: 2017-2018 | B14: 42795 | C14: 1 | D14: 42795 | E14: 42832 | F14: 727 | G14: 2650 | H14: ONLINE | I14: HANUMANGARH | J14: Analyst Cum Programmer DOIT&amp;C HANUMANGARH | K14: Office of Analyst cum programmer(Dy Director) DoIT&C Hanumangarh | L14: =TEXT(E14,"mmm") -> Apr | M14: =TEXT(E14,"yy") -> 17 | N14: ok | Q14: 727 | R14: 42832 | S14: 2017-2018 | T14: 2650 | V14: =F14-Q14 -> 0 | W14: =E14-R14 -> 0 | X14: =G14-T14 -> 0 | Y14: =V14+W14+X14 -> 0
A15: 2017-2018 | B15: 42826 | C15: 1 | D15: 42826 | E15: 42858 | F15: 5192 | G15: 2650 | H15: ONLINE | I15: HANUMANGARH | J15: Analyst Cum Programmer DOIT&amp;C HANUMANGARH | K15: Office of Analyst cum programmer(Dy Director) DoIT&C Hanumangarh | L15: =TEXT(E15,"mmm") -> May | M15: =TEXT(E15,"yy") -> 17 | N15: ok | Q15: 5192 | R15: 42858 | S15: 2017-2018 | T15: 2650 | V15: =F15-Q15 -> 0 | W15: =E15-R15 -> 0 | X15: =G15-T15 -> 0 | Y15: =V15+W15+X15 -> 0
A16: 2017-2018 | B16: 42856 | C16: 1 | D16: 42856 | E16: 42887 | F16: 10350 | G16: 2650 | H16: ONLINE | I16: HANUMANGARH | J16: Analyst Cum Programmer DOIT&amp;C HANUMANGARH | K16: Office of Analyst cum programmer(Dy Director) DoIT&C Hanumangarh | L16: =TEXT(E16,"mmm") -> Jun | M16: =TEXT(E16,"yy") -> 17 | N16: ok | Q16: 10350 | R16: 42887 | S16: 2017-2018 | T16: 2650 | V16: =F16-Q16 -> 0 | W16: =E16-R16 -> 0 | X16: =G16-T16 -> 0 | Y16: =V16+W16+X16 -> 0
A17: 2017-2018 | B17: 42887 | C17: 1 | D17: 42887 | E17: 42917 | F17: 15103 | G17: 2650 | H17: ONLINE | I17: HANUMANGARH | J17: Analyst Cum Programmer DOIT&amp;C HANUMANGARH | K17: Office of Analyst cum programmer(Dy Director) DoIT&C Hanumangarh | L17: =TEXT(E17,"mmm") -> Jul | M17: =TEXT(E17,"yy") -> 17 | N17: ok | Q17: 15103 | R17: 42917 | S17: 2017-2018 | T17: 2650 | V17: =F17-Q17 -> 0 | W17: =E17-R17 -> 0 | X17: =G17-T17 -> 0 | Y17: =V17+W17+X17 -> 0
A18: 2017-2018 | B18: 42917 | C18: 1 | D18: 42917 | E18: 42951 | F18: 20970 | G18: 2650 | H18: ONLINE | I18: HANUMANGARH | J18: Analyst Cum Programmer DOIT&amp;C HANUMANGARH | K18: Office of Analyst cum programmer(Dy Director) DoIT&C Hanumangarh | L18: =TEXT(E18,"mmm") -> Aug | M18: =TEXT(E18,"yy") -> 17 | N18: ok | Q18: 20970 | R18: 42951 | S18: 2017-2018 | T18: 2650 | V18: =F18-Q18 -> 0 | W18: =E18-R18 -> 0 | X18: =G18-T18 -> 0 | Y18: =V18+W18+X18 -> 0
A19: 2017-2018 | B19: 42948 | C19: 1 | D19: 42948 | E19: 42984 | F19: 24832 | G19: 2650 | H19: ONLINE | I19: HANUMANGARH | J19: Analyst Cum Programmer DOIT&amp;C HANUMANGARH | K19: Office of Analyst cum programmer(Dy Director) DoIT&C Hanumangarh | L19: =TEXT(E19,"mmm") -> Sep | M19: =TEXT(E19,"yy") -> 17 | N19: ok | Q19: 24832 | R19: 42984 | S19: 2017-2018 | T19: 2650 | V19: =F19-Q19 -> 0 | W19: =E19-R19 -> 0 | X19: =G19-T19 -> 0 | Y19: =V19+W19+X19 -> 0
A20: 2017-2018 | B20: 42979 | C20: 1 | D20: 42979 | E20: 43014 | F20: 29089 | G20: 2650 | H20: ONLINE | I20: HANUMANGARH | K20: Office of Analyst cum programmer(Dy Director) DoIT&C Hanumangarh | L20: =TEXT(E20,"mmm") -> Oct | M20: =TEXT(E20,"yy") -> 17 | N20: ok | Q20: 29089 | R20: 43014 | S20: 2017-2018 | T20: 2650 | V20: =F20-Q20 -> 0 | W20: =E20-R20 -> 0 | X20: =G20-T20 -> 0 | Y20: =V20+W20+X20 -> 0
A21: 2017-2018 | B21: 43009 | C21: 1 | D21: 43009 | E21: 43045 | F21: 37958 | G21: 2650 | H21: ONLINE | I21: HANUMANGARH | J21: Analyst Cum Programmer DOIT&amp;C HANUMANGARH | K21: Office of Analyst cum programmer(Dy Director) DoIT&C Hanumangarh | L21: =TEXT(E21,"mmm") -> Nov | M21: =TEXT(E21,"yy") -> 17 | N21: ok | Q21: 37958 | R21: 43045 | S21: 2017-2018 | T21: 2650 | V21: =F21-Q21 -> 0 | W21: =E21-R21 -> 0 | X21: =G21-T21 -> 0 | Y21: =V21+W21+X21 -> 0
A22: 2017-2018 | B22: 43040 | C22: 1 | D22: 43040 | E22: 43070 | F22: 41798 | G22: 2650 | H22: ONLINE | I22: HANUMANGARH | J22: Analyst Cum Programmer DOIT&amp;C HANUMANGARH | K22: Office of Analyst cum programmer(Dy Director) DoIT&C Hanumangarh | L22: =TEXT(E22,"mmm") -> Dec | M22: =TEXT(E22,"yy") -> 17 | N22: ok | Q22: 41798 | R22: 43070 | S22: 2017-2018 | T22: 2650 | V22: =F22-Q22 -> 0 | W22: =E22-R22 -> 0 | X22: =G22-T22 -> 0 | Y22: =V22+W22+X22 -> 0
A23: 2017-2018 | B23: 43070 | C23: 1 | D23: 43070 | E23: 43103 | F23: 47622 | G23: 2650 | H23: ONLINE | I23: HANUMANGARH | J23: Analyst Cum Programmer DOIT&amp;C HANUMANGARH | K23: Office of Analyst cum programmer(Dy Director) DoIT&C Hanumangarh | L23: =TEXT(E23,"mmm") -> Jan | M23: =TEXT(E23,"yy") -> 18 | N23: ok | Q23: 47622 | R23: 43103 | S23: 2017-2018 | T23: 2650 | V23: =F23-Q23 -> 0 | W23: =E23-R23 -> 0 | X23: =G23-T23 -> 0 | Y23: =V23+W23+X23 -> 0
A24: 2017-2018 | B24: 43101 | C24: 1 | D24: 43101 | E24: 43134 | F24: 52864 | G24: 2650 | H24: ONLINE | I24: HANUMANGARH | J24: Analyst Cum Programmer DOIT&amp;C HANUMANGARH | K24: Office of Analyst cum programmer(Dy Director) DoIT&C Hanumangarh | L24: =TEXT(E24,"mmm") -> Feb | M24: =TEXT(E24,"yy") -> 18 | N24: ok | Q24: 52864 | R24: 43134 | S24: 2017-2018 | T24: 2650 | V24: =F24-Q24 -> 0 | W24: =E24-R24 -> 0 | X24: =G24-T24 -> 0 | Y24: =V24+W24+X24 -> 0
A25: 2017-2018 | B25: 43132 | C25: 1 | D25: 43132 | E25: 43166 | F25: 59059 | G25: 2650 | H25: ONLINE | I25: HANUMANGARH | J25: Analyst Cum Programmer DOIT&amp;C HANUMANGARH | K25: Office of Analyst cum programmer(Dy Director) DoIT&C Hanumangarh | L25: =TEXT(E25,"mmm") -> Mar | M25: =TEXT(E25,"yy") -> 18 | N25: ok | Q25: 59059 | R25: 43166 | S25: 2017-2018 | T25: 2650 | V25: =F25-Q25 -> 0 | W25: =E25-R25 -> 0 | X25: =G25-T25 -> 0 | Y25: =V25+W25+X25 -> 0
A26: 2018-2019 | B26: 43160 | C26: 1 | D26: 43160 | E26: 43206 | F26: 2261 | G26: 3000 | H26: ONLINE | I26: HANUMANGARH | J26: Analyst Cum Programmer DOIT&amp;C HANUMANGARH | K26: Office of Analyst cum programmer(Dy Director) DoIT&C Hanumangarh | L26: =TEXT(E26,"mmm") -> Apr | M26: =TEXT(E26,"yy") -> 18 | N26: ok | Q26: 2261 | R26: 43206 | S26: 2018-2019 | T26: 3000 | V26: =F26-Q26 -> 0 | W26: =E26-R26 -> 0 | X26: =G26-T26 -> 0 | Y26: =V26+W26+X26 -> 0
A27: 2018-2019 | B27: 43191 | C27: 1 | D27: 43191 | E27: 43249 | F27: 12293 | G27: 3000 | H27: ONLINE | I27: HANUMANGARH | J27: Analyst Cum Programmer DOIT&amp;C HANUMANGARH | K27: Office of Analyst cum programmer(Dy Director) DoIT&C Hanumangarh | L27: =TEXT(E27,"mmm") -> May | M27: =TEXT(E27,"yy") -> 18 | N27: ok | Q27: 12293 | R27: 43249 | S27: 2018-2019 | T27: 3000 | V27: =F27-Q27 -> 0 | W27: =E27-R27 -> 0 | X27: =G27-T27 -> 0 | Y27: =V27+W27+X27 -> 0
A28: 2018-2019 | B28: 43221 | C28: 1 | D28: 43221 | E28: 43252 | F28: 14665 | G28: 3000 | H28: ONLINE | I28: HANUMANGARH | J28: Analyst Cum Programmer DOIT&amp;C HANUMANGARH | K28: Office of Analyst cum programmer(Dy Director) DoIT&C Hanumangarh | L28: =TEXT(E28,"mmm") -> Jun | M28: =TEXT(E28,"yy") -> 18 | N28: ok | Q28: 14665 | R28: 43252 | S28: 2018-2019 | T28: 3000 | V28: =F28-Q28 -> 0 | W28: =E28-R28 -> 0 | X28: =G28-T28 -> 0 | Y28: =V28+W28+X28 -> 0
A29: 2018-2019 | B29: 43252 | C29: 1 | D29: 43252 | E29: 43283 | F29: 20799 | G29: 3000 | H29: ONLINE | I29: HANUMANGARH | J29: Analyst Cum Programmer DOIT&amp;C HANUMANGARH | K29: Office of Analyst cum programmer(Dy Director) DoIT&C Hanumangarh | L29: =TEXT(E29,"mmm") -> Jul | M29: =TEXT(E29,"yy") -> 18 | N29: ok | Q29: 20799 | R29: 43283 | S29: 2018-2019 | T29: 3000 | V29: =F29-Q29 -> 0 | W29: =E29-R29 -> 0 | X29: =G29-T29 -> 0 | Y29: =V29+W29+X29 -> 0
A30: 2018-2019 | B30: 43282 | C30: 1 | D30: 43282 | E30: 43313 | F30: 28948 | G30: 3000 | H30: ONLINE | I30: HANUMANGARH | J30: Analyst Cum Programmer DOIT&amp;C HANUMANGARH | K30: Office of Analyst cum programmer(Dy Director) DoIT&C Hanumangarh | L30: =TEXT(E30,"mmm") -> Aug | M30: =TEXT(E30,"yy") -> 18 | N30: ok | Q30: 28948 | R30: 43313 | S30: 2018-2019 | T30: 3000 | V30: =F30-Q30 -> 0 | W30: =E30-R30 -> 0 | X30: =G30-T30 -> 0 | Y30: =V30+W30+X30 -> 0
A31: 2018-2019 | B31: 43313 | C31: 1 | D31: 43313 | E31: 43344 | F31: 38148 | G31: 3000 | H31: ONLINE | I31: HANUMANGARH | J31: Analyst Cum Programmer DOIT&amp;C HANUMANGARH | K31: Office of Analyst cum programmer(Dy Director) DoIT&C Hanumangarh | L31: =TEXT(E31,"mmm") -> Sep | M31: =TEXT(E31,"yy") -> 18 | N31: ok | Q31: 38148 | R31: 43344 | S31: 2018-2019 | T31: 3000 | V31: =F31-Q31 -> 0 | W31: =E31-R31 -> 0 | X31: =G31-T31 -> 0 | Y31: =V31+W31+X31 -> 0
A32: 2018-2019 | B32: 43344 | C32: 1 | D32: 43344 | E32: 43382 | F32: 45759 | G32: 3000 | H32: ONLINE | I32: HANUMANGARH | J32: Analyst Cum Programmer DOIT&amp;C HANUMANGARH | K32: Office of Analyst cum programmer(Dy Director) DoIT&C Hanumangarh | L32: =TEXT(E32,"mmm") -> Oct | M32: =TEXT(E32,"yy") -> 18 | N32: ok | Q32: 45759 | R32: 43382 | S32: 2018-2019 | T32: 3000 | V32: =F32-Q32 -> 0 | W32: =E32-R32 -> 0 | X32: =G32-T32 -> 0 | Y32: =V32+W32+X32 -> 0
... A49: 2019-2020 | B49: 43862 | C49: 1 | D49: 43831 | E49: 43894 | F49: 65112 | G49: 3000 | H49: ONLINE | I49: HANUMANGARH | J49: Analyst Cum Programmer DOIT&amp;C HANUMANGARH | K49: Office of Analyst cum programmer(Dy Director) DoIT&C Hanumangarh | L49: =TEXT(E49,"mmm") -> Mar | M49: =TEXT(E49,"yy") -> 20 | N49: ok | Q49: 65112 | R49: 43894 | S49: 2019-2020 | T49: 3000 | V49: =F49-Q49 -> 0 | W49: =E49-R49 -> 0 | X49: =G49-T49 -> 0 | Y49: =V49+W49+X49 -> 0
A50: 2020-2021 | B50: 43891 | L50: =TEXT(E50,"mmm") -> Jan | M50: =TEXT(E50,"yy") -> 00 | N50: march ki deduction may-2020 me hui hai | V50: =F50-Q50 -> 0 | W50: =E50-R50 -> 0 | X50: =G50-T50 -> 0 | Y50: =V50+W50+X50 -> 0
A51: 2020-2021 | B51: 43922 | C51: 1 | D51: 43922 | E51: 43956 | F51: 4971 | G51: 5000 | H51: ONLINE | I51: HANUMANGARH | J51: Analyst Cum Programmer DOIT&amp;C HANUMANGARH | K51: Office of Analyst cum programmer(Dy Director) DoIT&C Hanumangarh | L51: =TEXT(E51,"mmm") -> May | M51: =TEXT(E51,"yy") -> 20 | N51: ok | Q51: 4971 | R51: 43956 | S51: 2020-2021 | T51: 5000 | V51: =F51-Q51 -> 0 | W51: =E51-R51 -> 0 | X51: =G51-T51 -> 0 | Y51: =V51+W51+X51 -> 0
A52: 2020-2021 | B52: 43952 | C52: 1 | D52: 43952 | E52: 43983 | F52: 10260 | G52: 10000 | H52: ONLINE | I52: HANUMANGARH | J52: Analyst Cum Programmer DOIT&amp;C HANUMANGARH | K52: Office of Analyst cum programmer(Dy Director) DoIT&C Hanumangarh | L52: =TEXT(E52,"mmm") -> Jun | M52: =TEXT(E52,"yy") -> 20 | N52: ok | Q52: 10260 | R52: 43983 | S52: 2020-2021 | T52: 10000 | V52: =F52-Q52 -> 0 | W52: =E52-R52 -> 0 | X52: =G52-T52 -> 0 | Y52: =V52+W52+X52 -> 0
A53: 2020-2021 | B53: 43983 | C53: 1 | D53: 43983 | E53: 44015 | F53: 17622 | G53: 5000 | H53: ONLINE | I53: HANUMANGARH | J53: Analyst Cum Programmer DOIT&amp;C HANUMANGARH | K53: Office of Analyst cum programmer(Dy Director) DoIT&C Hanumangarh | L53: =TEXT(E53,"mmm") -> Jul | M53: =TEXT(E53,"yy") -> 20 | N53: ok | Q53: 17622 | R53: 44015 | S53: 2020-2021 | T53: 5000 | V53: =F53-Q53 -> 0 | W53: =E53-R53 -> 0 | X53: =G53-T53 -> 0 | Y53: =V53+W53+X53 -> 0
A54: 2020-2021 | B54: 44013 | C54: 1 | D54: 44013 | E54: 44048 | F54: 23350 | G54: 5000 | H54: ONLINE | I54: HANUMANGARH | J54: Analyst Cum Programmer DOIT&amp;C HANUMANGARH | K54: Office of Analyst cum programmer(Dy Director) DoIT&C Hanumangarh | L54: =TEXT(E54,"mmm") -> Aug | M54: =TEXT(E54,"yy") -> 20 | N54: ok | Q54: 23350 | R54: 44048 | S54: 2020-2021 | T54: 5000 | V54: =F54-Q54 -> 0 | W54: =E54-R54 -> 0 | X54: =G54-T54 -> 0 | Y54: =V54+W54+X54 -> 0
A55: 2020-2021 | B55: 44044 | C55: 1 | D55: 44044 | E55: 44077 | F55: 28462 | G55: 5000 | H55: ONLINE | I55: HANUMANGARH | J55: Analyst Cum Programmer DOIT&amp;C HANUMANGARH | K55: Office of Analyst cum programmer(Dy Director) DoIT&C Hanumangarh | L55: =TEXT(E55,"mmm") -> Sep | M55: =TEXT(E55,"yy") -> 20 | N55: ok | Q55: 28462 | R55: 44077 | S55: 2020-2021 | T55: 5000 | V55: =F55-Q55 -> 0 | W55: =E55-R55 -> 0 | X55: =G55-T55 -> 0 | Y55: =V55+W55+X55 -> 0
A56: 2020-2021 | B56: 44075 | C56: 1 | D56: 44075 | E56: 44109 | F56: 33490 | G56: 5000 | H56: ONLINE | I56: HANUMANGARH | J56: Analyst Cum Programmer DOIT&amp;C HANUMANGARH | K56: Office of Analyst cum programmer(Dy Director) DoIT&C Hanumangarh | L56: =TEXT(E56,"mmm") -> Oct | M56: =TEXT(E56,"yy") -> 20 | N56: ok | Q56: 33490 | R56: 44109 | S56: 2020-2021 | T56: 5000 | V56: =F56-Q56 -> 0 | W56: =E56-R56 -> 0 | X56: =G56-T56 -> 0 | Y56: =V56+W56+X56 -> 0
A57: 2020-2021 | B57: 44105 | C57: 1 | D57: 44105 | E57: 44137 | F57: 38388 | G57: 5000 | H57: ONLINE | I57: HANUMANGARH | J57: Analyst Cum Programmer DOIT&amp;C HANUMANGARH | K57: Office of Analyst cum programmer(Dy Director) DoIT&C Hanumangarh | L57: =TEXT(E57,"mmm") -> Nov | M57: =TEXT(E57,"yy") -> 20 | N57: ok | Q57: 38388 | R57: 44137 | S57: 2020-2021 | T57: 5000 | V57: =F57-Q57 -> 0 | W57: =E57-R57 -> 0 | X57: =G57-T57 -> 0 | Y57: =V57+W57+X57 -> 0
A58: 2020-2021 | B58: 44136 | C58: 1 | D58: 44136 | E58: 44169 | F58: 45971 | G58: 5000 | H58: ONLINE | I58: HANUMANGARH | J58: Analyst Cum Programmer DOIT&amp;C HANUMANGARH | K58: Office of Analyst cum programmer(Dy Director) DoIT&C Hanumangarh | L58: =TEXT(E58,"mmm") -> Dec | M58: =TEXT(E58,"yy") -> 20 | N58: ok | Q58: 45971 | R58: 44169 | S58: 2020-2021 | T58: 5000 | V58: =F58-Q58 -> 0 | W58: =E58-R58 -> 0 | X58: =G58-T58 -> 0 | Y58: =V58+W58+X58 -> 0
A59: 2020-2021 | B59: 44166 | C59: 1 | D59: 44166 | E59: 44197 | F59: 52244 | G59: 5000 | H59: ONLINE | I59: HANUMANGARH | J59: Analyst Cum Programmer DOIT&amp;C HANUMANGARH | K59: Office of Analyst cum programmer(Dy Director) DoIT&C Hanumangarh | L59: =TEXT(E59,"mmm") -> Jan | M59: =TEXT(E59,"yy") -> 21 | N59: ok | Q59: 52244 | R59: 44197 | S59: 2020-2021 | T59: 5000 | V59: =F59-Q59 -> 0 | W59: =E59-R59 -> 0 | X59: =G59-T59 -> 0 | Y59: =V59+W59+X59 -> 0
A60: 2020-2021 | B60: 44197 | C60: 1 | D60: 44197 | E60: 44231 | F60: 58485 | G60: 5000 | H60: ONLINE | I60: HANUMANGARH | J60: Analyst Cum Programmer DOIT&amp;C HANUMANGARH | K60: Office of Analyst cum programmer(Dy Director) DoIT&C Hanumangarh | L60: =TEXT(E60,"mmm") -> Feb | M60: =TEXT(E60,"yy") -> 21 | N60: ok | Q60: 58485 | R60: 44231 | S60: 2020-2021 | T60: 5000 | V60: =F60-Q60 -> 0 | W60: =E60-R60 -> 0 | X60: =G60-T60 -> 0 | Y60: =V60+W60+X60 -> 0
A61: 2020-2021 | B61: 44228 | C61: 1 | D61: 44228 | E61: 44258 | F61: 63803 | G61: 5000 | H61: ONLINE | I61: HANUMANGARH | J61: Analyst Cum Programmer DOIT&amp;C HANUMANGARH | K61: Office of Analyst cum programmer(Dy Director) DoIT&C Hanumangarh | L61: =TEXT(E61,"mmm") -> Mar | M61: =TEXT(E61,"yy") -> 21 | N61: ok | Q61: 63803 | R61: 44258 | S61: 2020-2021 | T61: 5000 | V61: =F61-Q61 -> 0 | W61: =E61-R61 -> 0 | X61: =G61-T61 -> 0 | Y61: =V61+W61+X61 -> 0
A62: 2021-2022 | B62: 44256 | C62: 1 | D62: 44256 | E62: 44294 | F62: 1971 | G62: 5000 | H62: ONLINE | I62: HANUMANGARH | J62: Analyst Cum Programmer DOIT&amp;C HANUMANGARH | K62: Office of Analyst cum programmer(Dy Director) DoIT&C Hanumangarh | L62: =TEXT(E62,"mmm") -> Apr | M62: =TEXT(E62,"yy") -> 21 | N62: ok | Q62: 1971 | R62: 44294 | S62: 2021-2022 | T62: 5000 | V62: =F62-Q62 -> 0 | W62: =E62-R62 -> 0 | X62: =G62-T62 -> 0 | Y62: =V62+W62+X62 -> 0
... A80: 2022-2023 | B80: 44805 | C80: 1 | D80: 44805 | E80: 44835 | F80: 38533 | G80: 5000 | H80: ONLINE | I80: HANUMANGARH | J80: Analyst Cum Programmer DOIT&amp;C HANUMANGARH | K80: Office of Analyst cum programmer(Dy Director) DoIT&C Hanumangarh | L80: =TEXT(E80,"mmm") -> Oct | M80: =TEXT(E80,"yy") -> 22 | N80: ok | Q80: 38533 | R80: 44835 | S80: 2022-2023 | T80: 5000 | V80: =F80-Q80 -> 0 | W80: =E80-R80 -> 0 | X80: =G80-T80 -> 0 | Y80: =V80+W80+X80 -> 0
A81: 2022-2023 | B81: 0ct-22 | C81: 1 | D81: 44835 | E81: 44866 | F81: 47806 | G81: 5000 | H81: ONLINE | I81: HANUMANGARH | J81: Analyst Cum Programmer DOIT&amp;C HANUMANGARH | K81: Office of Analyst cum programmer(Dy Director) DoIT&C Hanumangarh | L81: =TEXT(E81,"mmm") -> Nov | M81: =TEXT(E81,"yy") -> 22 | N81: ok | Q81: 47806 | R81: 44866 | S81: 2022-2023 | T81: 5000 | V81: =F81-Q81 -> 0 | W81: =E81-R81 -> 0 | X81: =G81-T81 -> 0 | Y81: =V81+W81+X81 -> 0
A82: 2022-2023 | B82: 44866 | C82: 1 | D82: 44866 | E82: 44896 | F82: 52784 | G82: 5000 | H82: ONLINE | I82: HANUMANGARH | J82: Analyst Cum Programmer DOIT&amp;C HANUMANGARH | K82: Office of Analyst cum programmer(Dy Director) DoIT&C Hanumangarh | L82: =TEXT(E82,"mmm") -> Dec | M82: =TEXT(E82,"yy") -> 22 | N82: ok | Q82: 52784 | R82: 44896 | S82: 2022-2023 | T82: 5000 | V82: =F82-Q82 -> 0 | W82: =E82-R82 -> 0 | X82: =G82-T82 -> 0 | Y82: =V82+W82+X82 -> 0
A83: 2022-2023 | B83: 44896 | C83: 1 | D83: 44896 | E83: 44928 | F83: 60602 | G83: 5000 | H83: ONLINE | I83: HANUMANGARH | J83: Analyst Cum Programmer DOIT&amp;C HANUMANGARH | K83: Office of Analyst cum programmer(Dy Director) DoIT&C Hanumangarh | L83: =TEXT(E83,"mmm") -> Jan | M83: =TEXT(E83,"yy") -> 23 | N83: ok | Q83: 60602 | R83: 44928 | S83: 2022-2023 | T83: 5000 | V83: =F83-Q83 -> 0 | W83: =E83-R83 -> 0 | X83: =G83-T83 -> 0 | Y83: =V83+W83+X83 -> 0
A84: 2022-2023 | B84: 44927 | C84: 1 | D84: 44927 | E84: 44958 | F84: 68683 | G84: 5000 | H84: ONLINE | I84: HANUMANGARH | J84: Analyst Cum Programmer DOIT&amp;C HANUMANGARH | K84: Office of Analyst cum programmer(Dy Director) DoIT&C Hanumangarh | L84: =TEXT(E84,"mmm") -> Feb | M84: =TEXT(E84,"yy") -> 23 | N84: ok | Q84: 68683 | R84: 44958 | S84: 2022-2023 | T84: 5000 | V84: =F84-Q84 -> 0 | W84: =E84-R84 -> 0 | X84: =G84-T84 -> 0 | Y84: =V84+W84+X84 -> 0
A85: 2022-2023 | B85: 44958 | C85: 1 | D85: 44958 | E85: 44986 | F85: 77782 | G85: 5000 | H85: ONLINE | I85: HANUMANGARH | J85: Analyst Cum Programmer DOIT&amp;C HANUMANGARH | K85: Office of Analyst cum programmer(Dy Director) DoIT&C Hanumangarh | L85: =TEXT(E85,"mmm") -> Mar | M85: =TEXT(E85,"yy") -> 23 | N85: ok | Q85: 77782 | R85: 44986 | S85: 2022-2023 | T85: 5000 | V85: =F85-Q85 -> 0 | W85: =E85-R85 -> 0 | X85: =G85-T85 -> 0 | Y85: =V85+W85+X85 -> 0
A86: 2023-2024 | B86: 44986 | C86: 1 | D86: 44986 | E86: 45019 | F86: 763 | G86: 5000 | H86: ONLINE | I86: HANUMANGARH | J86: 32598-Analyst Cum Programmer DOIT&amp;C HANUMANGARH | K86: 32598-Office of Analyst cum programmer(Dy Director) DoIT&C Hanumangarh | L86: =TEXT(E86,"mmm") -> Apr | M86: =TEXT(E86,"yy") -> 23 | N86: ok | Q86: 763 | R86: 45019 | S86: 2023-2024 | T86: 5000 | V86: =F86-Q86 -> 0 | W86: =E86-R86 -> 0 | X86: =G86-T86 -> 0 | Y86: =V86+W86+X86 -> 0
A87: 2023-2024 | B87: 45017 | C87: 1 | D87: 45017 | E87: 45061 | F87: 11389 | G87: 5000 | H87: ONLINE | I87: HANUMANGARH | J87: 32598-Analyst Cum Programmer DOIT&amp;C HANUMANGARH | K87: 32598-Office of Analyst cum programmer(Dy Director) DoIT&C Hanumangarh | L87: =TEXT(E87,"mmm") -> May | M87: =TEXT(E87,"yy") -> 23 | N87: ok | Q87: 11389 | R87: 45061 | S87: 2023-2024 | T87: 5000 | V87: =F87-Q87 -> 0 | W87: =E87-R87 -> 0 | X87: =G87-T87 -> 0 | Y87: =V87+W87+X87 -> 0
A88: 2023-2024 | B88: 45047 | C88: 1 | D88: 45047 | E88: 45078 | F88: 15727 | G88: 5000 | H88: ONLINE | I88: HANUMANGARH | J88: 32598-Analyst Cum Programmer DOIT&amp;C HANUMANGARH | K88: 32598-Office of Analyst cum programmer(Dy Director) DoIT&C Hanumangarh | L88: =TEXT(E88,"mmm") -> Jun | M88: =TEXT(E88,"yy") -> 23 | N88: ok | Q88: 15727 | R88: 45078 | S88: 2023-2024 | T88: 5000 | V88: =F88-Q88 -> 0 | W88: =E88-R88 -> 0 | X88: =G88-T88 -> 0 | Y88: =V88+W88+X88 -> 0
A89: 2023-2024 | B89: 45078 | C89: 1 | D89: 45078 | E89: 45108 | F89: 19972 | G89: 5000 | H89: ONLINE | I89: HANUMANGARH | J89: 32598-Analyst Cum Programmer DOIT&amp;C HANUMANGARH | K89: 32598-Office of Analyst cum programmer(Dy Director) DoIT&C Hanumangarh | L89: =TEXT(E89,"mmm") -> Jul | M89: =TEXT(E89,"yy") -> 23 | N89: ok | Q89: 19972 | R89: 45108 | S89: 2023-2024 | T89: 5000 | V89: =F89-Q89 -> 0 | W89: =E89-R89 -> 0 | X89: =G89-T89 -> 0 | Y89: =V89+W89+X89 -> 0
A90: 2023-2024 | B90: 45108 | C90: 1 | D90: 45108 | E90: 45145 | F90: 30437 | G90: 5000 | H90: ONLINE | I90: HANUMANGARH | J90: 32598-Analyst Cum Programmer DOIT&amp;C HANUMANGARH | K90: 32598-Office of Analyst cum programmer(Dy Director) DoIT&C Hanumangarh | L90: =TEXT(E90,"mmm") -> Aug | M90: =TEXT(E90,"yy") -> 23 | N90: ok | Q90: 30437 | R90: 45145 | S90: 2023-2024 | T90: 5000 | V90: =F90-Q90 -> 0 | W90: =E90-R90 -> 0 | X90: =G90-T90 -> 0 | Y90: =V90+W90+X90 -> 0
A91: 2023-2024 | B91: 45139 | C91: 1 | D91: 45139 | E91: 45170 | F91: 34957 | G91: 5000 | H91: ONLINE | I91: HANUMANGARH | J91: 32598-Analyst Cum Programmer DOIT&amp;C HANUMANGARH | K91: 32598-Office of Analyst cum programmer(Dy Director) DoIT&C Hanumangarh | L91: =TEXT(E91,"mmm") -> Sep | M91: =TEXT(E91,"yy") -> 23 | N91: ok | Q91: 34957 | R91: 45170 | S91: 2023-2024 | T91: 5000 | V91: =F91-Q91 -> 0 | W91: =E91-R91 -> 0 | X91: =G91-T91 -> 0 | Y91: =V91+W91+X91 -> 0
A92: 2023-2024 | B92: 45170 | C92: 1 | D92: 45170 | E92: 45202 | F92: 40520 | G92: 5000 | H92: ONLINE | I92: HANUMANGARH | J92: 32598-Analyst Cum Programmer DOIT&amp;C HANUMANGARH | K92: 32598-Office of Analyst cum programmer(Dy Director) DoIT&C Hanumangarh | L92: =TEXT(E92,"mmm") -> Oct | M92: =TEXT(E92,"yy") -> 23 | N92: ok | Q92: 40520 | R92: 45202 | S92: 2023-2024 | T92: 5000 | V92: =F92-Q92 -> 0 | W92: =E92-R92 -> 0 | X92: =G92-T92 -> 0 | Y92: =V92+W92+X92 -> 0
A93: 2023-2024 | B93: 45200 | C93: 1 | D93: 45200 | E93: 45231 | F93: 45911 | G93: 5000 | H93: ONLINE | I93: HANUMANGARH | J93: 32598-Analyst Cum Programmer DOIT&amp;C HANUMANGARH | K93: 32598-Office of Analyst cum programmer(Dy Director) DoIT&C Hanumangarh | L93: =TEXT(E93,"mmm") -> Nov | M93: =TEXT(E93,"yy") -> 23 | N93: ok | Q93: 45911 | R93: 45231 | S93: 2023-2024 | T93: 5000 | V93: =F93-Q93 -> 0 | W93: =E93-R93 -> 0 | X93: =G93-T93 -> 0 | Y93: =V93+W93+X93 -> 0
... A122: 2025-2026 | B122: 46054 | C122: 1 | D122: 46054 | E122: 46083 | F122: 4840915 | G122: 12242 | H122: ONLINE | I122: SECRETARIAT | J122: ANALIST CUM PROGRAMMER DEPUTY DIRECTOR DDO DOITC | K122: INFORMATION TECHNOLOGY AND COMMUNICATION DEPARTMENT | L122: =TEXT(E122,"mmm") -> Mar | M122: =TEXT(E122,"yy") -> 26 | N122: ok | Q122: 4840915 | R122: 46083 | S122: 2025-2026 | T122: 12242 | V122: =F122-Q122 -> 0 | W122: =E122-R122 -> 0 | X122: =G122-T122 -> 0 | Y122: =V122+W122+X122 -> 0
B123: 46082 | L123: =TEXT(E123,"mmm") -> Jan | M123: =TEXT(E123,"yy") -> 00 | V123: =F123-Q123 -> 0 | W123: =E123-R123 -> 0 | X123: =G123-T123 -> 0 | Y123: =V123+W123+X123 -> 0
B124: 46113 | L124: =TEXT(E124,"mmm") -> Jan | M124: =TEXT(E124,"yy") -> 00 | V124: =F124-Q124 -> 0 | W124: =E124-R124 -> 0 | X124: =G124-T124 -> 0 | Y124: =V124+W124+X124 -> 0
B125: 46143 | L125: =TEXT(E125,"mmm") -> Jan | M125: =TEXT(E125,"yy") -> 00 | V125: =F125-Q125 -> 0 | W125: =E125-R125 -> 0 | X125: =G125-T125 -> 0 | Y125: =V125+W125+X125 -> 0
B126: 46174 | L126: =TEXT(E126,"mmm") -> Jan | M126: =TEXT(E126,"yy") -> 00 | V126: =F126-Q126 -> 0 | W126: =E126-R126 -> 0 | X126: =G126-T126 -> 0 | Y126: =V126+W126+X126 -> 0
B127: 46204 | L127: =TEXT(E127,"mmm") -> Jan | M127: =TEXT(E127,"yy") -> 00 | V127: =F127-Q127 -> 0 | W127: =E127-R127 -> 0 | X127: =G127-T127 -> 0 | Y127: =V127+W127+X127 -> 0
B128: 46235 | L128: =TEXT(E128,"mmm") -> Jan | M128: =TEXT(E128,"yy") -> 00 | V128: =F128-Q128 -> 0 | W128: =E128-R128 -> 0 | X128: =G128-T128 -> 0 | Y128: =V128+W128+X128 -> 0
B129: 46266 | L129: =TEXT(E129,"mmm") -> Jan | M129: =TEXT(E129,"yy") -> 00 | V129: =F129-Q129 -> 0 | W129: =E129-R129 -> 0 | X129: =G129-T129 -> 0 | Y129: =V129+W129+X129 -> 0
B130: 46296 | L130: =TEXT(E130,"mmm") -> Jan | M130: =TEXT(E130,"yy") -> 00 | V130: =F130-Q130 -> 0 | W130: =E130-R130 -> 0 | X130: =G130-T130 -> 0 | Y130: =V130+W130+X130 -> 0
B131: 46327 | L131: =TEXT(E131,"mmm") -> Jan | M131: =TEXT(E131,"yy") -> 00 | V131: =F131-Q131 -> 0 | W131: =E131-R131 -> 0 | X131: =G131-T131 -> 0 | Y131: =V131+W131+X131 -> 0
B132: 46357 | L132: =TEXT(E132,"mmm") -> Jan | M132: =TEXT(E132,"yy") -> 00 | V132: =F132-Q132 -> 0 | W132: =E132-R132 -> 0 | X132: =G132-T132 -> 0 | Y132: =V132+W132+X132 -> 0
B133: 46388 | L133: =TEXT(E133,"mmm") -> Jan | M133: =TEXT(E133,"yy") -> 00 | V133: =F133-Q133 -> 0 | W133: =E133-R133 -> 0 | X133: =G133-T133 -> 0 | Y133: =V133+W133+X133 -> 0
B134: 46419 | L134: =TEXT(E134,"mmm") -> Jan | M134: =TEXT(E134,"yy") -> 00 | V134: =F134-Q134 -> 0 | W134: =E134-R134 -> 0 | X134: =G134-T134 -> 0 | Y134: =V134+W134+X134 -> 0
... B373: 53693 | L373: =TEXT(E373,"mmm") -> Jan | M373: =TEXT(E373,"yy") -> 00 | V373: =F373-Q373 -> 0 | W373: =E373-R373 -> 0 | X373: =G373-T373 -> 0 | Y373: =V373+W373+X373 -> 0
B374: 53724 | L374: =TEXT(E374,"mmm") -> Jan | M374: =TEXT(E374,"yy") -> 00

Sheet NPS (SSO ID)
A1: This Data is From SIPF Portal (Through SSO ID)
J3: Missing or pending | M3: Last Update on this sheet | N3: 46110
A4: Total | E4: =SUM(E56:E196) -> 0 | F4: =SUM(F6:F2122)/2 -> 124355.5 | G4: =SUM(G6:G2122)/2 -> 124355.5 | H4: =SUM(H6:H2122)/2 -> 248711 | J4: =SUM(Table4[CORRECTION NEEDED]) -> 11
A5: S.No | B5: SI FY | C5: Month | D5: TVNO | E5: Office Name | F5: Employee Contribution | G5: Employer Contribution | H5: Total | I5: Check Status with ga 55 | J5: CORRECTION NEEDED
A6: 1 | B6: 2015-2016 | C6: FEB-2016 | D6: 43674 | E6: Community Health Center, Sangaria (Hanumangarh) | F6: 2446 | G6: 2446 | H6: 4892 | I6: ok | J6: =IF(Table4[[#This Row],[Check Status with ga 55]]="OK",0,1) -> 0
A7: 2 | B7: 2015-2016 | C7: MAR-2016 | D7: 48941 | E7: Community Health Center, Sangaria (Hanumangarh) | F7: 2446 | G7: 2446 | H7: 4892 | I7: ok | J7: =IF(Table4[[#This Row],[Check Status with ga 55]]="OK",0,1) -> 0
A8: 3 | B8: 2015-2016 | C8: MAR-2016 | D8: 49219 | E8: Community Health Center, Sangaria (Hanumangarh) | F8: 2446 | G8: 2446 | H8: 4892 | I8: ok | J8: =IF(Table4[[#This Row],[Check Status with ga 55]]="OK",0,1) -> 0
A9: 4 | B9: 2015-2016 | C9: MAR-2016 | D9: 55291 | E9: Community Health Center, Sangaria (Hanumangarh) | F9: 5463 | G9: 5463 | H9: 10926 | I9: ok | J9: =IF(Table4[[#This Row],[Check Status with ga 55]]="OK",0,1) -> 0
A10: 5 | B10: 2016-2017 | C10: APR-2016 | D10: 2179 | E10: Community Health Center, Sangaria (Hanumangarh) | F10: 2446 | G10: 2446 | H10: 4892 | I10: ok | J10: =IF(Table4[[#This Row],[Check Status with ga 55]]="OK",0,1) -> 0
A11: 6 | B11: 2016-2017 | C11: MAY-2016 | D11: 3158 | E11: Community Health Center, Sangaria (Hanumangarh) | F11: 2513 | G11: 2513 | H11: 5026 | I11: ok | J11: =IF(Table4[[#This Row],[Check Status with ga 55]]="OK",0,1) -> 0
A12: 7 | B12: 2016-2017 | C12: JUN-2016 | D12: 13185 | E12: Office of Analyst cum programmer(Dy Director) DoIT&C Hanumangarh | F12: 2513 | G12: 2513 | H12: 5026 | I12: ok | J12: =IF(Table4[[#This Row],[Check Status with ga 55]]="OK",0,1) -> 0
A13: 8 | B13: 2016-2017 | C13: JUL-2016 | D13: 14705 | E13: Office of Analyst cum programmer(Dy Director) DoIT&C Hanumangarh | F13: 2513 | G13: 2513 | H13: 5026 | I13: ok | J13: =IF(Table4[[#This Row],[Check Status with ga 55]]="OK",0,1) -> 0
A14: 9 | B14: 2016-2017 | C14: AUG-2016 | D14: 19959 | E14: Office of Analyst cum programmer(Dy Director) DoIT&C Hanumangarh | F14: 2513 | G14: 2513 | H14: 5026 | I14: ok | J14: =IF(Table4[[#This Row],[Check Status with ga 55]]="OK",0,1) -> 0
A15: 10 | B15: 2016-2017 | C15: SEP-2016 | D15: 23893 | E15: Office of Analyst cum programmer(Dy Director) DoIT&C Hanumangarh | F15: 2590 | G15: 2590 | H15: 5180 | I15: ok | J15: =IF(Table4[[#This Row],[Check Status with ga 55]]="OK",0,1) -> 0
A16: 11 | B16: 2016-2017 | C16: SEP-2016 | D16: 26364 | E16: Office of Analyst cum programmer(Dy Director) DoIT&C Hanumangarh | F16: 77 | G16: 77 | H16: 154 | I16: ok | J16: =IF(Table4[[#This Row],[Check Status with ga 55]]="OK",0,1) -> 0
A17: 12 | B17: 2016-2017 | C17: OCT-2016 | D17: 28883 | E17: Office of Analyst cum programmer(Dy Director) DoIT&C Hanumangarh | F17: 2590 | G17: 2590 | H17: 5180 | I17: ok | J17: =IF(Table4[[#This Row],[Check Status with ga 55]]="OK",0,1) -> 0
A18: 13 | B18: 2016-2017 | C18: OCT-2016 | D18: 35248 | E18: Office of Analyst cum programmer(Dy Director) DoIT&C Hanumangarh | F18: 2590 | G18: 2590 | H18: 5180 | I18: ok | J18: =IF(Table4[[#This Row],[Check Status with ga 55]]="OK",0,1) -> 0
A19: 14 | B19: 2016-2017 | C19: OCT-2016 | D19: 37085 | F19: 201 | G19: 201 | H19: 402 | I19: missing | J19: =IF(Table4[[#This Row],[Check Status with ga 55]]="OK",0,1) -> 1
A20: 15 | B20: 2016-2017 | C20: DEC-2016 | D20: 40457 | E20: Office of Analyst cum programmer(Dy Director) DoIT&C Hanumangarh | F20: 2670 | G20: 2670 | H20: 5340 | I20: ok | J20: =IF(Table4[[#This Row],[Check Status with ga 55]]="OK",0,1) -> 0
A21: 16 | B21: 2016-2017 | C21: DEC-2016 | D21: 41655 | E21: Office of Analyst cum programmer(Dy Director) DoIT&C Hanumangarh | F21: 324 | G21: 324 | H21: 648 | I21: ok | J21: =IF(Table4[[#This Row],[Check Status with ga 55]]="OK",0,1) -> 0
A22: 17 | B22: 2016-2017 | C22: JAN-2017 | D22: 45844 | E22: Office of Analyst cum programmer(Dy Director) DoIT&C Hanumangarh | F22: 2670 | G22: 2670 | H22: 5340 | I22: ok | J22: =IF(Table4[[#This Row],[Check Status with ga 55]]="OK",0,1) -> 0
A23: 18 | B23: 2016-2017 | C23: FEB-2017 | D23: 50049 | E23: Office of Analyst cum programmer(Dy Director) DoIT&C Hanumangarh | F23: 2670 | G23: 2670 | H23: 5340 | I23: ok | J23: =IF(Table4[[#This Row],[Check Status with ga 55]]="OK",0,1) -> 0
A24: 19 | B24: 2016-2017 | C24: MAR-2017 | D24: 55694 | E24: Office of Analyst cum programmer(Dy Director) DoIT&C Hanumangarh | F24: 2670 | G24: 2670 | H24: 5340 | I24: ok | J24: =IF(Table4[[#This Row],[Check Status with ga 55]]="OK",0,1) -> 0
A25: 20 | B25: 2017-2018 | C25: APR-2017 | D25: 727 | E25: Office of Analyst cum programmer(Dy Director) DoIT&C Hanumangarh | F25: 2670 | G25: 2670 | H25: 5340 | I25: ok | J25: =IF(Table4[[#This Row],[Check Status with ga 55]]="OK",0,1) -> 0
A26: 21 | B26: 2017-2018 | C26: APR-2017 | D26: 3532 | E26: Office of Analyst cum programmer(Dy Director) DoIT&C Hanumangarh | F26: 138 | G26: 138 | H26: 276 | I26: ok | J26: =IF(Table4[[#This Row],[Check Status with ga 55]]="OK",0,1) -> 0
A27: 22 | B27: 2017-2018 | C27: MAY-2017 | D27: 5192 | E27: Office of Analyst cum programmer(Dy Director) DoIT&C Hanumangarh | F27: 2716 | G27: 2716 | H27: 5432 | I27: ok | J27: =IF(Table4[[#This Row],[Check Status with ga 55]]="OK",0,1) -> 0
A28: 23 | B28: 2017-2018 | C28: JUN-2017 | D28: 10350 | E28: Office of Analyst cum programmer(Dy Director) DoIT&C Hanumangarh | F28: 2716 | G28: 2716 | H28: 5432 | I28: ok | J28: =IF(Table4[[#This Row],[Check Status with ga 55]]="OK",0,1) -> 0
A29: 24 | B29: 2017-2018 | C29: JUL-2017 | D29: 15103 | E29: Office of Analyst cum programmer(Dy Director) DoIT&C Hanumangarh | F29: 2716 | G29: 2716 | H29: 5432 | I29: ok | J29: =IF(Table4[[#This Row],[Check Status with ga 55]]="OK",0,1) -> 0
A30: 25 | B30: 2017-2018 | C30: AUG-2017 | D30: 20970 | E30: Office of Analyst cum programmer(Dy Director) DoIT&C Hanumangarh | F30: 2716 | G30: 2716 | H30: 5432 | I30: ok | J30: =IF(Table4[[#This Row],[Check Status with ga 55]]="OK",0,1) -> 0
A31: 26 | B31: 2017-2018 | C31: SEP-2017 | D31: 24832 | E31: Office of Analyst cum programmer(Dy Director) DoIT&C Hanumangarh | F31: 2716 | G31: 2716 | H31: 5432 | I31: ok | J31: =IF(Table4[[#This Row],[Check Status with ga 55]]="OK",0,1) -> 0
... A37: 32 | B37: 2017-2018 | C37: FEB-2018 | D37: 52864 | E37: Office of Analyst cum programmer(Dy Director) DoIT&C Hanumangarh | F37: 3014 | G37: 3014 | H37: 6028 | I37: ok | J37: =IF(Table4[[#This Row],[Check Status with ga 55]]="OK",0,1) -> 0
A38: 33 | B38: 2017-2018 | C38: 2017-18 | D38: 54288 | F38: 789 | G38: 789 | H38: 1578 | I38: missing | J38: =IF(Table4[[#This Row],[Check Status with ga 55]]="OK",0,1) -> 1
A39: 34 | B39: 2017-2018 | C39: MAR-2018 | D39: 59059 | E39: Office of Analyst cum programmer(Dy Director) DoIT&C Hanumangarh | F39: 3014 | G39: 3014 | H39: 6028 | I39: ok | J39: =IF(Table4[[#This Row],[Check Status with ga 55]]="OK",0,1) -> 0
A40: 35 | B40: 2018-2019 | C40: APR-2018 | D40: 2261 | E40: Office of Analyst cum programmer(Dy Director) DoIT&C Hanumangarh | F40: 3071 | G40: 3071 | H40: 6142 | I40: ok | J40: =IF(Table4[[#This Row],[Check Status with ga 55]]="OK",0,1) -> 0
A41: 36 | B41: 2018-2019 | C41: APR-2018 | D41: 4380 | E41: Office of Analyst cum programmer(Dy Director) DoIT&C Hanumangarh | F41: 114 | G41: 114 | H41: 228 | I41: ok | J41: =IF(Table4[[#This Row],[Check Status with ga 55]]="OK",0,1) -> 0
A42: 37 | B42: 2018-2019 | C42: MAY-2018 | D42: 10650 | E42: Office of Analyst cum programmer(Dy Director) DoIT&C Hanumangarh | F42: 573 | G42: 573 | H42: 1146 | I42: ok | J42: =IF(Table4[[#This Row],[Check Status with ga 55]]="OK",0,1) -> 0
A43: 38 | B43: 2018-2019 | C43: MAY-2018 | D43: 12293 | E43: Office of Analyst cum programmer(Dy Director) DoIT&C Hanumangarh | F43: 3071 | G43: 3071 | H43: 6142 | I43: ok | J43: =IF(Table4[[#This Row],[Check Status with ga 55]]="OK",0,1) -> 0
A44: 39 | B44: 2018-2019 | C44: JUN-2018 | D44: 14665 | E44: Office of Analyst cum programmer(Dy Director) DoIT&C Hanumangarh | F44: 3071 | G44: 3071 | H44: 6142 | I44: ok | J44: =IF(Table4[[#This Row],[Check Status with ga 55]]="OK",0,1) -> 0
A45: 40 | B45: 2018-2019 | C45: JUL-2018 | D45: 20799 | E45: Office of Analyst cum programmer(Dy Director) DoIT&C Hanumangarh | F45: 3071 | G45: 3071 | H45: 6142 | I45: ok | J45: =IF(Table4[[#This Row],[Check Status with ga 55]]="OK",0,1) -> 0
A46: 41 | B46: 2018-2019 | C46: JUL-2018 | D46: 27703 | E46: Office of Analyst cum programmer(Dy Director) DoIT&C Hanumangarh | F46: 573 | G46: 573 | H46: 1146 | I46: ok | J46: =IF(Table4[[#This Row],[Check Status with ga 55]]="OK",0,1) -> 0
A47: 42 | B47: 2018-2019 | C47: AUG-2018 | D47: 28948 | E47: Office of Analyst cum programmer(Dy Director) DoIT&C Hanumangarh | F47: 3167 | G47: 3167 | H47: 6334 | I47: ok | J47: =IF(Table4[[#This Row],[Check Status with ga 55]]="OK",0,1) -> 0
A48: 43 | B48: 2018-2019 | C48: SEP-2018 | D48: 38148 | E48: Office of Analyst cum programmer(Dy Director) DoIT&C Hanumangarh | F48: 3167 | G48: 3167 | H48: 6334 | I48: ok | J48: =IF(Table4[[#This Row],[Check Status with ga 55]]="OK",0,1) -> 0
A49: 44 | B49: 2018-2019 | C49: OCT-2018 | D49: 45759 | E49: Office of Analyst cum programmer(Dy Director) DoIT&C Hanumangarh | F49: 3167 | G49: 3167 | H49: 6334 | I49: ok | J49: =IF(Table4[[#This Row],[Check Status with ga 55]]="OK",0,1) -> 0
A50: 45 | B50: 2018-2019 | C50: OCT-2018 | D50: 51682 | E50: Office of Analyst cum programmer(Dy Director) DoIT&C Hanumangarh | F50: 177 | G50: 177 | H50: 354 | I50: ok | J50: =IF(Table4[[#This Row],[Check Status with ga 55]]="OK",0,1) -> 0
A51: 46 | B51: 2018-2019 | C51: 2018-19 | D51: 61581 | F51: 759 | G51: 759 | H51: 1518 | I51: missing | J51: =IF(Table4[[#This Row],[Check Status with ga 55]]="OK",0,1) -> 1
A52: 47 | B52: 2018-2019 | C52: NOV-2018 | D52: 64791 | E52: Office of Analyst cum programmer(Dy Director) DoIT&C Hanumangarh | F52: 3226 | G52: 3226 | H52: 6452 | I52: ok | J52: =IF(Table4[[#This Row],[Check Status with ga 55]]="OK",0,1) -> 0
A53: 48 | B53: 2018-2019 | C53: JAN-2019 | D53: 78389 | E53: Office of Analyst cum programmer(Dy Director) DoIT&C Hanumangarh | F53: 3226 | G53: 3226 | H53: 6452 | I53: ok | J53: =IF(Table4[[#This Row],[Check Status with ga 55]]="OK",0,1) -> 0
A54: 49 | B54: 2018-2019 | C54: FEB-2019 | D54: 84675 | E54: Office of Analyst cum programmer(Dy Director) DoIT&C Hanumangarh | F54: 3226 | G54: 3226 | H54: 6452 | I54: ok | J54: =IF(Table4[[#This Row],[Check Status with ga 55]]="OK",0,1) -> 0
A55: 50 | B55: 2018-2019 | C55: FEB-2019 | D55: 84676 | E55: Office of Analyst cum programmer(Dy Director) DoIT&C Hanumangarh | F55: 3226 | G55: 3226 | H55: 6452 | I55: ok | J55: =IF(Table4[[#This Row],[Check Status with ga 55]]="OK",0,1) -> 0
A56: 51 | B56: 2018-2019 | C56: MAR-2019 | D56: 89654 | E56: Office of Analyst cum programmer(Dy Director) DoIT&C Hanumangarh | F56: 3226 | G56: 3226 | H56: 6452 | I56: ok | J56: =IF(Table4[[#This Row],[Check Status with ga 55]]="OK",0,1) -> 0
A57: 52 | B57: 2019-2020 | C57: APR-2019 | D57: 2067 | E57: Office of Analyst cum programmer(Dy Director) DoIT&C Hanumangarh | F57: 3315 | G57: 3315 | H57: 6630 | I57: ok | J57: =IF(Table4[[#This Row],[Check Status with ga 55]]="OK",0,1) -> 0
A58: 53 | B58: 2019-2020 | C58: MAY-2019 | D58: 7783 | E58: Office of Analyst cum programmer(Dy Director) DoIT&C Hanumangarh | F58: 3315 | G58: 3315 | H58: 6630 | I58: ok | J58: =IF(Table4[[#This Row],[Check Status with ga 55]]="OK",0,1) -> 0
A59: 54 | B59: 2019-2020 | C59: 2019-20 | D59: 8498 | F59: 178 | G59: 178 | H59: 356 | I59: missing | J59: =IF(Table4[[#This Row],[Check Status with ga 55]]="OK",0,1) -> 1
A60: 55 | B60: 2019-2020 | C60: JUN-2019 | D60: 13083 | E60: Office of Analyst cum programmer(Dy Director) DoIT&C Hanumangarh | F60: 3315 | G60: 3315 | H60: 6630 | I60: ok | J60: =IF(Table4[[#This Row],[Check Status with ga 55]]="OK",0,1) -> 0
A61: 56 | B61: 2019-2020 | C61: JUL-2019 | D61: 17962 | E61: Office of Analyst cum programmer(Dy Director) DoIT&C Hanumangarh | F61: 3315 | G61: 3315 | H61: 6630 | I61: ok | J61: =IF(Table4[[#This Row],[Check Status with ga 55]]="OK",0,1) -> 0
A62: 57 | B62: 2019-2020 | C62: AUG-2019 | D62: 22832 | E62: Office of Analyst cum programmer(Dy Director) DoIT&C Hanumangarh | F62: 3416 | G62: 3416 | H62: 6832 | I62: ok | J62: =IF(Table4[[#This Row],[Check Status with ga 55]]="OK",0,1) -> 0
A63: 58 | B63: 2019-2020 | C63: SEP-2019 | D63: 28118 | E63: Office of Analyst cum programmer(Dy Director) DoIT&C Hanumangarh | F63: 3416 | G63: 3416 | H63: 6832 | I63: ok | J63: =IF(Table4[[#This Row],[Check Status with ga 55]]="OK",0,1) -> 0
A64: 59 | B64: 2019-2020 | C64: OCT-2019 | D64: 35390 | E64: Office of Analyst cum programmer(Dy Director) DoIT&C Hanumangarh | F64: 3416 | G64: 3416 | H64: 6832 | I64: ok | J64: =IF(Table4[[#This Row],[Check Status with ga 55]]="OK",0,1) -> 0
A65: 60 | B65: 2019-2020 | C65: NOV-2019 | D65: 41375 | E65: Office of Analyst cum programmer(Dy Director) DoIT&C Hanumangarh | F65: 3416 | G65: 3416 | H65: 6832 | I65: ok | J65: =IF(Table4[[#This Row],[Check Status with ga 55]]="OK",0,1) -> 0
A66: 61 | B66: 2019-2020 | C66: DEC-2019 | D66: 48035 | E66: Office of Analyst cum programmer(Dy Director) DoIT&C Hanumangarh | F66: 3416 | G66: 3416 | H66: 6832 | I66: ok | J66: =IF(Table4[[#This Row],[Check Status with ga 55]]="OK",0,1) -> 0
A67: 62 | B67: 2019-2020 | C67: JAN-2020 | D67: 53590 | E67: Office of Analyst cum programmer(Dy Director) DoIT&C Hanumangarh | F67: 3416 | G67: 3416 | H67: 6832 | I67: ok | J67: =IF(Table4[[#This Row],[Check Status with ga 55]]="OK",0,1) -> 0
A68: 63 | B68: 2019-2020 | C68: FEB-2020 | D68: 58674 | E68: Office of Analyst cum programmer(Dy Director) DoIT&C Hanumangarh | F68: 3416 | G68: 3416 | H68: 6832 | I68: ok | J68: =IF(Table4[[#This Row],[Check Status with ga 55]]="OK",0,1) -> 0
A69: 64 | B69: 2019-2020 | C69: MAR-2020 | D69: 65112 | E69: Office of Analyst cum programmer(Dy Director) DoIT&C Hanumangarh | F69: 3416 | G69: 3416 | H69: 6832 | I69: ok | J69: =IF(Table4[[#This Row],[Check Status with ga 55]]="OK",0,1) -> 0
A70: 65 | B70: 2020-2021 | C70: APR-2020 | D70: 291 | E70: Office of Analyst cum programmer(Dy Director) DoIT&C Hanumangarh | F70: 2532 | G70: 2532 | H70: 5064 | I70: ok | J70: =IF(Table4[[#This Row],[Check Status with ga 55]]="OK",0,1) -> 0
A71: 66 | B71: 2020-2021 | C71: MAY-2020 | D71: 4971 | E71: Office of Analyst cum programmer(Dy Director) DoIT&C Hanumangarh | F71: 3569 | G71: 3569 | H71: 7138 | I71: ok | J71: =IF(Table4[[#This Row],[Check Status with ga 55]]="OK",0,1) -> 0
... A90: 85 | B90: 2021-2022 | C90: SEP-2021 | D90: 28815 | E90: Office of Analyst cum programmer(Dy Director) DoIT&C Hanumangarh | F90: 4134 | G90: 4134 | H90: 8268 | I90: ok | J90: =IF(Table4[[#This Row],[Check Status with ga 55]]="OK",0,1) -> 0
A91: 87 | B91: 2021-2022 | D91: 36889 | F91: 4134 | G91: 4134 | H91: 8268 | I91: missing | J91: =IF(Table4[[#This Row],[Check Status with ga 55]]="OK",0,1) -> 1
A92: 88 | B92: 2021-2022 | D92: 40146 | F92: 4231 | G92: 4231 | H92: 8462 | I92: missing | J92: =IF(Table4[[#This Row],[Check Status with ga 55]]="OK",0,1) -> 1
A93: 88 | B93: 2021-2022 | D93: 48467 | F93: 4231 | G93: 4231 | H93: 8462 | I93: missing | J93: =IF(Table4[[#This Row],[Check Status with ga 55]]="OK",0,1) -> 1
A94: 88 | B94: 2021-2022 | D94: 55697 | F94: 4231 | G94: 4231 | H94: 8462 | I94: missing | J94: =IF(Table4[[#This Row],[Check Status with ga 55]]="OK",0,1) -> 1
A95: 88 | B95: 2021-2022 | D95: 63392 | F95: 4231 | G95: 4231 | H95: 8462 | I95: missing | J95: =IF(Table4[[#This Row],[Check Status with ga 55]]="OK",0,1) -> 1
A96: 88 | B96: 2021-2022 | D96: 52725 | F96: 291 | G96: 291 | H96: 582 | I96: missing | J96: =IF(Table4[[#This Row],[Check Status with ga 55]]="OK",0,1) -> 1
B97: 2022-2023 | I97: ok | J97: =IF(Table4[[#This Row],[Check Status with ga 55]]="OK",0,1) -> 0 | L97: ye entry pivot table ko maintain krne k liye hai ise delete na kren

Sheet NPS Site
A1: This Data is From NPS Portal | F1: Last Update on this sheet | G1: 46110 | M1: Transaction Details | Y1: Transaction Details
O2: SBI | R2: UTI | U2: LIC | AB2: SBI | AE2: UTI | AH2: LIC
A3: 1- This Sheet is having all data from single sheet. 2- In part-1 This data is taken from Contribution/Redemption Details 3- In part-2 SBI, LIC and UTI details from Transaction Details | F3: Contribution/ Redemption Details | O3: Rupee | P3: NAV | Q3: Units | R3: Rupee | S3: NAV | T3: Units | U3: Rupee | V3: NAV | W3: Units | AA3: Total | AB3: Rupee | AC3: NAV | AD3: Units | AE3: Rupee | AF3: NAV | AG3: Units | AH3: Rupee | AI3: NAV | AJ3: Units
H4: Total | I4: =SUM(I7:I1060) -> 239958 | J4: =SUM(J7:J1060) -> 239958 | K4: =SUM(K7:K1060) -> 530916 | N4: Total | O4: =SUM(O7:O1060) -> 185707.54 | Q4: =SUM(Q7:Q1060) -> 7273.541 | R4: =SUM(R7:R1060) -> 171326.71 | T4: =SUM(T7:T1060) -> 6754.8804 | U4: =SUM(U7:U1060) -> 173881.75 | W4: =SUM(W7:W1060) -> 6769.0067 | Z4: Total | AA4: =AB4+AE4+AH4 -> -25.2 | AB4: =SUM(AB7:AB1060) -> -11.22 | AD4: =SUM(AD7:AD1060) -> -0.3448 | AE4: =SUM(AE7:AE1060) -> -10.62 | AG4: =SUM(AG7:AG1060) -> -0.3268 | AH4: =SUM(AH7:AH106) -> -3.36 | AJ4: =SUM(AJ7:AJ1060) -> -0.3235
F5: Date | G5: Particulars | H5: Date | I5: Particulars | J5: Uploaded By | K5: Contribution | M5: Date | N5: Particulars | O5: SBI PENSION FUND SCHEME - STATE GOVT Amount (Rs) | P5: SBI PENSION FUND SCHEME - STATE GOVT NAV (Rs) | Q5: SBI PENSION FUND SCHEME - STATE GOVT Units | R5: UTI RETIREMENT SOLUTIONS PENSION FUND SCHEME- STATE GOVT Amount (Rs) | S5: UTI RETIREMENT SOLUTIONS PENSION FUND SCHEME- STATE GOVT NAV (Rs) | T5: UTI RETIREMENT SOLUTIONS PENSION FUND SCHEME- STATE GOVT Units | U5: LIC PENSION FUND SCHEME - STATE GOVT Amount (Rs) | V5: LIC PENSION FUND SCHEME - STATE GOVT NAV (Rs) | W5: LIC PENSION FUND SCHEME - STATE GOVT Units | Y5: Date | Z5: Particulars | AA5: Withdrawal/ deduction in units towards intermediary charges (Rs.) | AB5: SBI PENSION FUND SCHEME - STATE GOVT Amount (Rs) | AC5: SBI PENSION FUND SCHEME - STATE GOVT NAV (Rs) | AD5: SBI PENSION FUND SCHEME - STATE GOVT Units | AE5: UTI RETIREMENT SOLUTIONS PENSION FUND SCHEME- STATE GOVT Amount (Rs) | AF5: UTI RETIREMENT SOLUTIONS PENSION FUND SCHEME- STATE GOVT NAV (Rs) | AG5: UTI RETIREMENT SOLUTIONS PENSION FUND SCHEME- STATE GOVT Units | AH5: LIC PENSION FUND SCHEME - STATE GOVT Amount (Rs) | AI5: LIC PENSION FUND SCHEME - STATE GOVT NAV (Rs) | AJ5: LIC PENSION FUND SCHEME - STATE GOVT Units | AL5: =SUM(AL6:AL305) -> -51000
A6: Part 1 | F6: 42095 | G6: Opening balance | K6: 0 | M6: 01-Apr-15 | N6: Opening Balance | Q6: 0 | T6: 0 | W6: 0
F7: 42451 | G7: For January 2016 | H7: DTO State Insurance and Provident Fund Hanumangarh(REG NO.4011350)Rajasthan | I7: 2446 | J7: 2446 | K7: 4892 | M7: 22-Mar-16 | N7: By Contribution for January2016 | O7: 1663.28 | P7: 18.6269 | Q7: 89.2945 | R7: 1565.44 | S7: 18.6596 | T7: 83.8946 | U7: 1663.28 | V7: 18.8464 | W7: 88.2545 | AL7: =I7+J7-O7-R7-U7 -> 0
A8: Total Contributions | B8: =COUNTA(F7:F1000) -> 109 | F8: 42459 | G8: For December 2015 | H8: DTO State Insurance and Provident Fund Hanumangarh(REG NO.4011350)Rajasthan | I8: 2446 | J8: 2446 | K8: 4892 | M8: 30-Mar-16 | N8: By Contribution for February2016 | O8: 1663.28 | P8: 18.6549 | Q8: 89.1604 | R8: 1565.44 | S8: 18.6938 | T8: 83.7411 | U8: 1663.28 | V8: 18.8696 | W8: 88.146 | AL8: =I8+J8-O8-R8-U8 -> 0
A9: Contribution by Employee | B9: =I4 -> 239958 | F9: 42459 | G9: For February 2016 | H9: DTO State Insurance and Provident Fund Hanumangarh(REG NO.4011350)Rajasthan | I9: 2446 | J9: 2446 | K9: 4892 | M9: 30-Mar-16 | N9: By Contribution for December2015 | O9: 1663.28 | P9: 18.6549 | Q9: 89.1604 | R9: 1565.44 | S9: 18.6938 | T9: 83.7411 | U9: 1663.28 | V9: 18.8696 | W9: 88.146 | AL9: =I9+J9-O9-R9-U9 -> 0
A10: Contribution by Employer | B10: =J4 -> 239958 | F10: 42487 | G10: By Arrear - ARREARS | H10: DTO State Insurance and Provident Fund Hanumangarh(REG NO.4011350)Rajasthan | I10: 5463 | J10: 5463 | K10: 10926 | M10: 27-Apr-16 | N10: By Arrear - ARREARS | O10: 3714.84 | P10: 18.9511 | Q10: 196.0223 | R10: 3496.32 | S10: 18.983 | T10: 184.1816 | U10: 3714.84 | V10: 19.1841 | W10: 193.6416 | AL10: =I10+J10-O10-R10-U10 -> 0
A11: Total Contribution | B11: =K4 -> 530916 | F11: 42503 | G11: For March 2016 | H11: DTO State Insurance and Provident Fund Hanumangarh(REG NO.4011350)Rajasthan | I11: 2446 | J11: 2446 | K11: 4892 | M11: 13-May-16 | N11: By Contribution for March2016 | O11: 1663.28 | P11: 18.9853 | Q11: 87.6088 | R11: 1565.44 | S11: 19.0292 | T11: 82.2651 | U11: 1663.28 | V11: 19.215 | W11: 86.5615 | AL11: =I11+J11-O11-R11-U11 -> 0
F12: 42520 | G12: For April 2016 | H12: DTO State Insurance and Provident Fund Hanumangarh(REG NO.4011350)Rajasthan | I12: 2513 | J12: 2513 | K12: 5026 | M12: 30-May-16 | N12: By Contribution for April2016 | O12: 1708.84 | P12: 19.1185 | Q12: 89.3814 | R12: 1608.32 | S12: 19.1706 | T12: 83.8951 | U12: 1708.84 | V12: 19.3482 | W12: 88.3203 | AL12: =I12+J12-O12-R12-U12 -> 0
A13: Part 2 | F13: 42570 | G13: For May 2016 | H13: DTO State Insurance and Provident Fund Hanumangarh(REG NO.4011350)Rajasthan | I13: 2513 | J13: 2513 | K13: 5026 | M13: 19-Jul-16 | N13: By Contribution for May2016 | O13: 1708.84 | P13: 19.7191 | Q13: 86.6591 | R13: 1608.32 | S13: 19.7928 | T13: 81.2578 | U13: 1708.84 | V13: 19.9525 | W13: 85.6454 | AL13: =I13+J13-O13-R13-U13 -> 0
F14: 42586 | G14: For June 2016 | H14: DTO State Insurance and Provident Fund Hanumangarh(REG NO.4011350)Rajasthan | I14: 2513 | J14: 2513 | K14: 5026 | M14: 04-Aug-16 | N14: By Contribution for June2016 | O14: 1708.84 | P14: 20.037 | Q14: 85.2842 | R14: 1608.32 | S14: 20.1054 | T14: 79.9944 | U14: 1708.84 | V14: 20.2653 | W14: 84.3234 | AL14: =I14+J14-O14-R14-U14 -> 0
F15: 42612 | G15: For July 2016 | H15: DTO State Insurance and Provident Fund Hanumangarh(REG NO.4011350)Rajasthan | I15: 2513 | J15: 2513 | K15: 5026 | M15: 30-Aug-16 | N15: By Contribution for July2016 | O15: 1708.84 | P15: 20.3696 | Q15: 83.8916 | R15: 1608.32 | S15: 20.4373 | T15: 78.6953 | U15: 1708.84 | V15: 20.6094 | W15: 82.9155 | AL15: =I15+J15-O15-R15-U15 -> 0
A16: Total Contributions | B16: =COUNTA(M7:M1000) -> 109 | F16: 42642 | G16: For August 2016 | H16: DTO State Insurance and Provident Fund Hanumangarh(REG NO.4011350)Rajasthan | I16: 2590 | J16: 2590 | K16: 5180 | M16: 29-Sep-16 | N16: By Contribution for August2016 | O16: 1761.2 | P16: 20.5731 | Q16: 85.6069 | R16: 1657.6 | S16: 20.6168 | T16: 80.4004 | U16: 1761.2 | V16: 20.8065 | W16: 84.6466 | AL16: =I16+J16-O16-R16-U16 -> 0
A17: Total Amount Invested | B17: =O2 -> SBI | C17: =O4 -> 185707.54 | F17: 42653 | G17: By Arrear - ARREARS | H17: DTO State Insurance and Provident Fund Hanumangarh(REG NO.4011350)Rajasthan | I17: 77 | J17: 77 | K17: 154 | M17: 10-Oct-16 | N17: By Arrear - ARREARS | O17: 52.36 | P17: 20.8012 | Q17: 2.5171 | R17: 49.28 | S17: 20.8579 | T17: 2.3626 | U17: 52.36 | V17: 21.0323 | W17: 2.4895 | AL17: =I17+J17-O17-R17-U17 -> 0
B18: =R2 -> UTI | C18: =R4 -> 171326.71 | F18: 42667 | G18: For September 2016 | H18: DTO State Insurance and Provident Fund Hanumangarh(REG NO.4011350)Rajasthan | I18: 2590 | J18: 2590 | K18: 5180 | M18: 24-Oct-16 | N18: By Contribution for September2016 | O18: 1761.2 | P18: 20.7649 | Q18: 84.8162 | R18: 1657.6 | S18: 20.8377 | T18: 79.5481 | U18: 1761.2 | V18: 21.0155 | W18: 83.8048 | AL18: =I18+J18-O18-R18-U18 -> 0
B19: =U2 -> LIC | C19: =U4 -> 173881.75 | F19: 42692 | G19: For October 2016 | H19: DTO State Insurance and Provident Fund Hanumangarh(REG NO.4011350)Rajasthan | I19: 2590 | J19: 2590 | K19: 5180 | M19: 18-Nov-16 | N19: By Contribution for October2016 | O19: 1813 | P19: 21.0569 | Q19: 86.1 | R19: 1735.3 | S19: 21.0434 | T19: 82.4629 | U19: 1631.7 | V19: 21.2567 | W19: 76.7616 | AL19: =I19+J19-O19-R19-U19 -> 0
B20: Total | C20: =SUM(C17:C19) -> 530916 | F20: 42698 | G20: By Arrear - DA ARREARS | H20: DTO State Insurance and Provident Fund Hanumangarh(REG NO.4011350)Rajasthan | I20: 201 | J20: 201 | K20: 402 | M20: 24-Nov-16 | N20: By Arrear - DA ARREARS | O20: 140.7 | P20: 21.4049 | Q20: 6.5732 | R20: 134.67 | S20: 21.381 | T20: 6.2985 | U20: 126.63 | V20: 21.6013 | W20: 5.8621 | AL20: =I20+J20-O20-R20-U20 -> 0
F21: 42731 | G21: For November 2016 | H21: DTO State Insurance and Provident Fund Hanumangarh(REG NO.4011350)Rajasthan | I21: 2670 | J21: 2670 | K21: 5340 | M21: 27-Dec-16 | N21: By Contribution for November2016 | O21: 1869 | P21: 20.7874 | Q21: 89.9102 | R21: 1788.9 | S21: 20.7746 | T21: 86.1099 | U21: 1682.1 | V21: 20.9445 | W21: 80.3122 | AL21: =I21+J21-O21-R21-U21 -> 0
A22: Part 3 | F22: 42731 | G22: By Arrear - DA ARREARS-07/16 TO 10/16 | H22: DTO State Insurance and Provident Fund Hanumangarh(REG NO.4011350)Rajasthan | I22: 324 | J22: 324 | K22: 648 | M22: 27-Dec-16 | N22: By Arrear - DA ARREARS-07/16 TO 10/16 | O22: 226.8 | P22: 20.7874 | Q22: 10.9104 | R22: 217.08 | S22: 20.7746 | T22: 10.4492 | U22: 204.12 | V22: 20.9445 | W22: 9.7457 | AL22: =I22+J22-O22-R22-U22 -> 0
F23: 42760 | G23: For December 2016 | H23: DTO State Insurance and Provident Fund Hanumangarh(REG NO.4011350)Rajasthan | I23: 2670 | J23: 2670 | K23: 5340 | M23: 25-Jan-17 | N23: By Contribution for December2016 | O23: 1869 | P23: 21.2222 | Q23: 88.0681 | R23: 1788.9 | S23: 21.2367 | T23: 84.2362 | U23: 1682.1 | V23: 21.4283 | W23: 78.4989 | AL23: =I23+J23-O23-R23-U23 -> 0
F24: 42794 | G24: For January 2017 | H24: DTO State Insurance and Provident Fund Hanumangarh(REG NO.4011350)Rajasthan | I24: 2670 | J24: 2670 | K24: 5340 | M24: 28-Feb-17 | N24: By Contribution for January2017 | O24: 1869 | P24: 20.8415 | Q24: 89.6768 | R24: 1788.9 | S24: 20.9286 | T24: 85.4763 | U24: 1682.1 | V24: 21.1066 | W24: 79.6954 | AL24: =I24+J24-O24-R24-U24 -> 0
A25: Total Dedections | B25: =COUNTA(Y16:Y1000) -> 2 | F25: 42821 | G25: For February 2017 | H25: DTO State Insurance and Provident Fund Hanumangarh(REG NO.4011350)Rajasthan | I25: 2670 | J25: 2670 | K25: 5340 | M25: 27-Mar-17 | N25: By Contribution for February2017 | O25: 1869 | P25: 21.0947 | Q25: 88.6004 | R25: 1788.9 | S25: 21.1831 | T25: 84.4493 | U25: 1682.1 | V25: 21.3624 | W25: 78.7411 | AL25: =I25+J25-O25-R25-U25 -> 0
A26: Total Amount Deducted | B26: =AB2 -> SBI | C26: =AE4 -> -10.62 | F26: 42845 | G26: For March 2017 | H26: DTO State Insurance and Provident Fund Hanumangarh(REG NO.4011350)Rajasthan | I26: 2670 | J26: 2670 | K26: 5340 | M26: 20-Apr-17 | N26: By Contribution for March2017 | O26: 1869 | P26: 21.1828 | Q26: 88.2319 | R26: 1788.9 | S26: 21.2809 | T26: 84.0612 | U26: 1682.1 | V26: 21.4518 | W26: 78.413 | AL26: =I26+J26-O26-R26-U26 -> 0
B27: =AE2 -> UTI | C27: =AH4 -> -3.36 | F27: 42870 | G27: By Arrear - DA ARREARS | H27: DTO State Insurance and Provident Fund Hanumangarh(REG NO.4011350)Rajasthan | I27: 138 | J27: 138 | K27: 276 | M27: 15-May-17 | N27: By Arrear - DA ARREARS | O27: 96.6 | P27: 21.3717 | Q27: 4.5199 | R27: 92.46 | S27: 21.4859 | T27: 4.3032 | U27: 86.94 | V27: 21.654 | W27: 4.0149 | AL27: =I27+J27-O27-R27-U27 -> 0
B28: =AH2 -> LIC | C28: =AH4 -> -3.36 | F28: 42887 | G28: For April 2017 | H28: DTO State Insurance and Provident Fund Hanumangarh(REG NO.4011350)Rajasthan | I28: 2716 | J28: 2716 | K28: 5432 | M28: 01-Jun-17 | N28: By Contribution for April2017 | O28: 1901.2 | P28: 21.6351 | Q28: 87.8757 | R28: 1819.72 | S28: 21.7112 | T28: 83.8148 | U28: 1711.08 | V28: 21.8932 | W28: 78.1557 | AL28: =I28+J28-O28-R28-U28 -> 0
B29: Total | C29: =SUM(C26:C28) -> -17.34 | F29: 42915 | G29: For May 2017 | H29: DTO State Insurance and Provident Fund Hanumangarh(REG NO.4011350)Rajasthan | I29: 2716 | J29: 2716 | K29: 5432 | M29: 29-Jun-17 | N29: By Contribution for May2017 | O29: 1901.2 | P29: 21.9302 | Q29: 86.6932 | R29: 1819.72 | S29: 21.9881 | T29: 82.7593 | U29: 1711.08 | V29: 22.1903 | W29: 77.1093 | AL29: =I29+J29-O29-R29-U29 -> 0
F30: 42942 | G30: For June 2017 | H30: DTO State Insurance and Provident Fund Hanumangarh(REG NO.4011350)Rajasthan | I30: 2716 | J30: 2716 | K30: 5432 | M30: 26-Jul-17 | N30: By Contribution for June2017 | O30: 1901.2 | P30: 22.2469 | Q30: 85.459 | R30: 1819.72 | S30: 22.3502 | T30: 81.4185 | U30: 1711.08 | V30: 22.5235 | W30: 75.9686 | AL30: =I30+J30-O30-R30-U30 -> 0
A31: Part 4 | F31: 42982 | G31: For July 2017 | H31: DTO State Insurance and Provident Fund Hanumangarh(REG NO.4011350)Rajasthan | I31: 2716 | J31: 2716 | K31: 5432 | M31: 04-Sep-17 | N31: By Contribution for July2017 | O31: 1901.2 | P31: 22.3303 | Q31: 85.1399 | R31: 1819.72 | S31: 22.4352 | T31: 81.11 | U31: 1711.08 | V31: 22.6179 | W31: 75.6515 | AL31: =I31+J31-O31-R31-U31 -> 0
F32: 43017 | G32: For August 2017 | H32: DTO State Insurance and Provident Fund Hanumangarh(REG NO.4011350)Rajasthan | I32: 2716 | J32: 2716 | K32: 5432 | M32: 09-Oct-17 | N32: By Contribution for August2017 | O32: 1901.2 | P32: 22.2525 | Q32: 85.4375 | R32: 1819.72 | S32: 22.3766 | T32: 81.3224 | U32: 1711.08 | V32: 22.5311 | W32: 75.943 | AL32: =I32+J32-O32-R32-U32 -> 0
A33: Balance Units | B33: SBI | C33: =Q4+AD4 -> 7273.1962 | F33: 43035 | G33: For September 2017 | H33: DTO State Insurance and Provident Fund Hanumangarh(REG NO.4011350)Rajasthan | I33: 2716 | J33: 2716 | K33: 5432 | M33: 27-Oct-17 | N33: By Contribution for September2017 | O33: 1901.2 | P33: 22.3927 | Q33: 84.9026 | R33: 1819.72 | S33: 22.5348 | T33: 80.7515 | U33: 1711.08 | V33: 22.7036 | W33: 75.366 | AL33: =I33+J33-O33-R33-U33 -> 0
B34: UTI | C34: =T4+AG4 -> 6754.5536 | F34: 43053 | G34: By Arrear - ARREARS | H34: DTO State Insurance and Provident Fund Hanumangarh(REG NO.4011350)Rajasthan | I34: 105 | J34: 105 | K34: 210 | M34: 14-Nov-17 | N34: By Arrear - ARREARS | O34: 69.3 | P34: 22.2697 | Q34: 3.1118 | R34: 71.4 | S34: 22.4296 | T34: 3.1832 | U34: 69.3 | V34: 22.5442 | W34: 3.0739 | AL34: =I34+J34-O34-R34-U34 -> 0
B35: LIC | C35: =W4+AJ4 -> 6768.6832 | F35: 43069 | G35: For October 2017 | H35: DTO State Insurance and Provident Fund Hanumangarh(REG NO.4011350)Rajasthan | I35: 2751 | J35: 2751 | K35: 5502 | M35: 30-Nov-17 | N35: By Contribution for October2017 | O35: 1815.66 | P35: 22.3074 | Q35: 81.3927 | R35: 1870.68 | S35: 22.4667 | T35: 83.2645 | U35: 1815.66 | V35: 22.5998 | W35: 80.3396 | AL35: =I35+J35-O35-R35-U35 -> 0
F36: 43111 | G36: For November 2017 | H36: DTO State Insurance and Provident Fund Hanumangarh(REG NO.4011350)Rajasthan | I36: 2751 | J36: 2751 | K36: 5502 | M36: 11-Jan-18 | N36: By Contribution for November2017 | O36: 1815.66 | P36: 22.3127 | Q36: 81.3733 | R36: 1870.68 | S36: 22.5301 | T36: 83.0302 | U36: 1815.66 | V36: 22.6396 | W36: 80.1984 | AL36: =I36+J36-O36-R36-U36 -> 0
A37: Part 5 | F37: 43131 | G37: For December 2017 | H37: DTO State Insurance and Provident Fund Hanumangarh(REG NO.4011350)Rajasthan | I37: 2751 | J37: 2751 | K37: 5502 | M37: 31-Jan-18 | N37: By Contribution for December2017 | O37: 1815.66 | P37: 22.324 | Q37: 81.3321 | R37: 1870.68 | S37: 22.5261 | T37: 83.045 | U37: 1815.66 | V37: 22.6387 | W37: 80.2016 | AL37: =I37+J37-O37-R37-U37 -> 0
F38: 43171 | G38: For January 2018 | H38: DTO State Insurance and Provident Fund Hanumangarh(REG NO.4011350)Rajasthan | I38: 3014 | J38: 3014 | K38: 6028 | M38: 12-Mar-18 | N38: By Contribution for January2018 | O38: 1989.24 | P38: 22.0617 | Q38: 90.1671 | R38: 2049.52 | S38: 22.2232 | T38: 92.2243 | U38: 1989.24 | V38: 22.326 | W38: 89.0997 | AL38: =I38+J38-O38-R38-U38 -> 0
A39: Balance Amout | B39: SBI | C39: =C17+C26 -> 185696.92 | F39: 43175 | G39: By Arrear - ARREARS | H39: DTO State Insurance and Provident Fund Hanumangarh(REG NO.4011350)Rajasthan | I39: 263 | J39: 263 | K39: 526 | M39: 16-Mar-18 | N39: By Arrear - ARREARS | O39: 173.58 | P39: 22.1109 | Q39: 7.8504 | R39: 178.84 | S39: 22.2645 | T39: 8.0325 | U39: 173.58 | V39: 22.3808 | W39: 7.7557 | AL39: =I39+J39-O39-R39-U39 -> 0
B40: UTI | C40: =C18+C27 -> 171323.35 | F40: 43175 | G40: By Arrear - ARREARS | H40: DTO State Insurance and Provident Fund Hanumangarh(REG NO.4011350)Rajasthan | I40: 263 | J40: 263 | K40: 526 | M40: 16-Mar-18 | N40: By Arrear - ARREARS | O40: 173.58 | P40: 22.1109 | Q40: 7.8504 | R40: 178.84 | S40: 22.2645 | T40: 8.0325 | U40: 173.58 | V40: 22.3808 | W40: 7.7557 | AL40: =I40+J40-O40-R40-U40 -> 0
B41: LIC | C41: =C19+C28 -> 173878.39 | F41: 43175 | G41: By Arrear - ARREARS | H41: DTO State Insurance and Provident Fund Hanumangarh(REG NO.4011350)Rajasthan | I41: 263 | J41: 263 | K41: 526 | M41: 16-Mar-18 | N41: By Arrear - ARREARS | O41: 173.58 | P41: 22.1109 | Q41: 7.8504 | R41: 178.84 | S41: 22.2645 | T41: 8.0325 | U41: 173.58 | V41: 22.3808 | W41: 7.7557 | AL41: =I41+J41-O41-R41-U41 -> 0
F42: 43186 | G42: For February 2018 | H42: DTO State Insurance and Provident Fund Hanumangarh(REG NO.4011350)Rajasthan | I42: 3014 | J42: 3014 | K42: 6028 | M42: 27-Mar-18 | N42: By Contribution for February2018 | O42: 1989.24 | P42: 22.4367 | Q42: 88.66 | R42: 2049.52 | S42: 22.5742 | T42: 90.7903 | U42: 1989.24 | V42: 22.6939 | W42: 87.6552 | AL42: =I42+J42-O42-R42-U42 -> 0
F43: 43244 | G43: For March 2018 | H43: DTO State Insurance and Provident Fund Hanumangarh(REG NO.4011350)Rajasthan | I43: 3071 | J43: 3071 | K43: 6142 | M43: 24-May-18 | N43: By Contribution for March2018 | O43: 2057.57 | P43: 22.1402 | Q43: 92.9336 | R43: 2088.28 | S43: 22.2839 | T43: 93.7125 | U43: 1996.15 | V43: 22.3912 | W43: 89.1488 | AL43: =I43+J43-O43-R43-U43 -> 0
F44: 43244 | G44: By Arrear - ARREARS-DA Arrear | H44: DTO State Insurance and Provident Fund Hanumangarh(REG NO.4011350)Rajasthan | I44: 114 | J44: 114 | K44: 228 | M44: 24-May-18 | N44: By Arrear - ARREARS-DA Arrear | O44: 76.38 | P44: 22.1402 | Q44: 3.4498 | R44: 77.52 | S44: 22.2839 | T44: 3.4787 | U44: 74.1 | V44: 22.3912 | W44: 3.3093 | AL44: =I44+J44-O44-R44-U44 -> 0
F45: 43264 | G45: For April 2018 | H45: DTO State Insurance and Provident Fund Hanumangarh(REG NO.4011350)Rajasthan | I45: 3071 | J45: 3071 | K45: 6142 | M45: 13-Jun-18 | N45: By Arrear - ARREARS | O45: 383.91 | P45: 22.1971 | Q45: 17.2955 | R45: 389.64 | S45: 22.3712 | T45: 17.417 | U45: 372.45 | V45: 22.4866 | W45: 16.5631 | AL45: =I45+J45-O45-R45-U45 -> 4996
A46: Is total number of contributions equal?? | B46: =IF(B8=B16,"YES","No, Need to check part 1 and 2 total entries") -> YES | F46: 43264 | G46: By Arrear - ARREARS | H46: DTO State Insurance and Provident Fund Hanumangarh(REG NO.4011350)Rajasthan | I46: 573 | J46: 573 | K46: 1146 | M46: 13-Jun-18 | N46: By Contribution for April2018 | O46: 2057.57 | P46: 22.1971 | Q46: 92.6954 | R46: 2088.28 | S46: 22.3712 | T46: 93.3468 | U46: 1996.15 | V46: 22.4866 | W46: 88.7706 | AL46: =I46+J46-O46-R46-U46 -> -4996
F47: 43277 | G47: For May 2018 | H47: DTO State Insurance and Provident Fund Hanumangarh(REG NO.4011350)Rajasthan | I47: 3071 | J47: 3071 | K47: 6142 | M47: 26-Jun-18 | N47: By Contribution for May2018 | O47: 2057.57 | P47: 22.3357 | Q47: 92.1202 | R47: 2088.28 | S47: 22.4947 | T47: 92.8343 | U47: 1996.15 | V47: 22.5978 | W47: 88.3338 | AL47: =I47+J47-O47-R47-U47 -> 0
A48: Is total contribution equal?? | B48: =IF(B11=C20,"YES","No, Need to check part 1 and 2 total entries") -> YES | F48: 43312 | G48: By Arrear - ARREARS | H48: DTO State Insurance and Provident Fund Hanumangarh(REG NO.4011350)Rajasthan | I48: 3071 | J48: 3071 | K48: 6142 | M48: 31-Jul-18 | N48: By Arrear - ARREARS | O48: 2057.57 | P48: 22.6264 | Q48: 90.9366 | R48: 2088.28 | S48: 22.8276 | T48: 91.4804 | U48: 1996.15 | V48: 22.9083 | W48: 87.1365 | AL48: =I48+J48-O48-R48-U48 -> 0
F49: 43328 | G49: By Arrear - ARREARS | H49: DTO State Insurance and Provident Fund Hanumangarh(REG NO.4011350)Rajasthan | I49: 56 | J49: 56 | K49: 112 | M49: 16-Aug-18 | N49: By Arrear - ARREARS | O49: 37.52 | P49: 22.6562 | Q49: 1.656 | R49: 38.08 | S49: 22.8589 | T49: 1.6658 | U49: 36.4 | V49: 22.9274 | W49: 1.5876 | AL49: =I49+J49-O49-R49-U49 -> 0
F50: 43328 | G50: By Arrear - ARREARS | H50: DTO State Insurance and Provident Fund Hanumangarh(REG NO.4011350)Rajasthan | I50: 56 | J50: 56 | K50: 112 | M50: 16-Aug-18 | N50: By Arrear - ARREARS | O50: 37.52 | P50: 22.6562 | Q50: 1.656 | R50: 38.08 | S50: 22.8589 | T50: 1.6658 | U50: 36.4 | V50: 22.9274 | W50: 1.5876 | AL50: =I50+J50-O50-R50-U50 -> 0
F51: 43328 | G51: By Arrear - ARREARS | H51: DTO State Insurance and Provident Fund Hanumangarh(REG NO.4011350)Rajasthan | I51: 56 | J51: 56 | K51: 112 | M51: 16-Aug-18 | N51: By Arrear - ARREARS | O51: 37.52 | P51: 22.6562 | Q51: 1.656 | R51: 38.08 | S51: 22.8589 | T51: 1.6658 | U51: 36.4 | V51: 22.9274 | W51: 1.5876 | AL51: =I51+J51-O51-R51-U51 -> 0
F52: 43328 | G52: By Arrear - ARREARS | H52: DTO State Insurance and Provident Fund Hanumangarh(REG NO.4011350)Rajasthan | I52: 56 | J52: 56 | K52: 112 | M52: 16-Aug-18 | N52: By Arrear - ARREARS | O52: 37.52 | P52: 22.6562 | Q52: 1.656 | R52: 38.08 | S52: 22.8589 | T52: 1.6658 | U52: 36.4 | V52: 22.9274 | W52: 1.5876 | AL52: =I52+J52-O52-R52-U52 -> 0
F53: 43328 | G53: By Arrear - ARREARS | H53: DTO State Insurance and Provident Fund Hanumangarh(REG NO.4011350)Rajasthan | I53: 56 | J53: 56 | K53: 112 | M53: 16-Aug-18 | N53: By Arrear - ARREARS | O53: 37.52 | P53: 22.6562 | Q53: 1.656 | R53: 38.08 | S53: 22.8589 | T53: 1.6658 | U53: 36.4 | V53: 22.9274 | W53: 1.5876 | AL53: =I53+J53-O53-R53-U53 -> 0
A54: Amount | F54: 43328 | G54: By Arrear - ARREARS | H54: DTO State Insurance and Provident Fund Hanumangarh(REG NO.4011350)Rajasthan | I54: 56 | J54: 56 | K54: 112 | M54: 16-Aug-18 | N54: By Arrear - ARREARS | O54: 37.52 | P54: 22.6562 | Q54: 1.656 | R54: 38.08 | S54: 22.8589 | T54: 1.6658 | U54: 36.4 | V54: 22.9274 | W54: 1.5876 | AL54: =I54+J54-O54-R54-U54 -> 0
A55: Contribution/ Redemption Details | B55: =K4 -> 530916 | C55: =IF(B55=B56,"Equal","Not Equal, Need to Check") -> Equal | F55: 43328 | G55: By Arrear - ARREARS | H55: DTO State Insurance and Provident Fund Hanumangarh(REG NO.4011350)Rajasthan | I55: 79 | J55: 79 | K55: 158 | M55: 16-Aug-18 | N55: By Arrear - ARREARS | O55: 52.93 | P55: 22.6562 | Q55: 2.3362 | R55: 53.72 | S55: 22.8589 | T55: 2.35 | U55: 51.35 | V55: 22.9274 | W55: 2.2396 | AL55: =I55+J55-O55-R55-U55 -> 0
A56: Transaction Details (Deposit) | B56: =O4+R4+U4 -> 530916 | F56: 43328 | G56: By Arrear - ARREARS | H56: DTO State Insurance and Provident Fund Hanumangarh(REG NO.4011350)Rajasthan | I56: 79 | J56: 79 | K56: 158 | M56: 16-Aug-18 | N56: By Arrear - ARREARS | O56: 52.93 | P56: 22.6562 | Q56: 2.3362 | R56: 53.72 | S56: 22.8589 | T56: 2.35 | U56: 51.35 | V56: 22.9274 | W56: 2.2396 | AL56: =I56+J56-O56-R56-U56 -> 0
A57: Transaction Details (Withdraw or Charges) | B57: =AA4 -> -25.2 | F57: 43328 | G57: By Arrear - ARREARS | H57: DTO State Insurance and Provident Fund Hanumangarh(REG NO.4011350)Rajasthan | I57: 79 | J57: 79 | K57: 158 | M57: 16-Aug-18 | N57: By Arrear - ARREARS | O57: 52.93 | P57: 22.6562 | Q57: 2.3362 | R57: 53.72 | S57: 22.8589 | T57: 2.35 | U57: 51.35 | V57: 22.9274 | W57: 2.2396 | AL57: =I57+J57-O57-R57-U57 -> 0
F58: 43346 | G58: For July 2018 | H58: DTO State Insurance and Provident Fund Hanumangarh(REG NO.4011350)Rajasthan | I58: 3167 | J58: 3167 | K58: 6334 | M58: 03-Sep-18 | N58: By Contribution for July2018 | O58: 2121.89 | P58: 22.6693 | Q58: 93.6019 | R58: 2153.56 | S58: 22.8806 | T58: 94.1216 | U58: 2058.55 | V58: 22.9617 | W58: 89.6514 | AL58: =I58+J58-O58-R58-U58 -> 0
F59: 43378 | G59: For August 2018 | H59: DTO State Insurance and Provident Fund Hanumangarh(REG NO.4011350)Rajasthan | I59: 3167 | J59: 3167 | K59: 6334 | M59: 05-Oct-2018 | N59: By Contribution for August2018 | O59: 2121.89 | P59: 22.4117 | Q59: 94.6777 | R59: 2153.56 | S59: 22.496 | T59: 95.7307 | U59: 2058.55 | V59: 22.6011 | W59: 91.0818 | AL59: =I59+J59-O59-R59-U59 -> 0
F60: 43453 | G60: For September 2018 | H60: DTO State Insurance and Provident Fund Hanumangarh(REG NO.4011350)Rajasthan | I60: 3167 | J60: 3167 | K60: 6334 | M60: 19-Dec-2018 | N60: By Contribution for September2018 | O60: 2121.89 | P60: 23.7079 | Q60: 89.5013 | R60: 2153.56 | S60: 23.8219 | T60: 90.4025 | U60: 2058.55 | V60: 24.0016 | W60: 85.7671 | AL60: =I60+J60-O60-R60-U60 -> 0
F61: 43460 | G61: By Arrear - ARREARS-DA Arrear | H61: DTO State Insurance and Provident Fund Hanumangarh(REG NO.4011350)Rajasthan | I61: 59 | J61: 59 | K61: 118 | M61: 26-Dec-2018 | N61: By Arrear - ARREARS-DA Arrear | O61: 39.53 | P61: 23.7233 | Q61: 1.6662 | R61: 40.12 | S61: 23.8123 | T61: 1.6848 | U61: 38.35 | V61: 23.9992 | W61: 1.5979 | AL61: =I61+J61-O61-R61-U61 -> 0
F62: 43460 | G62: By Arrear - ARREARS-DA Arrear | H62: DTO State Insurance and Provident Fund Hanumangarh(REG NO.4011350)Rajasthan | I62: 59 | J62: 59 | K62: 118 | M62: 26-Dec-2018 | N62: By Arrear - ARREARS-DA Arrear | O62: 39.53 | P62: 23.7233 | Q62: 1.6662 | R62: 40.12 | S62: 23.8123 | T62: 1.6848 | U62: 38.35 | V62: 23.9992 | W62: 1.5979 | AL62: =I62+J62-O62-R62-U62 -> 0
F63: 43460 | G63: By Arrear - ARREARS-DA Arrear | H63: DTO State Insurance and Provident Fund Hanumangarh(REG NO.4011350)Rajasthan | I63: 59 | J63: 59 | K63: 118 | M63: 26-Dec-2018 | N63: By Arrear - ARREARS-DA Arrear | O63: 39.53 | P63: 23.7233 | Q63: 1.6662 | R63: 40.12 | S63: 23.8123 | T63: 1.6848 | U63: 38.35 | V63: 23.9992 | W63: 1.5979 | AL63: =I63+J63-O63-R63-U63 -> 0
A64: Part 6 | F64: 43472 | G64: For October 2018 | H64: DTO State Insurance and Provident Fund Hanumangarh(REG NO.4011350)Rajasthan | I64: 3226 | J64: 3226 | K64: 6452 | M64: 07-Jan-2019 | N64: By Arrear - ARREARS-SALARY ARREARS | O64: 508.53 | P64: 23.6101 | Q64: 21.5386 | R64: 516.12 | S64: 23.7159 | T64: 21.7626 | U64: 493.35 | V64: 23.8701 | W64: 20.6681 | AL64: =I64+J64-O64-R64-U64 -> 4934
F65: 43472 | G65: By Arrear - ARREARS-SALARY ARREARS | H65: DTO State Insurance and Provident Fund Hanumangarh(REG NO.4011350)Rajasthan | I65: 759 | J65: 759 | K65: 1518 | M65: 07-Jan-2019 | N65: By Contribution for October2018 | O65: 2161.42 | P65: 23.6101 | Q65: 91.5464 | R65: 2193.68 | S65: 23.7159 | T65: 92.4982 | U65: 2096.9 | V65: 23.8701 | W65: 87.8463 | AL65: =I65+J65-O65-R65-U65 -> -4934
A66: Average Per Unit Price | B66: SBI | C66: =C39/C33 -> 25.53168 | F66: 43495 | G66: For December 2018 | H66: DTO State Insurance and Provident Fund Hanumangarh(REG NO.4011350)Rajasthan | I66: 3226 | J66: 3226 | K66: 6452 | M66: 30-Jan-2019 | N66: By Contribution for December2018 | O66: 2161.42 | P66: 23.6803 | Q66: 91.275 | R66: 2193.68 | S66: 23.7737 | T66: 92.2733 | U66: 2096.9 | V66: 23.9062 | W66: 87.7136 | AL66: =I66+J66-O66-R66-U66 -> 0
B67: UTI | C67: =C40/C34 -> 25.364126 | F67: 43542 | G67: For November 2018 | H67: DTO State Insurance and Provident Fund Hanumangarh(REG NO.4011350)Rajasthan | I67: 3226 | J67: 3226 | K67: 6452 | M67: 18-Mar-2019 | N67: By Contribution for January2019 | O67: 2161.42 | P67: 24.1646 | Q67: 89.4457 | R67: 2193.68 | S67: 24.2876 | T67: 90.3209 | U67: 2096.9 | V67: 24.3819 | W67: 86.0023 | AL67: =I67+J67-O67-R67-U67 -> 0
B68: LIC | C68: =C41/C35 -> 25.688658 | F68: 43542 | G68: For January 2019 | H68: DTO State Insurance and Provident Fund Hanumangarh(REG NO.4011350)Rajasthan | I68: 3226 | J68: 3226 | K68: 6452 | M68: 18-Mar-2019 | N68: By Contribution for November2018 | O68: 2161.42 | P68: 24.1646 | Q68: 89.4457 | R68: 2193.68 | S68: 24.2876 | T68: 90.3209 | U68: 2096.9 | V68: 24.3819 | W68: 86.0023 | AL68: =I68+J68-O68-R68-U68 -> 0
F69: 43553 | G69: For February 2019 | H69: DTO State Insurance and Provident Fund Hanumangarh(REG NO.4011350)Rajasthan | I69: 3226 | J69: 3226 | K69: 6452 | M69: 29-Mar-2019 | N69: By Contribution for February2019 | O69: 2161.42 | P69: 24.3923 | Q69: 88.6107 | R69: 2193.68 | S69: 24.5115 | T69: 89.4959 | U69: 2096.9 | V69: 24.6081 | W69: 85.2117 | AL69: =I69+J69-O69-R69-U69 -> 0
F70: 43608 | G70: By Arrear - ARREARS-REGULAR DEDUCTION | H70: DTO State Insurance and Provident Fund Hanumangarh(REG NO.4011350)Rajasthan | I70: 3315 | J70: 3315 | K70: 6630 | M70: 23-May-2019 | N70: By Arrear - ARREARS-REGULAR DEDUCTION | O70: 2254.2 | P70: 24.7255 | Q70: 91.169 | R70: 2221.05 | S70: 24.7887 | T70: 89.5992 | U70: 2154.75 | V70: 24.9346 | W70: 86.416 | AL70: =I70+J70-O70-R70-U70 -> 0
F71: 43640 | G71: For April 2019 | H71: DTO State Insurance and Provident Fund Hanumangarh(REG NO.4011350)Rajasthan | I71: 3315 | J71: 3315 | K71: 6630 | M71: 24-Jun-2019 | N71: By Arrear - ARREARS-ARREARS | O71: 60.52 | P71: 25.3957 | Q71: 2.383 | R71: 59.63 | S71: 25.4314 | T71: 2.3447 | U71: 57.85 | V71: 25.6835 | W71: 2.2524 | AL71: =I71+J71-O71-R71-U71 -> 6452
A72: For Difference sheet | B72: =IF(B46="yes",0,1) -> 0 | C72: =IF(B48="yes",0,1) -> 0 | D72: =IF(C55="Equal",0,1) -> 0 | F72: 43640 | G72: By Arrear - ARREARS-ARREARS | H72: DTO State Insurance and Provident Fund Hanumangarh(REG NO.4011350)Rajasthan | I72: 89 | J72: 89 | K72: 178 | M72: 24-Jun-2019 | N72: By Arrear - ARREARS-ARREARS | O72: 60.52 | P72: 25.3957 | Q72: 2.383 | R72: 59.63 | S72: 25.4314 | T72: 2.3447 | U72: 57.85 | V72: 25.6835 | W72: 2.2524 | AL72: =I72+J72-O72-R72-U72 -> 0
B73: =SUM(B72:D72) -> 0 | F73: 43640 | G73: By Arrear - ARREARS-ARREARS | H73: DTO State Insurance and Provident Fund Hanumangarh(REG NO.4011350)Rajasthan | I73: 89 | J73: 89 | K73: 178 | M73: 24-Jun-2019 | N73: By Contribution for April2019 | O73: 2254.2 | P73: 25.3957 | Q73: 88.763 | R73: 2221.05 | S73: 25.4314 | T73: 87.3349 | U73: 2154.75 | V73: 25.6835 | W73: 83.8962 | AL73: =I73+J73-O73-R73-U73 -> -6452
F74: 43648 | G74: For May 2019 | H74: DTO State Insurance and Provident Fund Hanumangarh(REG NO.4011350)Rajasthan | I74: 3315 | J74: 3315 | K74: 6630 | M74: 02-Jul-2019 | N74: By Contribution for May2019 | O74: 2254.2 | P74: 25.457 | Q74: 88.5493 | R74: 2221.05 | S74: 25.5025 | T74: 87.0914 | U74: 2154.75 | V74: 25.7714 | W74: 83.6101 | AL74: =I74+J74-O74-R74-U74 -> 0
F75: 43691 | G75: For June 2019 | H75: DTO State Insurance and Provident Fund Hanumangarh(REG NO.4011350)Rajasthan | I75: 3315 | J75: 3315 | K75: 6630 | M75: 14-Aug-2019 | N75: By Contribution for June2019 | O75: 2254.2 | P75: 25.6598 | Q75: 87.8494 | R75: 2221.05 | S75: 25.603 | T75: 86.7495 | U75: 2154.75 | V75: 25.8072 | W75: 83.4941 | AL75: =I75+J75-O75-R75-U75 -> 0
F76: 43711 | G76: For July 2019 | H76: DTO State Insurance and Provident Fund Hanumangarh(REG NO.4011350)Rajasthan | I76: 3416 | J76: 3416 | K76: 6832 | M76: 03-Sep-2019 | N76: By Contribution for July2019 | O76: 2322.88 | P76: 25.8326 | Q76: 89.9204 | R76: 2288.72 | S76: 25.7255 | T76: 88.9669 | U76: 2220.4 | V76: 25.9533 | W76: 85.5536 | AL76: =I76+J76-O76-R76-U76 -> 0
F77: 43753 | G77: For August 2019 | H77: DTO State Insurance and Provident Fund Hanumangarh(REG NO.4011350)Rajasthan | I77: 3416 | J77: 3416 | K77: 6832 | M77: 15-Oct-2019 | N77: By Contribution for August2019 | O77: 2322.88 | P77: 25.9694 | Q77: 89.4468 | R77: 2288.72 | S77: 25.923 | T77: 88.2891 | U77: 2220.4 | V77: 26.0669 | W77: 85.1808 | AL77: =I77+J77-O77-R77-U77 -> 0
F78: 43774 | G78: For September 2019 | H78: DTO State Insurance and Provident Fund Hanumangarh(REG NO.4011350)Rajasthan | I78: 3416 | J78: 3416 | K78: 6832 | M78: 05-Nov-2019 | N78: By Contribution for September2019 | O78: 2322.88 | P78: 26.2326 | Q78: 88.5493 | R78: 2288.72 | S78: 26.2083 | T78: 87.328 | U78: 2220.4 | V78: 26.3565 | W78: 84.2448 | AL78: =I78+J78-O78-R78-U78 -> 0
F79: 43798 | G79: For October 2019 | H79: DTO State Insurance and Provident Fund Hanumangarh(REG NO.4011350)Rajasthan | I79: 3416 | J79: 3416 | K79: 6832 | M79: 29-Nov-2019 | N79: By Contribution for October2019 | O79: 2322.88 | P79: 26.4423 | Q79: 87.8471 | R79: 2288.72 | S79: 26.4349 | T79: 86.5794 | U79: 2220.4 | V79: 26.5509 | W79: 83.628 | AL79: =I79+J79-O79-R79-U79 -> 0
F80: 43803 | G80: By Voluntary Contributions | H80: eNPS - Online (5000682) | I80: 1000 | J80: 0 | K80: 1000 | M80: 04-Dec-2019 | N80: By Voluntary Contributions | O80: 340 | P80: 26.4863 | Q80: 12.8368 | R80: 335 | S80: 26.4688 | T80: 12.6564 | U80: 325 | V80: 26.5901 | W80: 12.2225 | AL80: =I80+J80-O80-R80-U80 -> 0
F81: 43843 | G81: For November 2019 | H81: DTO State Insurance and Provident Fund Hanumangarh(REG NO.4011350)Rajasthan | I81: 3416 | J81: 3416 | K81: 6832 | M81: 13-Jan-2020 | N81: By Contribution for November2019 | O81: 2322.88 | P81: 26.5542 | Q81: 87.4769 | R81: 2288.72 | S81: 26.5504 | T81: 86.2028 | U81: 2220.4 | V81: 26.5648 | W81: 83.5842 | Y81: 04-Jan-2020 | Z81: Billing for Q3 2019-2020 | AA81: -10.32 | AB81: -3.52 | AC81: 26.5541 | AD81: -0.1325 | AE81: -3.44 | AF81: 26.5406 | AG81: -0.1296 | AH81: -3.36 | AI81: 26.5812 | AJ81: -0.1264 | AL81: =I81+J81-O81-R81-U81 -> 0
F82: 43872 | G82: For December 2019 | H82: DTO State Insurance and Provident Fund Hanumangarh(REG NO.4011350)Rajasthan | I82: 3416 | J82: 3416 | K82: 6832 | M82: 11-Feb-2020 | N82: By Contribution for December2019 | O82: 2322.88 | P82: 26.9713 | Q82: 86.1241 | R82: 2288.72 | S82: 26.9498 | T82: 84.9253 | U82: 2220.4 | V82: 26.9587 | W82: 82.363 | AL82: =I82+J82-O82-R82-U82 -> 0
F83: 43893 | G83: For January 2020 | H83: DTO State Insurance and Provident Fund Hanumangarh(REG NO.4011350)Rajasthan | I83: 3416 | J83: 3416 | K83: 6832 | M83: 03-Mar-2020 | N83: By Contribution for January2020 | O83: 2322.88 | P83: 27.0321 | Q83: 85.9304 | R83: 2288.72 | S83: 26.9263 | T83: 84.9994 | U83: 2220.4 | V83: 26.9544 | W83: 82.3761 | AL83: =I83+J83-O83-R83-U83 -> 0
F84: 43924 | G84: For February 2020 | H84: DTO State Insurance and Provident Fund Hanumangarh(REG NO.4011350)Rajasthan | I84: 3416 | J84: 3416 | K84: 6832 | M84: 03-Apr-2020 | N84: By Contribution for February2020 | O84: 2322.88 | P84: 26.29 | Q84: 88.356 | R84: 2288.72 | S84: 26.0471 | T84: 87.8685 | U84: 2220.4 | V84: 26.0053 | W84: 85.3825 | AL84: =I84+J84-O84-R84-U84 -> 0
